arbiter_rr.v
module arbiter_rr #(
    parameter NUM_PORTS = 4,
    parameter PRIORITY_SCHEME = 1  // 0: Fixed priority, 1: Round-robin
) (
    input wire clk,
    input wire rst_n,
    input wire [NUM_PORTS-1:0] request,
    output reg [NUM_PORTS-1:0] grant,
    output wire active          // Indicates if any request is being serviced
);

    // Internal registers for round-robin scheme
    reg [$clog2(NUM_PORTS)-1:0] priority_ptr;
    
    // Active signal is high when any request is being serviced
    assign active = |grant;
    
    // Main arbitration logic
    always @(posedge clk or negedge rst_n) begin
        if (!rst_n) begin
            grant <= {NUM_PORTS{1'b0}};
            priority_ptr <= 0;  // Initialize priority pointer to 0
        end
        else begin
            // Default: no grants
            grant <= {NUM_PORTS{1'b0}};
            
            if (|request) begin
                if (PRIORITY_SCHEME == 0) begin
                    // Fixed priority scheme (higher index has higher priority)
                    integer i;
                    for (i = NUM_PORTS-1; i >= 0; i = i - 1) begin
                        if (request[i]) begin
                            grant[i] <= 1'b1;
                            // Once highest priority request is granted, break
                            i = -1;
                        end
                    end
                end
                else begin
                    // Round-robin priority scheme using integer variables
                    integer i;
                    integer check_idx;
                    integer ptr;
                    reg granted;
                    
                    granted = 1'b0;
                    
                    /* verilator lint_off WIDTHEXPAND */
                    ptr = priority_ptr;  // Convert to integer
                    /* verilator lint_on WIDTHEXPAND */
                    
                    // Check all ports starting from priority_ptr
                    for (i = 0; i < NUM_PORTS; i = i + 1) begin
                        check_idx = (ptr + i) % NUM_PORTS;
                        
                        if (request[check_idx] && !granted) begin
                            grant[check_idx] <= 1'b1;
                            granted = 1'b1;
                            
                            /* verilator lint_off WIDTHTRUNC */
                            // Update priority pointer for next cycle
                            priority_ptr <= (check_idx + 1) % NUM_PORTS;
                            /* verilator lint_on WIDTHTRUNC */
                        end
                    end
                end
            end
        end
    end

endmodule

arbiter_rr_sim.vcd
$version Generated by VerilatedVcd $end
$timescale 1ps $end
 $scope module TOP $end
  $var wire 1 ( clk $end
  $var wire 1 ) rst_n $end
  $var wire 4 * request [3:0] $end
  $var wire 4 + grant [3:0] $end
  $var wire 1 , active $end
  $scope module arbiter_rr $end
   $var wire 32 - NUM_PORTS [31:0] $end
   $var wire 32 . PRIORITY_SCHEME [31:0] $end
   $var wire 1 ( clk $end
   $var wire 1 ) rst_n $end
   $var wire 4 * request [3:0] $end
   $var wire 4 + grant [3:0] $end
   $var wire 1 , active $end
   $var wire 2 # priority_ptr [1:0] $end
   $scope module unnamedblk2 $end
    $var wire 32 $ i [31:0] $end
    $var wire 32 % check_idx [31:0] $end
    $var wire 32 & ptr [31:0] $end
    $var wire 1 ' granted $end
   $upscope $end
  $upscope $end
 $upscope $end
$enddefinitions $end


#0
b00 #
b00000000000000000000000000000000 $
b00000000000000000000000000000000 %
b00000000000000000000000000000000 &
0'
0(
0)
b0000 *
b0000 +
0,
b00000000000000000000000000000100 -
b00000000000000000000000000000001 .
#1
1(
#2
0(
1)
b1111 *
#3
b01 #
b00000000000000000000000000000100 $
b00000000000000000000000000000011 %
1'
1(
b0001 +
1,
#4
0(
#5
b10 #
b00000000000000000000000000000000 %
b00000000000000000000000000000001 &
1(
b0010 +
#6
0(
#7
b11 #
b00000000000000000000000000000001 %
b00000000000000000000000000000010 &
1(
b0100 +
#8
0(
#9
b00 #
b00000000000000000000000000000010 %
b00000000000000000000000000000011 &
1(
b1000 +
#10
0(
#11
b01 #
b00000000000000000000000000000011 %
b00000000000000000000000000000000 &
1(
b0001 +
#12
0(
#13
b10 #
b00000000000000000000000000000000 %
b00000000000000000000000000000001 &
1(
b0010 +
#14
0(
#15
b11 #
b00000000000000000000000000000001 %
b00000000000000000000000000000010 &
1(
b0100 +
#16
0(
#17
b00 #
b00000000000000000000000000000010 %
b00000000000000000000000000000011 &
1(
b1000 +
#18
0(
b0101 *
#19
b01 #
b00000000000000000000000000000011 %
b00000000000000000000000000000000 &
1(
b0001 +
#20
0(
b1010 *
#21
b10 #
b00000000000000000000000000000000 %
b00000000000000000000000000000001 &
1(
b0010 +
#22
0(
b0101 *
#23
b11 #
b00000000000000000000000000000001 %
b00000000000000000000000000000010 &
1(
b0100 +
#24
0(
b1010 *
#25
b00 #
b00000000000000000000000000000010 %
b00000000000000000000000000000011 &
1(
b1000 +
#26
0(
b0101 *
#27
b01 #
b00000000000000000000000000000011 %
b00000000000000000000000000000000 &
1(
b0001 +
#28
0(
b1010 *
#29
b10 #
b00000000000000000000000000000000 %
b00000000000000000000000000000001 &
1(
b0010 +
