barrel_shifter.v
module barrel_shifter #(
    parameter DATA_WIDTH = 32,
    parameter SHIFT_WIDTH = $clog2(DATA_WIDTH)
) (
    input wire [DATA_WIDTH-1:0] data_in,
    input wire [SHIFT_WIDTH-1:0] shift_amount,
    input wire shift_direction,  // 0 for right shift, 1 for left shift
    input wire rotate,           // 0 for logical shift, 1 for rotate
    output reg [DATA_WIDTH-1:0] data_out
);

    reg [DATA_WIDTH-1:0] temp_data;
    
    always @(*) begin
        temp_data = data_in;
        
        if (shift_direction) begin
            // Left shift or rotate
            if (rotate) begin
                // Rotate left
                data_out = (temp_data << shift_amount) | (temp_data >> (DATA_WIDTH - shift_amount));
            end else begin
                // Logical left shift
                data_out = temp_data << shift_amount;
            end
        end else begin
            // Right shift or rotate
            if (rotate) begin
                // Rotate right
                data_out = (temp_data >> shift_amount) | (temp_data << (DATA_WIDTH - shift_amount));
            end else begin
                // Logical right shift
                data_out = temp_data >> shift_amount;
            end
        end
    end

endmodule

barrel_shifter_sim.vcd
$version Generated by VerilatedVcd $end
$timescale 1ps $end
 $scope module TOP $end
  $var wire 32 # data_in [31:0] $end
  $var wire 5 $ shift_amount [4:0] $end
  $var wire 1 % shift_direction $end
  $var wire 1 & rotate $end
  $var wire 32 ' data_out [31:0] $end
  $scope module barrel_shifter $end
   $var wire 32 ) DATA_WIDTH [31:0] $end
   $var wire 32 * SHIFT_WIDTH [31:0] $end
   $var wire 32 # data_in [31:0] $end
   $var wire 5 $ shift_amount [4:0] $end
   $var wire 1 % shift_direction $end
   $var wire 1 & rotate $end
   $var wire 32 ' data_out [31:0] $end
   $var wire 32 ( temp_data [31:0] $end
  $upscope $end
 $upscope $end
$enddefinitions $end


#0
b00000000000000000000000000000001 #
b00000 $
0%
0&
b00000000000000000000000000000001 '
b00000000000000000000000000000001 (
b00000000000000000000000000100000 )
b00000000000000000000000000000101 *
#1
1&
#2
1%
0&
#3
1&
#4
b00001 $
0%
0&
b00000000000000000000000000000000 '
#5
1&
b10000000000000000000000000000000 '
#6
1%
0&
b00000000000000000000000000000010 '
#7
1&
#8
b00010 $
0%
0&
b00000000000000000000000000000000 '
#9
1&
b01000000000000000000000000000000 '
#10
1%
0&
b00000000000000000000000000000100 '
#11
1&
#12
b00011 $
0%
0&
b00000000000000000000000000000000 '
#13
1&
b00100000000000000000000000000000 '
#14
1%
0&
b00000000000000000000000000001000 '
#15
1&
#16
b00100 $
0%
0&
b00000000000000000000000000000000 '
#17
1&
b00010000000000000000000000000000 '
#18
1%
0&
b00000000000000000000000000010000 '
#19
1&
#20
b00101 $
0%
0&
b00000000000000000000000000000000 '
#21
1&
b00001000000000000000000000000000 '
#22
1%
0&
b00000000000000000000000000100000 '
#23
1&
#24
b00110 $
0%
0&
b00000000000000000000000000000000 '
#25
1&
b00000100000000000000000000000000 '
#26
1%
0&
b00000000000000000000000001000000 '
#27
1&
#28
b00111 $
0%
0&
b00000000000000000000000000000000 '
#29
1&
b00000010000000000000000000000000 '
#30
1%
0&
b00000000000000000000000010000000 '
#31
1&
#32
b01000 $
0%
0&
b00000000000000000000000000000000 '
#33
1&
b00000001000000000000000000000000 '
#34
1%
0&
b00000000000000000000000100000000 '
#35
1&
#36
b01001 $
0%
0&
b00000000000000000000000000000000 '
#37
1&
b00000000100000000000000000000000 '
#38
1%
0&
b00000000000000000000001000000000 '
#39
1&
#40
b01010 $
0%
0&
b00000000000000000000000000000000 '
#41
1&
b00000000010000000000000000000000 '
#42
1%
0&
b00000000000000000000010000000000 '
#43
1&
#44
b01011 $
0%
0&
b00000000000000000000000000000000 '
#45
1&
b00000000001000000000000000000000 '
#46
1%
0&
b00000000000000000000100000000000 '
#47
1&
#48
b01100 $
0%
0&
b00000000000000000000000000000000 '
#49
1&
b00000000000100000000000000000000 '
#50
1%
0&
b00000000000000000001000000000000 '
#51
1&
#52
b01101 $
0%
0&
b00000000000000000000000000000000 '
#53
1&
b00000000000010000000000000000000 '
#54
1%
0&
b00000000000000000010000000000000 '
#55
1&
#56
b01110 $
0%
0&
b00000000000000000000000000000000 '
#57
1&
b00000000000001000000000000000000 '
#58
1%
0&
b00000000000000000100000000000000 '
#59
1&
#60
b01111 $
0%
0&
b00000000000000000000000000000000 '
#61
1&
b00000000000000100000000000000000 '
#62
1%
0&
b00000000000000001000000000000000 '
#63
1&
#64
b10000 $
0%
0&
b00000000000000000000000000000000 '
#65
1&
b00000000000000010000000000000000 '
#66
1%
0&
#67
1&
#68
b10001 $
0%
0&
b00000000000000000000000000000000 '
#69
1&
b00000000000000001000000000000000 '
#70
1%
0&
b00000000000000100000000000000000 '
#71
1&
#72
b10010 $
0%
0&
b00000000000000000000000000000000 '
#73
1&
b00000000000000000100000000000000 '
#74
1%
0&
b00000000000001000000000000000000 '
#75
1&
#76
b10011 $
0%
0&
b00000000000000000000000000000000 '
#77
1&
b00000000000000000010000000000000 '
#78
1%
0&
b00000000000010000000000000000000 '
#79
1&
#80
b10100 $
0%
0&
b00000000000000000000000000000000 '
#81
1&
b00000000000000000001000000000000 '
#82
1%
0&
b00000000000100000000000000000000 '
#83
1&
#84
b10101 $
0%
0&
b00000000000000000000000000000000 '
#85
1&
b00000000000000000000100000000000 '
#86
1%
0&
b00000000001000000000000000000000 '
#87
1&
#88
b10110 $
0%
0&
b00000000000000000000000000000000 '
#89
1&
b00000000000000000000010000000000 '
#90
1%
0&
b00000000010000000000000000000000 '
#91
1&
#92
b10111 $
0%
0&
b00000000000000000000000000000000 '
#93
1&
b00000000000000000000001000000000 '
#94
1%
0&
b00000000100000000000000000000000 '
#95
1&
#96
b11000 $
0%
0&
b00000000000000000000000000000000 '
#97
1&
b00000000000000000000000100000000 '
#98
1%
0&
b00000001000000000000000000000000 '
#99
1&
#100
b11001 $
0%
0&
b00000000000000000000000000000000 '
#101
1&
b00000000000000000000000010000000 '
#102
1%
0&
b00000010000000000000000000000000 '
#103
1&
#104
b11010 $
0%
0&
b00000000000000000000000000000000 '
#105
1&
b00000000000000000000000001000000 '
#106
1%
0&
b00000100000000000000000000000000 '
#107
1&
#108
b11011 $
0%
0&
b00000000000000000000000000000000 '
#109
1&
b00000000000000000000000000100000 '
#110
1%
0&
b00001000000000000000000000000000 '
#111
1&
#112
b11100 $
0%
0&
b00000000000000000000000000000000 '
#113
1&
b00000000000000000000000000010000 '
#114
1%
0&
b00010000000000000000000000000000 '
#115
1&
#116
b11101 $
0%
0&
b00000000000000000000000000000000 '
#117
1&
b00000000000000000000000000001000 '
#118
1%
0&
b00100000000000000000000000000000 '
#119
1&
#120
b11110 $
0%
0&
b00000000000000000000000000000000 '
#121
1&
b00000000000000000000000000000100 '
#122
1%
0&
b01000000000000000000000000000000 '
#123
1&
#124
b11111 $
0%
0&
b00000000000000000000000000000000 '
#125
1&
b00000000000000000000000000000010 '
#126
1%
0&
b10000000000000000000000000000000 '
#127
1&
#128
b10000000000000000000000000000000 #
b00000 $
0%
0&
b10000000000000000000000000000000 (
#129
1&
#130
1%
0&
#131
1&
#132
b00001 $
0%
0&
b01000000000000000000000000000000 '
#133
1&
#134
1%
0&
b00000000000000000000000000000000 '
#135
1&
b00000000000000000000000000000001 '
#136
b00010 $
0%
0&
b00100000000000000000000000000000 '
#137
1&
#138
1%
0&
b00000000000000000000000000000000 '
#139
1&
b00000000000000000000000000000010 '
#140
b00011 $
0%
0&
b00010000000000000000000000000000 '
#141
1&
#142
1%
0&
b00000000000000000000000000000000 '
#143
1&
b00000000000000000000000000000100 '
#144
b00100 $
0%
0&
b00001000000000000000000000000000 '
#145
1&
#146
1%
0&
b00000000000000000000000000000000 '
#147
1&
b00000000000000000000000000001000 '
#148
b00101 $
0%
0&
b00000100000000000000000000000000 '
#149
1&
#150
1%
0&
b00000000000000000000000000000000 '
#151
1&
b00000000000000000000000000010000 '
#152
b00110 $
0%
0&
b00000010000000000000000000000000 '
#153
1&
#154
1%
0&
b00000000000000000000000000000000 '
#155
1&
b00000000000000000000000000100000 '
#156
b00111 $
0%
0&
b00000001000000000000000000000000 '
#157
1&
#158
1%
0&
b00000000000000000000000000000000 '
#159
1&
b00000000000000000000000001000000 '
#160
b01000 $
0%
0&
b00000000100000000000000000000000 '
#161
1&
#162
1%
0&
b00000000000000000000000000000000 '
#163
1&
b00000000000000000000000010000000 '
#164
b01001 $
0%
0&
b00000000010000000000000000000000 '
#165
1&
#166
1%
0&
b00000000000000000000000000000000 '
#167
1&
b00000000000000000000000100000000 '
#168
b01010 $
0%
0&
b00000000001000000000000000000000 '
#169
1&
#170
1%
0&
b00000000000000000000000000000000 '
#171
1&
b00000000000000000000001000000000 '
#172
b01011 $
0%
0&
b00000000000100000000000000000000 '
#173
1&
#174
1%
0&
b00000000000000000000000000000000 '
#175
1&
b00000000000000000000010000000000 '
#176
b01100 $
0%
0&
b00000000000010000000000000000000 '
#177
1&
#178
1%
0&
b00000000000000000000000000000000 '
#179
1&
b00000000000000000000100000000000 '
#180
b01101 $
0%
0&
b00000000000001000000000000000000 '
#181
1&
#182
1%
0&
b00000000000000000000000000000000 '
#183
1&
b00000000000000000001000000000000 '
#184
b01110 $
0%
0&
b00000000000000100000000000000000 '
#185
1&
#186
1%
0&
b00000000000000000000000000000000 '
#187
1&
b00000000000000000010000000000000 '
#188
b01111 $
0%
0&
b00000000000000010000000000000000 '
#189
1&
#190
1%
0&
b00000000000000000000000000000000 '
#191
1&
b00000000000000000100000000000000 '
#192
b10000 $
0%
0&
b00000000000000001000000000000000 '
#193
1&
#194
1%
0&
b00000000000000000000000000000000 '
#195
1&
b00000000000000001000000000000000 '
#196
b10001 $
0%
0&
b00000000000000000100000000000000 '
#197
1&
#198
1%
0&
b00000000000000000000000000000000 '
#199
1&
b00000000000000010000000000000000 '
#200
b10010 $
0%
0&
b00000000000000000010000000000000 '
#201
1&
#202
1%
0&
b00000000000000000000000000000000 '
#203
1&
b00000000000000100000000000000000 '
#204
b10011 $
0%
0&
b00000000000000000001000000000000 '
#205
1&
#206
1%
0&
b00000000000000000000000000000000 '
#207
1&
b00000000000001000000000000000000 '
#208
b10100 $
0%
0&
b00000000000000000000100000000000 '
#209
1&
#210
1%
0&
b00000000000000000000000000000000 '
#211
1&
b00000000000010000000000000000000 '
#212
b10101 $
0%
0&
b00000000000000000000010000000000 '
#213
1&
#214
1%
0&
b00000000000000000000000000000000 '
#215
1&
b00000000000100000000000000000000 '
#216
b10110 $
0%
0&
b00000000000000000000001000000000 '
#217
1&
#218
1%
0&
b00000000000000000000000000000000 '
#219
1&
b00000000001000000000000000000000 '
#220
b10111 $
0%
0&
b00000000000000000000000100000000 '
#221
1&
#222
1%
0&
b00000000000000000000000000000000 '
#223
1&
b00000000010000000000000000000000 '
#224
b11000 $
0%
0&
b00000000000000000000000010000000 '
#225
1&
#226
1%
0&
b00000000000000000000000000000000 '
#227
1&
b00000000100000000000000000000000 '
#228
b11001 $
0%
0&
b00000000000000000000000001000000 '
#229
1&
#230
1%
0&
b00000000000000000000000000000000 '
#231
1&
b00000001000000000000000000000000 '
#232
b11010 $
0%
0&
b00000000000000000000000000100000 '
#233
1&
#234
1%
0&
b00000000000000000000000000000000 '
#235
1&
b00000010000000000000000000000000 '
#236
b11011 $
0%
0&
b00000000000000000000000000010000 '
#237
1&
#238
1%
0&
b00000000000000000000000000000000 '
#239
1&
b00000100000000000000000000000000 '
#240
b11100 $
0%
0&
b00000000000000000000000000001000 '
#241
1&
#242
1%
0&
b00000000000000000000000000000000 '
#243
1&
b00001000000000000000000000000000 '
#244
b11101 $
0%
0&
b00000000000000000000000000000100 '
#245
1&
#246
1%
0&
b00000000000000000000000000000000 '
#247
1&
b00010000000000000000000000000000 '
#248
b11110 $
0%
0&
b00000000000000000000000000000010 '
#249
1&
#250
1%
0&
b00000000000000000000000000000000 '
#251
1&
b00100000000000000000000000000000 '
#252
b11111 $
0%
0&
b00000000000000000000000000000001 '
#253
1&
#254
1%
0&
b00000000000000000000000000000000 '
#255
1&
b01000000000000000000000000000000 '
#256
b01010101010101010101010101010101 #
b00000 $
0%
0&
b01010101010101010101010101010101 '
b01010101010101010101010101010101 (
#257
1&
#258
1%
0&
#259
1&
#260
b00001 $
0%
0&
b00101010101010101010101010101010 '
#261
1&
b10101010101010101010101010101010 '
#262
1%
0&
#263
1&
#264
b00010 $
0%
0&
b00010101010101010101010101010101 '
#265
1&
b01010101010101010101010101010101 '
#266
1%
0&
b01010101010101010101010101010100 '
#267
1&
b01010101010101010101010101010101 '
#268
b00011 $
0%
0&
b00001010101010101010101010101010 '
#269
1&
b10101010101010101010101010101010 '
#270
1%
0&
b10101010101010101010101010101000 '
#271
1&
b10101010101010101010101010101010 '
#272
b00100 $
0%
0&
b00000101010101010101010101010101 '
#273
1&
b01010101010101010101010101010101 '
#274
1%
0&
b01010101010101010101010101010000 '
#275
1&
b01010101010101010101010101010101 '
#276
b00101 $
0%
0&
b00000010101010101010101010101010 '
#277
1&
b10101010101010101010101010101010 '
#278
1%
0&
b10101010101010101010101010100000 '
#279
1&
b10101010101010101010101010101010 '
#280
b00110 $
0%
0&
b00000001010101010101010101010101 '
#281
1&
b01010101010101010101010101010101 '
#282
1%
0&
b01010101010101010101010101000000 '
#283
1&
b01010101010101010101010101010101 '
#284
b00111 $
0%
0&
b00000000101010101010101010101010 '
#285
1&
b10101010101010101010101010101010 '
#286
1%
0&
b10101010101010101010101010000000 '
#287
1&
b10101010101010101010101010101010 '
#288
b01000 $
0%
0&
b00000000010101010101010101010101 '
#289
1&
b01010101010101010101010101010101 '
#290
1%
0&
b01010101010101010101010100000000 '
#291
1&
b01010101010101010101010101010101 '
#292
b01001 $
0%
0&
b00000000001010101010101010101010 '
#293
1&
b10101010101010101010101010101010 '
#294
1%
0&
b10101010101010101010101000000000 '
#295
1&
b10101010101010101010101010101010 '
#296
b01010 $
0%
0&
b00000000000101010101010101010101 '
#297
1&
b01010101010101010101010101010101 '
#298
1%
0&
b01010101010101010101010000000000 '
#299
1&
b01010101010101010101010101010101 '
#300
b01011 $
0%
0&
b00000000000010101010101010101010 '
#301
1&
b10101010101010101010101010101010 '
#302
1%
0&
b10101010101010101010100000000000 '
#303
1&
b10101010101010101010101010101010 '
#304
b01100 $
0%
0&
b00000000000001010101010101010101 '
#305
1&
b01010101010101010101010101010101 '
#306
1%
0&
b01010101010101010101000000000000 '
#307
1&
b01010101010101010101010101010101 '
#308
b01101 $
0%
0&
b00000000000000101010101010101010 '
#309
1&
b10101010101010101010101010101010 '
#310
1%
0&
b10101010101010101010000000000000 '
#311
1&
b10101010101010101010101010101010 '
#312
b01110 $
0%
0&
b00000000000000010101010101010101 '
#313
1&
b01010101010101010101010101010101 '
#314
1%
0&
b01010101010101010100000000000000 '
#315
1&
b01010101010101010101010101010101 '
#316
b01111 $
0%
0&
b00000000000000001010101010101010 '
#317
1&
b10101010101010101010101010101010 '
#318
1%
0&
b10101010101010101000000000000000 '
#319
1&
b10101010101010101010101010101010 '
#320
b10000 $
0%
0&
b00000000000000000101010101010101 '
#321
1&
b01010101010101010101010101010101 '
#322
1%
0&
b01010101010101010000000000000000 '
#323
1&
b01010101010101010101010101010101 '
#324
b10001 $
0%
0&
b00000000000000000010101010101010 '
#325
1&
b10101010101010101010101010101010 '
#326
1%
0&
b10101010101010100000000000000000 '
#327
1&
b10101010101010101010101010101010 '
#328
b10010 $
0%
0&
b00000000000000000001010101010101 '
#329
1&
b01010101010101010101010101010101 '
#330
1%
0&
b01010101010101000000000000000000 '
#331
1&
b01010101010101010101010101010101 '
#332
b10011 $
0%
0&
b00000000000000000000101010101010 '
#333
1&
b10101010101010101010101010101010 '
#334
1%
0&
b10101010101010000000000000000000 '
#335
1&
b10101010101010101010101010101010 '
#336
b10100 $
0%
0&
b00000000000000000000010101010101 '
#337
1&
b01010101010101010101010101010101 '
#338
1%
0&
b01010101010100000000000000000000 '
#339
1&
b01010101010101010101010101010101 '
#340
b10101 $
0%
0&
b00000000000000000000001010101010 '
#341
1&
b10101010101010101010101010101010 '
#342
1%
0&
b10101010101000000000000000000000 '
#343
1&
b10101010101010101010101010101010 '
#344
b10110 $
0%
0&
b00000000000000000000000101010101 '
#345
1&
b01010101010101010101010101010101 '
#346
1%
0&
b01010101010000000000000000000000 '
#347
1&
b01010101010101010101010101010101 '
#348
b10111 $
0%
0&
b00000000000000000000000010101010 '
#349
1&
b10101010101010101010101010101010 '
#350
1%
0&
b10101010100000000000000000000000 '
#351
1&
b10101010101010101010101010101010 '
#352
b11000 $
0%
0&
b00000000000000000000000001010101 '
#353
1&
b01010101010101010101010101010101 '
#354
1%
0&
b01010101000000000000000000000000 '
#355
1&
b01010101010101010101010101010101 '
#356
b11001 $
0%
0&
b00000000000000000000000000101010 '
#357
1&
b10101010101010101010101010101010 '
#358
1%
0&
b10101010000000000000000000000000 '
#359
1&
b10101010101010101010101010101010 '
#360
b11010 $
0%
0&
b00000000000000000000000000010101 '
#361
1&
b01010101010101010101010101010101 '
#362
1%
0&
b01010100000000000000000000000000 '
#363
1&
b01010101010101010101010101010101 '
#364
b11011 $
0%
0&
b00000000000000000000000000001010 '
#365
1&
b10101010101010101010101010101010 '
#366
1%
0&
b10101000000000000000000000000000 '
#367
1&
b10101010101010101010101010101010 '
#368
b11100 $
0%
0&
b00000000000000000000000000000101 '
#369
1&
b01010101010101010101010101010101 '
#370
1%
0&
b01010000000000000000000000000000 '
#371
1&
b01010101010101010101010101010101 '
#372
b11101 $
0%
0&
b00000000000000000000000000000010 '
#373
1&
b10101010101010101010101010101010 '
#374
1%
0&
b10100000000000000000000000000000 '
#375
1&
b10101010101010101010101010101010 '
#376
b11110 $
0%
0&
b00000000000000000000000000000001 '
#377
1&
b01010101010101010101010101010101 '
#378
1%
0&
b01000000000000000000000000000000 '
#379
1&
b01010101010101010101010101010101 '
#380
b11111 $
0%
0&
b00000000000000000000000000000000 '
#381
1&
b10101010101010101010101010101010 '
#382
1%
0&
b10000000000000000000000000000000 '
#383
1&
b10101010101010101010101010101010 '
#384
b10101010101010101010101010101010 #
b00000 $
0%
0&
b10101010101010101010101010101010 (
#385
1&
#386
1%
0&
#387
1&
#388
b00001 $
0%
0&
b01010101010101010101010101010101 '
#389
1&
#390
1%
0&
b01010101010101010101010101010100 '
#391
1&
b01010101010101010101010101010101 '
#392
b00010 $
0%
0&
b00101010101010101010101010101010 '
#393
1&
b10101010101010101010101010101010 '
#394
1%
0&
b10101010101010101010101010101000 '
#395
1&
b10101010101010101010101010101010 '
#396
b00011 $
0%
0&
b00010101010101010101010101010101 '
#397
1&
b01010101010101010101010101010101 '
#398
1%
0&
b01010101010101010101010101010000 '
#399
1&
b01010101010101010101010101010101 '
#400
b00100 $
0%
0&
b00001010101010101010101010101010 '
#401
1&
b10101010101010101010101010101010 '
#402
1%
0&
b10101010101010101010101010100000 '
#403
1&
b10101010101010101010101010101010 '
#404
b00101 $
0%
0&
b00000101010101010101010101010101 '
#405
1&
b01010101010101010101010101010101 '
#406
1%
0&
b01010101010101010101010101000000 '
#407
1&
b01010101010101010101010101010101 '
#408
b00110 $
0%
0&
b00000010101010101010101010101010 '
#409
1&
b10101010101010101010101010101010 '
#410
1%
0&
b10101010101010101010101010000000 '
#411
1&
b10101010101010101010101010101010 '
#412
b00111 $
0%
0&
b00000001010101010101010101010101 '
#413
1&
b01010101010101010101010101010101 '
#414
1%
0&
b01010101010101010101010100000000 '
#415
1&
b01010101010101010101010101010101 '
#416
b01000 $
0%
0&
b00000000101010101010101010101010 '
#417
1&
b10101010101010101010101010101010 '
#418
1%
0&
b10101010101010101010101000000000 '
#419
1&
b10101010101010101010101010101010 '
#420
b01001 $
0%
0&
b00000000010101010101010101010101 '
#421
1&
b01010101010101010101010101010101 '
#422
1%
0&
b01010101010101010101010000000000 '
#423
1&
b01010101010101010101010101010101 '
#424
b01010 $
0%
0&
b00000000001010101010101010101010 '
#425
1&
b10101010101010101010101010101010 '
#426
1%
0&
b10101010101010101010100000000000 '
#427
1&
b10101010101010101010101010101010 '
#428
b01011 $
0%
0&
b00000000000101010101010101010101 '
#429
1&
b01010101010101010101010101010101 '
#430
1%
0&
b01010101010101010101000000000000 '
#431
1&
b01010101010101010101010101010101 '
#432
b01100 $
0%
0&
b00000000000010101010101010101010 '
#433
1&
b10101010101010101010101010101010 '
#434
1%
0&
b10101010101010101010000000000000 '
#435
1&
b10101010101010101010101010101010 '
#436
b01101 $
0%
0&
b00000000000001010101010101010101 '
#437
1&
b01010101010101010101010101010101 '
#438
1%
0&
b01010101010101010100000000000000 '
#439
1&
b01010101010101010101010101010101 '
#440
b01110 $
0%
0&
b00000000000000101010101010101010 '
#441
1&
b10101010101010101010101010101010 '
#442
1%
0&
b10101010101010101000000000000000 '
#443
1&
b10101010101010101010101010101010 '
#444
b01111 $
0%
0&
b00000000000000010101010101010101 '
#445
1&
b01010101010101010101010101010101 '
#446
1%
0&
b01010101010101010000000000000000 '
#447
1&
b01010101010101010101010101010101 '
#448
b10000 $
0%
0&
b00000000000000001010101010101010 '
#449
1&
b10101010101010101010101010101010 '
#450
1%
0&
b10101010101010100000000000000000 '
#451
1&
b10101010101010101010101010101010 '
#452
b10001 $
0%
0&
b00000000000000000101010101010101 '
#453
1&
b01010101010101010101010101010101 '
#454
1%
0&
b01010101010101000000000000000000 '
#455
1&
b01010101010101010101010101010101 '
#456
b10010 $
0%
0&
b00000000000000000010101010101010 '
#457
1&
b10101010101010101010101010101010 '
#458
1%
0&
b10101010101010000000000000000000 '
#459
1&
b10101010101010101010101010101010 '
#460
b10011 $
0%
0&
b00000000000000000001010101010101 '
#461
1&
b01010101010101010101010101010101 '
#462
1%
0&
b01010101010100000000000000000000 '
#463
1&
b01010101010101010101010101010101 '
#464
b10100 $
0%
0&
b00000000000000000000101010101010 '
#465
1&
b10101010101010101010101010101010 '
#466
1%
0&
b10101010101000000000000000000000 '
#467
1&
b10101010101010101010101010101010 '
#468
b10101 $
0%
0&
b00000000000000000000010101010101 '
#469
1&
b01010101010101010101010101010101 '
#470
1%
0&
b01010101010000000000000000000000 '
#471
1&
b01010101010101010101010101010101 '
#472
b10110 $
0%
0&
b00000000000000000000001010101010 '
#473
1&
b10101010101010101010101010101010 '
#474
1%
0&
b10101010100000000000000000000000 '
#475
1&
b10101010101010101010101010101010 '
#476
b10111 $
0%
0&
b00000000000000000000000101010101 '
#477
1&
b01010101010101010101010101010101 '
#478
1%
0&
b01010101000000000000000000000000 '
#479
1&
b01010101010101010101010101010101 '
#480
b11000 $
0%
0&
b00000000000000000000000010101010 '
#481
1&
b10101010101010101010101010101010 '
#482
1%
0&
b10101010000000000000000000000000 '
#483
1&
b10101010101010101010101010101010 '
#484
b11001 $
0%
0&
b00000000000000000000000001010101 '
#485
1&
b01010101010101010101010101010101 '
#486
1%
0&
b01010100000000000000000000000000 '
#487
1&
b01010101010101010101010101010101 '
#488
b11010 $
0%
0&
b00000000000000000000000000101010 '
#489
1&
b10101010101010101010101010101010 '
#490
1%
0&
b10101000000000000000000000000000 '
#491
1&
b10101010101010101010101010101010 '
#492
b11011 $
0%
0&
b00000000000000000000000000010101 '
#493
1&
b01010101010101010101010101010101 '
#494
1%
0&
b01010000000000000000000000000000 '
#495
1&
b01010101010101010101010101010101 '
#496
b11100 $
0%
0&
b00000000000000000000000000001010 '
#497
1&
b10101010101010101010101010101010 '
#498
1%
0&
b10100000000000000000000000000000 '
#499
1&
b10101010101010101010101010101010 '
#500
b11101 $
0%
0&
b00000000000000000000000000000101 '
#501
1&
b01010101010101010101010101010101 '
#502
1%
0&
b01000000000000000000000000000000 '
#503
1&
b01010101010101010101010101010101 '
#504
b11110 $
0%
0&
b00000000000000000000000000000010 '
#505
1&
b10101010101010101010101010101010 '
#506
1%
0&
b10000000000000000000000000000000 '
#507
1&
b10101010101010101010101010101010 '
#508
b11111 $
0%
0&
b00000000000000000000000000000001 '
#509
1&
b01010101010101010101010101010101 '
#510
1%
0&
b00000000000000000000000000000000 '
#511
1&
b01010101010101010101010101010101 '
#512
b11111111111111111111111111111111 #
b00000 $
0%
0&
b11111111111111111111111111111111 '
b11111111111111111111111111111111 (
#513
1&
#514
1%
0&
#515
1&
#516
b00001 $
0%
0&
b01111111111111111111111111111111 '
#517
1&
b11111111111111111111111111111111 '
#518
1%
0&
b11111111111111111111111111111110 '
#519
1&
b11111111111111111111111111111111 '
#520
b00010 $
0%
0&
b00111111111111111111111111111111 '
#521
1&
b11111111111111111111111111111111 '
#522
1%
0&
b11111111111111111111111111111100 '
#523
1&
b11111111111111111111111111111111 '
#524
b00011 $
0%
0&
b00011111111111111111111111111111 '
#525
1&
b11111111111111111111111111111111 '
#526
1%
0&
b11111111111111111111111111111000 '
#527
1&
b11111111111111111111111111111111 '
#528
b00100 $
0%
0&
b00001111111111111111111111111111 '
#529
1&
b11111111111111111111111111111111 '
#530
1%
0&
b11111111111111111111111111110000 '
#531
1&
b11111111111111111111111111111111 '
#532
b00101 $
0%
0&
b00000111111111111111111111111111 '
#533
1&
b11111111111111111111111111111111 '
#534
1%
0&
b11111111111111111111111111100000 '
#535
1&
b11111111111111111111111111111111 '
#536
b00110 $
0%
0&
b00000011111111111111111111111111 '
#537
1&
b11111111111111111111111111111111 '
#538
1%
0&
b11111111111111111111111111000000 '
#539
1&
b11111111111111111111111111111111 '
#540
b00111 $
0%
0&
b00000001111111111111111111111111 '
#541
1&
b11111111111111111111111111111111 '
#542
1%
0&
b11111111111111111111111110000000 '
#543
1&
b11111111111111111111111111111111 '
#544
b01000 $
0%
0&
b00000000111111111111111111111111 '
#545
1&
b11111111111111111111111111111111 '
#546
1%
0&
b11111111111111111111111100000000 '
#547
1&
b11111111111111111111111111111111 '
#548
b01001 $
0%
0&
b00000000011111111111111111111111 '
#549
1&
b11111111111111111111111111111111 '
#550
1%
0&
b11111111111111111111111000000000 '
#551
1&
b11111111111111111111111111111111 '
#552
b01010 $
0%
0&
b00000000001111111111111111111111 '
#553
1&
b11111111111111111111111111111111 '
#554
1%
0&
b11111111111111111111110000000000 '
#555
1&
b11111111111111111111111111111111 '
#556
b01011 $
0%
0&
b00000000000111111111111111111111 '
#557
1&
b11111111111111111111111111111111 '
#558
1%
0&
b11111111111111111111100000000000 '
#559
1&
b11111111111111111111111111111111 '
#560
b01100 $
0%
0&
b00000000000011111111111111111111 '
#561
1&
b11111111111111111111111111111111 '
#562
1%
0&
b11111111111111111111000000000000 '
#563
1&
b11111111111111111111111111111111 '
#564
b01101 $
0%
0&
b00000000000001111111111111111111 '
#565
1&
b11111111111111111111111111111111 '
#566
1%
0&
b11111111111111111110000000000000 '
#567
1&
b11111111111111111111111111111111 '
#568
b01110 $
0%
0&
b00000000000000111111111111111111 '
#569
1&
b11111111111111111111111111111111 '
#570
1%
0&
b11111111111111111100000000000000 '
#571
1&
b11111111111111111111111111111111 '
#572
b01111 $
0%
0&
b00000000000000011111111111111111 '
#573
1&
b11111111111111111111111111111111 '
#574
1%
0&
b11111111111111111000000000000000 '
#575
1&
b11111111111111111111111111111111 '
#576
b10000 $
0%
0&
b00000000000000001111111111111111 '
#577
1&
b11111111111111111111111111111111 '
#578
1%
0&
b11111111111111110000000000000000 '
#579
1&
b11111111111111111111111111111111 '
#580
b10001 $
0%
0&
b00000000000000000111111111111111 '
#581
1&
b11111111111111111111111111111111 '
#582
1%
0&
b11111111111111100000000000000000 '
#583
1&
b11111111111111111111111111111111 '
#584
b10010 $
0%
0&
b00000000000000000011111111111111 '
#585
1&
b11111111111111111111111111111111 '
#586
1%
0&
b11111111111111000000000000000000 '
#587
1&
b11111111111111111111111111111111 '
#588
b10011 $
0%
0&
b00000000000000000001111111111111 '
#589
1&
b11111111111111111111111111111111 '
#590
1%
0&
b11111111111110000000000000000000 '
#591
1&
b11111111111111111111111111111111 '
#592
b10100 $
0%
0&
b00000000000000000000111111111111 '
#593
1&
b11111111111111111111111111111111 '
#594
1%
0&
b11111111111100000000000000000000 '
#595
1&
b11111111111111111111111111111111 '
#596
b10101 $
0%
0&
b00000000000000000000011111111111 '
#597
1&
b11111111111111111111111111111111 '
#598
1%
0&
b11111111111000000000000000000000 '
#599
1&
b11111111111111111111111111111111 '
#600
b10110 $
0%
0&
b00000000000000000000001111111111 '
#601
1&
b11111111111111111111111111111111 '
#602
1%
0&
b11111111110000000000000000000000 '
#603
1&
b11111111111111111111111111111111 '
#604
b10111 $
0%
0&
b00000000000000000000000111111111 '
#605
1&
b11111111111111111111111111111111 '
#606
1%
0&
b11111111100000000000000000000000 '
#607
1&
b11111111111111111111111111111111 '
#608
b11000 $
0%
0&
b00000000000000000000000011111111 '
#609
1&
b11111111111111111111111111111111 '
#610
1%
0&
b11111111000000000000000000000000 '
#611
1&
b11111111111111111111111111111111 '
#612
b11001 $
0%
0&
b00000000000000000000000001111111 '
#613
1&
b11111111111111111111111111111111 '
#614
1%
0&
b11111110000000000000000000000000 '
#615
1&
b11111111111111111111111111111111 '
#616
b11010 $
0%
0&
b00000000000000000000000000111111 '
#617
1&
b11111111111111111111111111111111 '
#618
1%
0&
b11111100000000000000000000000000 '
#619
1&
b11111111111111111111111111111111 '
#620
b11011 $
0%
0&
b00000000000000000000000000011111 '
#621
1&
b11111111111111111111111111111111 '
#622
1%
0&
b11111000000000000000000000000000 '
#623
1&
b11111111111111111111111111111111 '
#624
b11100 $
0%
0&
b00000000000000000000000000001111 '
#625
1&
b11111111111111111111111111111111 '
#626
1%
0&
b11110000000000000000000000000000 '
#627
1&
b11111111111111111111111111111111 '
#628
b11101 $
0%
0&
b00000000000000000000000000000111 '
#629
1&
b11111111111111111111111111111111 '
#630
1%
0&
b11100000000000000000000000000000 '
#631
1&
b11111111111111111111111111111111 '
#632
b11110 $
0%
0&
b00000000000000000000000000000011 '
