barrel_rotator.v
module barrel_rotator #(
    parameter DATA_WIDTH = 8,
    parameter SHIFT_WIDTH = $clog2(DATA_WIDTH)
) (
    input wire [DATA_WIDTH-1:0] data_in,
    input wire [SHIFT_WIDTH-1:0] rotate_amount,
    input wire direction,  // 0 for right rotation, 1 for left rotation
    output reg [DATA_WIDTH-1:0] data_out
);

    // Implementation using a shift-and-or approach
    always @(*) begin
        data_out = data_in; // Default
        
        if (direction == 1'b0) begin
            // Right rotation
            case (rotate_amount)
                3'd0: data_out = data_in;
                3'd1: data_out = {data_in[0], data_in[DATA_WIDTH-1:1]};
                3'd2: data_out = {data_in[1:0], data_in[DATA_WIDTH-1:2]};
                3'd3: data_out = {data_in[2:0], data_in[DATA_WIDTH-1:3]};
                3'd4: data_out = {data_in[3:0], data_in[DATA_WIDTH-1:4]};
                3'd5: data_out = {data_in[4:0], data_in[DATA_WIDTH-1:5]};
                3'd6: data_out = {data_in[5:0], data_in[DATA_WIDTH-1:6]};
                3'd7: data_out = {data_in[6:0], data_in[DATA_WIDTH-1:7]};
                default: data_out = data_in;
            endcase
        end else begin
            // Left rotation
            case (rotate_amount)
                3'd0: data_out = data_in;
                3'd1: data_out = {data_in[DATA_WIDTH-2:0], data_in[DATA_WIDTH-1]};
                3'd2: data_out = {data_in[DATA_WIDTH-3:0], data_in[DATA_WIDTH-1:DATA_WIDTH-2]};
                3'd3: data_out = {data_in[DATA_WIDTH-4:0], data_in[DATA_WIDTH-1:DATA_WIDTH-3]};
                3'd4: data_out = {data_in[DATA_WIDTH-5:0], data_in[DATA_WIDTH-1:DATA_WIDTH-4]};
                3'd5: data_out = {data_in[DATA_WIDTH-6:0], data_in[DATA_WIDTH-1:DATA_WIDTH-5]};
                3'd6: data_out = {data_in[DATA_WIDTH-7:0], data_in[DATA_WIDTH-1:DATA_WIDTH-6]};
                3'd7: data_out = {data_in[DATA_WIDTH-8:0], data_in[DATA_WIDTH-1:DATA_WIDTH-7]};
                default: data_out = data_in;
            endcase
        end
    end

endmodule

barrel_rotator_sim.vcd
$version Generated by VerilatedVcd $end
$timescale 1ps $end
 $scope module TOP $end
  $var wire 8 # data_in [7:0] $end
  $var wire 3 $ rotate_amount [2:0] $end
  $var wire 1 % direction $end
  $var wire 8 & data_out [7:0] $end
  $scope module barrel_rotator $end
   $var wire 32 ' DATA_WIDTH [31:0] $end
   $var wire 32 ( SHIFT_WIDTH [31:0] $end
   $var wire 8 # data_in [7:0] $end
   $var wire 3 $ rotate_amount [2:0] $end
   $var wire 1 % direction $end
   $var wire 8 & data_out [7:0] $end
  $upscope $end
 $upscope $end
$enddefinitions $end


#0
b00000001 #
b000 $
0%
b00000001 &
b00000000000000000000000000001000 '
b00000000000000000000000000000011 (
#1
1%
#2
b001 $
0%
b10000000 &
#3
1%
b00000010 &
#4
b010 $
0%
b01000000 &
#5
1%
b00000100 &
#6
b011 $
0%
b00100000 &
#7
1%
b00001000 &
#8
b100 $
0%
b00010000 &
#9
1%
#10
b101 $
0%
b00001000 &
#11
1%
b00100000 &
#12
b110 $
0%
b00000100 &
#13
1%
b01000000 &
#14
b111 $
0%
b00000010 &
#15
1%
b10000000 &
#16
b10000000 #
b000 $
0%
#17
1%
#18
b001 $
0%
b01000000 &
#19
1%
b00000001 &
#20
b010 $
0%
b00100000 &
#21
1%
b00000010 &
#22
b011 $
0%
b00010000 &
#23
1%
b00000100 &
#24
b100 $
0%
b00001000 &
#25
1%
#26
b101 $
0%
b00000100 &
#27
1%
b00010000 &
#28
b110 $
0%
b00000010 &
#29
1%
b00100000 &
#30
b111 $
0%
b00000001 &
#31
1%
b01000000 &
#32
b01010101 #
b000 $
0%
b01010101 &
#33
1%
#34
b001 $
0%
b10101010 &
#35
1%
#36
b010 $
0%
b01010101 &
#37
1%
#38
b011 $
0%
b10101010 &
#39
1%
#40
b100 $
0%
b01010101 &
#41
1%
#42
b101 $
0%
b10101010 &
#43
1%
#44
b110 $
0%
b01010101 &
#45
1%
#46
b111 $
0%
b10101010 &
#47
1%
#48
b10101010 #
b000 $
0%
#49
1%
#50
b001 $
0%
b01010101 &
#51
1%
#52
b010 $
0%
b10101010 &
#53
1%
#54
b011 $
0%
b01010101 &
#55
1%
#56
b100 $
0%
b10101010 &
#57
1%
#58
b101 $
0%
b01010101 &
#59
1%
#60
b110 $
0%
b10101010 &
#61
1%
#62
b111 $
0%
b01010101 &
#63
1%
#64
b11111111 #
b000 $
0%
b11111111 &
#65
1%
#66
b001 $
0%
#67
1%
#68
b010 $
0%
#69
1%
#70
b011 $
0%
#71
1%
#72
b100 $
0%
#73
1%
#74
b101 $
0%
#75
1%
#76
b110 $
0%
#77
1%
#78
b111 $
0%
#79
1%
#80
b00010010 #
b000 $
0%
b00010010 &
#81
1%
#82
b001 $
0%
b00001001 &
#83
1%
b00100100 &
#84
b010 $
0%
b10000100 &
#85
1%
b01001000 &
#86
b011 $
0%
b01000010 &
#87
1%
b10010000 &
#88
b100 $
0%
b00100001 &
#89
1%
#90
b101 $
0%
b10010000 &
#91
1%
b01000010 &
#92
b110 $
0%
b01001000 &
#93
1%
b10000100 &
#94
b111 $
0%
b00100100 &
#95
1%
b00001001 &
#96
b00001111 #
b000 $
0%
b00001111 &
#97
1%
#98
b001 $
0%
b10000111 &
#99
1%
b00011110 &
#100
b010 $
0%
b11000011 &
#101
1%
b00111100 &
#102
b011 $
0%
b11100001 &
#103
1%
b01111000 &
#104
b100 $
0%
b11110000 &
#105
1%
#106
b101 $
0%
b01111000 &
#107
1%
b11100001 &
#108
b110 $
0%
b00111100 &
#109
1%
b11000011 &
#110
b111 $
0%
b00011110 &
#111
1%
b10000111 &
#112
b11110000 #
b000 $
0%
b11110000 &
#113
1%
#114
b001 $
0%
b01111000 &
#115
1%
b11100001 &
#116
b010 $
0%
b00111100 &
#117
1%
b11000011 &
#118
b011 $
0%
b00011110 &
#119
1%
b10000111 &
#120
b100 $
0%
b00001111 &
#121
1%
#122
b101 $
0%
b10000111 &
#123
1%
b00011110 &
#124
b110 $
0%
b11000011 &
#125
1%
b00111100 &
#126
b111 $
0%
b11100001 &
#127
1%
b01111000 &
