libraries/codings/binary_to_gray.v
module binary_to_gray #(
    parameter WIDTH = 4
)(
    input wire [WIDTH-1:0] binary_in,
    output wire [WIDTH-1:0] gray_out
);

    // Gray code conversion: gray_out = binary_in ^ (binary_in >> 1)
    assign gray_out[WIDTH-1] = binary_in[WIDTH-1];
    
    genvar i;
    generate
        for (i = 0; i < WIDTH-1; i = i + 1) begin : gen_gray
            assign gray_out[i] = binary_in[i] ^ binary_in[i+1];
        end
    endgenerate

endmodule

binary_to_gray_sim.vcd
$version Generated by VerilatedVcd $end
$timescale 1ps $end
 $scope module TOP $end
  $var wire 4 # binary_in [3:0] $end
  $var wire 4 $ gray_out [3:0] $end
  $scope module binary_to_gray $end
   $var wire 32 % WIDTH [31:0] $end
   $var wire 4 # binary_in [3:0] $end
   $var wire 4 $ gray_out [3:0] $end
  $upscope $end
 $upscope $end
$enddefinitions $end


#0
b0000 #
b0000 $
b00000000000000000000000000000100 %
#1
b0001 #
b0001 $
#2
b0010 #
b0011 $
#3
b0011 #
b0010 $
#4
b0100 #
b0110 $
#5
b0101 #
b0111 $
#6
b0110 #
b0101 $
#7
b0111 #
b0100 $
#8
b1000 #
b1100 $
#9
b1001 #
b1101 $
#10
b1010 #
b1111 $
#11
b1011 #
b1110 $
#12
b1100 #
b1010 $
#13
b1101 #
b1011 $
#14
b1110 #
b1001 $
#15
b1111 #
b1000 $
