clock_divider.v
/* verilator lint_off EOFNEWLINE */
module clock_divider #(
    parameter DIV_WIDTH = 8,         // Width of the division ratio register
    parameter DUTY_WIDTH = 8         // Width of the duty cycle register
) (
    input wire clk_in,               // Input clock
    input wire rst_n,                // Active low reset
    input wire [DIV_WIDTH-1:0] div_ratio, // Clock division ratio
    input wire [DUTY_WIDTH-1:0] duty_cycle, // Duty cycle control (0-255 for 0-100%)
    output reg clk_out               // Output divided clock
);

    // Counter for tracking division
    reg [DIV_WIDTH:0] counter;  // Increased counter width to match duty_threshold
    
    // Calculate threshold for duty cycle
    wire [DIV_WIDTH:0] duty_threshold; // Increased width to handle calculation properly
    
    // Scale duty_cycle (0-255) to div_ratio range
    // This ensures duty_threshold is proportional to div_ratio
    assign duty_threshold = (div_ratio * duty_cycle) / 255;
    
    // Clock division logic
    always @(posedge clk_in or negedge rst_n) begin
        if (!rst_n) begin
            counter <= {(DIV_WIDTH+1){1'b0}};
            clk_out <= 1'b0;
        end 
        else begin
            // Increment counter
            if (counter >= div_ratio - 1) begin
                counter <= {(DIV_WIDTH+1){1'b0}};
            end 
            else begin
                counter <= counter + 1'b1;
            end
            
            // Set output based on duty cycle
            /* verilator lint_off UNSIGNED */
            if (counter < duty_threshold && div_ratio > 0) begin
            /* verilator lint_on UNSIGNED */
                clk_out <= 1'b1;
            end 
            else begin
                clk_out <= 1'b0;
            end
        end
    end

endmodule

clock_divider_sim.vcd
$version Generated by VerilatedVcd $end
$timescale 1ps $end
 $scope module TOP $end
  $var wire 1 # clk_in $end
  $var wire 1 $ rst_n $end
  $var wire 8 % div_ratio [7:0] $end
  $var wire 8 & duty_cycle [7:0] $end
  $var wire 1 ' clk_out $end
  $scope module clock_divider $end
   $var wire 32 * DIV_WIDTH [31:0] $end
   $var wire 32 * DUTY_WIDTH [31:0] $end
   $var wire 1 # clk_in $end
   $var wire 1 $ rst_n $end
   $var wire 8 % div_ratio [7:0] $end
   $var wire 8 & duty_cycle [7:0] $end
   $var wire 1 ' clk_out $end
   $var wire 9 ( counter [8:0] $end
   $var wire 9 ) duty_threshold [8:0] $end
  $upscope $end
 $upscope $end
$enddefinitions $end


#0
0#
0$
b00000100 %
b10000000 &
0'
b000000000 (
b000000010 )
b00000000000000000000000000001000 *
#1
1#
#2
0#
1$
#3
1#
1'
b000000001 (
#4
0#
#5
1#
b000000010 (
#6
0#
#7
1#
0'
b000000011 (
#8
0#
#9
1#
b000000000 (
#10
0#
#11
1#
1'
b000000001 (
#12
0#
#13
1#
b000000010 (
#14
0#
#15
1#
0'
b000000011 (
#16
0#
#17
1#
b000000000 (
#18
0#
#19
1#
1'
b000000001 (
#20
0#
#21
1#
b000000010 (
#22
0#
#23
1#
0'
b000000011 (
#24
0#
#25
1#
b000000000 (
#26
0#
#27
1#
1'
b000000001 (
#28
0#
#29
1#
b000000010 (
#30
0#
#31
1#
0'
b000000011 (
#32
0#
#33
1#
b000000000 (
#34
0#
#35
1#
1'
b000000001 (
#36
0#
#37
1#
b000000010 (
#38
0#
#39
1#
0'
b000000011 (
#40
0#
#41
1#
b000000000 (
#42
0#
#43
1#
1'
b000000001 (
#44
0#
#45
1#
b000000010 (
#46
0#
#47
1#
0'
b000000011 (
#48
0#
#49
1#
b000000000 (
#50
0#
#51
1#
1'
b000000001 (
#52
0#
#53
1#
b000000010 (
#54
0#
#55
1#
0'
b000000011 (
#56
0#
#57
1#
b000000000 (
#58
0#
#59
1#
1'
b000000001 (
#60
0#
#61
1#
b000000010 (
#62
0#
#63
1#
0'
b000000011 (
#64
0#
#65
1#
b000000000 (
#66
0#
#67
1#
1'
b000000001 (
#68
0#
#69
1#
b000000010 (
#70
0#
#71
1#
0'
b000000011 (
#72
0#
#73
1#
b000000000 (
#74
0#
#75
1#
1'
b000000001 (
#76
0#
#77
1#
b000000010 (
#78
0#
#79
1#
0'
b000000011 (
#80
0#
#81
1#
b000000000 (
#82
0#
#83
1#
1'
b000000001 (
#84
0#
#85
1#
b000000010 (
#86
0#
#87
1#
0'
b000000011 (
#88
0#
#89
1#
b000000000 (
#90
0#
#91
1#
1'
b000000001 (
#92
0#
#93
1#
b000000010 (
#94
0#
#95
1#
0'
b000000011 (
#96
0#
#97
1#
b000000000 (
#98
0#
#99
1#
1'
b000000001 (
#100
0#
#101
1#
b000000010 (
#102
0#
#103
1#
0'
b000000011 (
#104
0#
#105
1#
b000000000 (
#106
0#
#107
1#
1'
b000000001 (
#108
0#
#109
1#
b000000010 (
#110
0#
#111
1#
0'
b000000011 (
#112
0#
#113
1#
b000000000 (
#114
0#
#115
1#
1'
b000000001 (
#116
0#
#117
1#
b000000010 (
#118
0#
#119
1#
0'
b000000011 (
#120
0#
#121
1#
b000000000 (
#122
0#
#123
1#
1'
b000000001 (
#124
0#
#125
1#
b000000010 (
#126
0#
#127
1#
0'
b000000011 (
#128
0#
#129
1#
b000000000 (
#130
0#
#131
1#
1'
b000000001 (
#132
0#
#133
1#
b000000010 (
#134
0#
#135
1#
0'
b000000011 (
#136
0#
#137
1#
b000000000 (
#138
0#
#139
1#
1'
b000000001 (
#140
0#
#141
1#
b000000010 (
#142
0#
#143
1#
0'
b000000011 (
#144
0#
#145
1#
b000000000 (
#146
0#
#147
1#
1'
b000000001 (
#148
0#
#149
1#
b000000010 (
#150
0#
#151
1#
0'
b000000011 (
#152
0#
#153
1#
b000000000 (
#154
0#
#155
1#
1'
b000000001 (
#156
0#
#157
1#
b000000010 (
#158
0#
#159
1#
0'
b000000011 (
#160
0#
#161
1#
b000000000 (
#162
0#
#163
1#
1'
b000000001 (
#164
0#
#165
1#
b000000010 (
#166
0#
#167
1#
0'
b000000011 (
#168
0#
#169
1#
b000000000 (
#170
0#
#171
1#
1'
b000000001 (
#172
0#
#173
1#
b000000010 (
#174
0#
#175
1#
0'
b000000011 (
#176
0#
#177
1#
b000000000 (
#178
0#
#179
1#
1'
b000000001 (
#180
0#
#181
1#
b000000010 (
#182
0#
#183
1#
0'
b000000011 (
#184
0#
#185
1#
b000000000 (
#186
0#
#187
1#
1'
b000000001 (
#188
0#
#189
1#
b000000010 (
#190
0#
#191
1#
0'
b000000011 (
#192
0#
#193
1#
b000000000 (
#194
0#
#195
1#
1'
b000000001 (
#196
0#
#197
1#
b000000010 (
#198
0#
#199
1#
0'
b000000011 (
#200
0#
#201
1#
b000000000 (
#202
0#
0$
b00001010 %
b000000101 )
#203
1#
#204
0#
1$
#205
1#
1'
b000000001 (
#206
0#
#207
1#
b000000010 (
#208
0#
#209
1#
b000000011 (
#210
0#
#211
1#
b000000100 (
#212
0#
#213
1#
b000000101 (
#214
0#
#215
1#
0'
b000000110 (
#216
0#
#217
1#
b000000111 (
#218
0#
#219
1#
b000001000 (
#220
0#
#221
1#
b000001001 (
#222
0#
#223
1#
b000000000 (
#224
0#
#225
1#
1'
b000000001 (
#226
0#
#227
1#
b000000010 (
#228
0#
#229
1#
b000000011 (
#230
0#
#231
1#
b000000100 (
#232
0#
#233
1#
b000000101 (
#234
0#
#235
1#
0'
b000000110 (
#236
0#
#237
1#
b000000111 (
#238
0#
#239
1#
b000001000 (
#240
0#
#241
1#
b000001001 (
#242
0#
#243
1#
b000000000 (
#244
0#
#245
1#
1'
b000000001 (
#246
0#
#247
1#
b000000010 (
#248
0#
#249
1#
b000000011 (
#250
0#
#251
1#
b000000100 (
#252
0#
#253
1#
b000000101 (
#254
0#
#255
1#
0'
b000000110 (
#256
0#
#257
1#
b000000111 (
#258
0#
#259
1#
b000001000 (
#260
0#
#261
1#
b000001001 (
#262
0#
#263
1#
b000000000 (
#264
0#
#265
1#
1'
b000000001 (
#266
0#
#267
1#
b000000010 (
#268
0#
#269
1#
b000000011 (
#270
0#
#271
1#
b000000100 (
#272
0#
#273
1#
b000000101 (
#274
0#
#275
1#
0'
b000000110 (
#276
0#
#277
1#
b000000111 (
#278
0#
#279
1#
b000001000 (
#280
0#
#281
1#
b000001001 (
#282
0#
#283
1#
b000000000 (
#284
0#
#285
1#
1'
b000000001 (
#286
0#
#287
1#
b000000010 (
#288
0#
#289
1#
b000000011 (
#290
0#
#291
1#
b000000100 (
#292
0#
#293
1#
b000000101 (
#294
0#
#295
1#
0'
b000000110 (
#296
0#
#297
1#
b000000111 (
#298
0#
#299
1#
b000001000 (
#300
0#
#301
1#
b000001001 (
#302
0#
#303
1#
b000000000 (
#304
0#
#305
1#
1'
b000000001 (
#306
0#
#307
1#
b000000010 (
#308
0#
#309
1#
b000000011 (
#310
0#
#311
1#
b000000100 (
#312
0#
#313
1#
b000000101 (
#314
0#
#315
1#
0'
b000000110 (
#316
0#
#317
1#
b000000111 (
#318
0#
#319
1#
b000001000 (
#320
0#
#321
1#
b000001001 (
#322
0#
#323
1#
b000000000 (
#324
0#
#325
1#
1'
b000000001 (
#326
0#
#327
1#
b000000010 (
#328
0#
#329
1#
b000000011 (
#330
0#
#331
1#
b000000100 (
#332
0#
#333
1#
b000000101 (
#334
0#
#335
1#
0'
b000000110 (
#336
0#
#337
1#
b000000111 (
#338
0#
#339
1#
b000001000 (
#340
0#
#341
1#
b000001001 (
#342
0#
#343
1#
b000000000 (
#344
0#
#345
1#
1'
b000000001 (
#346
0#
#347
1#
b000000010 (
#348
0#
#349
1#
b000000011 (
#350
0#
#351
1#
b000000100 (
#352
0#
#353
1#
b000000101 (
#354
0#
#355
1#
0'
b000000110 (
#356
0#
#357
1#
b000000111 (
#358
0#
#359
1#
b000001000 (
#360
0#
#361
1#
b000001001 (
#362
0#
#363
1#
b000000000 (
#364
0#
#365
1#
1'
b000000001 (
#366
0#
#367
1#
b000000010 (
#368
0#
#369
1#
b000000011 (
#370
0#
#371
1#
b000000100 (
#372
0#
#373
1#
b000000101 (
#374
0#
#375
1#
0'
b000000110 (
#376
0#
#377
1#
b000000111 (
#378
0#
#379
1#
b000001000 (
#380
0#
#381
1#
b000001001 (
#382
0#
#383
1#
b000000000 (
#384
0#
#385
1#
1'
b000000001 (
#386
0#
#387
1#
b000000010 (
#388
0#
#389
1#
b000000011 (
#390
0#
#391
1#
b000000100 (
#392
0#
#393
1#
b000000101 (
#394
0#
#395
1#
0'
b000000110 (
#396
0#
#397
1#
b000000111 (
#398
0#
#399
1#
b000001000 (
#400
0#
#401
1#
b000001001 (
#402
0#
#403
1#
b000000000 (
#404
0#
#405
1#
1'
b000000001 (
#406
0#
#407
1#
b000000010 (
#408
0#
#409
1#
b000000011 (
#410
0#
#411
1#
b000000100 (
#412
0#
#413
1#
b000000101 (
#414
0#
#415
1#
0'
b000000110 (
#416
0#
#417
1#
b000000111 (
#418
0#
#419
1#
b000001000 (
#420
0#
#421
1#
b000001001 (
#422
0#
#423
1#
b000000000 (
#424
0#
#425
1#
1'
b000000001 (
#426
0#
#427
1#
b000000010 (
#428
0#
#429
1#
b000000011 (
#430
0#
#431
1#
b000000100 (
#432
0#
#433
1#
b000000101 (
#434
0#
#435
1#
0'
b000000110 (
#436
0#
#437
1#
b000000111 (
#438
0#
#439
1#
b000001000 (
#440
0#
#441
1#
b000001001 (
#442
0#
#443
1#
b000000000 (
#444
0#
#445
1#
1'
b000000001 (
#446
0#
#447
1#
b000000010 (
#448
0#
#449
1#
b000000011 (
#450
0#
#451
1#
b000000100 (
#452
0#
#453
1#
b000000101 (
#454
0#
#455
1#
0'
b000000110 (
#456
0#
#457
1#
b000000111 (
#458
0#
#459
1#
b000001000 (
#460
0#
#461
1#
b000001001 (
#462
0#
#463
1#
b000000000 (
#464
0#
#465
1#
1'
b000000001 (
#466
0#
#467
1#
b000000010 (
#468
0#
#469
1#
b000000011 (
#470
0#
#471
1#
b000000100 (
#472
0#
#473
1#
b000000101 (
#474
0#
#475
1#
0'
b000000110 (
#476
0#
#477
1#
b000000111 (
#478
0#
#479
1#
b000001000 (
#480
0#
#481
1#
b000001001 (
#482
0#
#483
1#
b000000000 (
#484
0#
#485
1#
1'
b000000001 (
#486
0#
#487
1#
b000000010 (
#488
0#
#489
1#
b000000011 (
#490
0#
#491
1#
b000000100 (
#492
0#
#493
1#
b000000101 (
#494
0#
#495
1#
0'
b000000110 (
#496
0#
#497
1#
b000000111 (
#498
0#
#499
1#
b000001000 (
#500
0#
#501
1#
b000001001 (
#502
0#
#503
1#
b000000000 (
#504
0#
#505
1#
1'
b000000001 (
#506
0#
#507
1#
b000000010 (
#508
0#
#509
1#
b000000011 (
#510
0#
#511
1#
b000000100 (
#512
0#
#513
1#
b000000101 (
#514
0#
#515
1#
0'
b000000110 (
#516
0#
#517
1#
b000000111 (
#518
0#
#519
1#
b000001000 (
#520
0#
#521
1#
b000001001 (
#522
0#
#523
1#
b000000000 (
#524
0#
#525
1#
1'
b000000001 (
#526
0#
#527
1#
b000000010 (
#528
0#
#529
1#
b000000011 (
#530
0#
#531
1#
b000000100 (
#532
0#
#533
1#
b000000101 (
#534
0#
#535
1#
0'
b000000110 (
#536
0#
#537
1#
b000000111 (
#538
0#
#539
1#
b000001000 (
#540
0#
#541
1#
b000001001 (
#542
0#
#543
1#
b000000000 (
#544
0#
#545
1#
1'
b000000001 (
#546
0#
#547
1#
b000000010 (
#548
0#
#549
1#
b000000011 (
#550
0#
#551
1#
b000000100 (
#552
0#
#553
1#
b000000101 (
#554
0#
#555
1#
0'
b000000110 (
#556
0#
#557
1#
b000000111 (
#558
0#
#559
1#
b000001000 (
#560
0#
#561
1#
b000001001 (
#562
0#
#563
1#
b000000000 (
#564
0#
#565
1#
1'
b000000001 (
#566
0#
#567
1#
b000000010 (
#568
0#
#569
1#
b000000011 (
#570
0#
#571
1#
b000000100 (
#572
0#
#573
1#
b000000101 (
#574
0#
#575
1#
0'
b000000110 (
#576
0#
#577
1#
b000000111 (
#578
0#
#579
1#
b000001000 (
#580
0#
#581
1#
b000001001 (
#582
0#
#583
1#
b000000000 (
#584
0#
#585
1#
1'
b000000001 (
#586
0#
#587
1#
b000000010 (
#588
0#
#589
1#
b000000011 (
#590
0#
#591
1#
b000000100 (
#592
0#
#593
1#
b000000101 (
#594
0#
#595
1#
0'
b000000110 (
#596
0#
#597
1#
b000000111 (
#598
0#
#599
1#
b000001000 (
#600
0#
#601
1#
b000001001 (
#602
0#
#603
1#
b000000000 (
#604
0#
0$
b00001000 %
b01000000 &
b000000010 )
#605
1#
#606
0#
1$
#607
1#
1'
b000000001 (
#608
0#
#609
1#
b000000010 (
#610
0#
#611
1#
0'
b000000011 (
#612
0#
#613
1#
b000000100 (
#614
0#
#615
1#
b000000101 (
#616
0#
#617
1#
b000000110 (
#618
0#
#619
1#
b000000111 (
#620
0#
#621
1#
b000000000 (
#622
0#
#623
1#
1'
b000000001 (
#624
0#
#625
1#
b000000010 (
#626
0#
#627
1#
0'
b000000011 (
#628
0#
#629
1#
b000000100 (
#630
0#
#631
1#
b000000101 (
#632
0#
#633
1#
b000000110 (
#634
0#
#635
1#
b000000111 (
#636
0#
#637
1#
b000000000 (
#638
0#
#639
1#
1'
b000000001 (
#640
0#
#641
1#
b000000010 (
#642
0#
#643
1#
0'
b000000011 (
#644
0#
#645
1#
b000000100 (
#646
0#
#647
1#
b000000101 (
#648
0#
#649
1#
b000000110 (
#650
0#
#651
1#
b000000111 (
#652
0#
#653
1#
b000000000 (
#654
0#
#655
1#
1'
b000000001 (
#656
0#
#657
1#
b000000010 (
#658
0#
#659
1#
0'
b000000011 (
#660
0#
#661
1#
b000000100 (
#662
0#
#663
1#
b000000101 (
#664
0#
#665
1#
b000000110 (
#666
0#
#667
1#
b000000111 (
#668
0#
#669
1#
b000000000 (
#670
0#
#671
1#
1'
b000000001 (
#672
0#
#673
1#
b000000010 (
#674
0#
#675
1#
0'
b000000011 (
#676
0#
#677
1#
b000000100 (
#678
0#
#679
1#
b000000101 (
#680
0#
#681
1#
b000000110 (
#682
0#
#683
1#
b000000111 (
#684
0#
#685
1#
b000000000 (
#686
0#
#687
1#
1'
b000000001 (
#688
0#
#689
1#
b000000010 (
#690
0#
#691
1#
0'
b000000011 (
#692
0#
#693
1#
b000000100 (
#694
0#
#695
1#
b000000101 (
#696
0#
#697
1#
b000000110 (
#698
0#
#699
1#
b000000111 (
#700
0#
#701
1#
b000000000 (
#702
0#
#703
1#
1'
b000000001 (
#704
0#
#705
1#
b000000010 (
#706
0#
#707
1#
0'
b000000011 (
#708
0#
#709
1#
b000000100 (
#710
0#
#711
1#
b000000101 (
#712
0#
#713
1#
b000000110 (
#714
0#
#715
1#
b000000111 (
#716
0#
#717
1#
b000000000 (
#718
0#
#719
1#
1'
b000000001 (
#720
0#
#721
1#
b000000010 (
#722
0#
#723
1#
0'
b000000011 (
#724
0#
#725
1#
b000000100 (
#726
0#
#727
1#
b000000101 (
#728
0#
#729
1#
b000000110 (
#730
0#
#731
1#
b000000111 (
#732
0#
#733
1#
b000000000 (
#734
0#
#735
1#
1'
b000000001 (
#736
0#
#737
1#
b000000010 (
#738
0#
#739
1#
0'
b000000011 (
#740
0#
#741
1#
b000000100 (
#742
0#
#743
1#
b000000101 (
#744
0#
#745
1#
b000000110 (
#746
0#
#747
1#
b000000111 (
#748
0#
#749
1#
b000000000 (
#750
0#
#751
1#
1'
b000000001 (
#752
0#
#753
1#
b000000010 (
#754
0#
#755
1#
0'
b000000011 (
#756
0#
#757
1#
b000000100 (
#758
0#
#759
1#
b000000101 (
#760
0#
#761
1#
b000000110 (
#762
0#
#763
1#
b000000111 (
#764
0#
#765
1#
b000000000 (
#766
0#
#767
1#
1'
b000000001 (
#768
0#
#769
1#
b000000010 (
#770
0#
#771
1#
0'
b000000011 (
#772
0#
#773
1#
b000000100 (
#774
0#
#775
1#
b000000101 (
#776
0#
#777
1#
b000000110 (
#778
0#
#779
1#
b000000111 (
#780
0#
#781
1#
b000000000 (
#782
0#
#783
1#
1'
b000000001 (
#784
0#
#785
1#
b000000010 (
#786
0#
#787
1#
0'
b000000011 (
#788
0#
#789
1#
b000000100 (
#790
0#
#791
1#
b000000101 (
#792
0#
#793
1#
b000000110 (
#794
0#
#795
1#
b000000111 (
#796
0#
#797
1#
b000000000 (
#798
0#
#799
1#
1'
b000000001 (
#800
0#
#801
1#
b000000010 (
#802
0#
#803
1#
0'
b000000011 (
#804
0#
#805
1#
b000000100 (
#806
0#
#807
1#
b000000101 (
#808
0#
#809
1#
b000000110 (
#810
0#
#811
1#
b000000111 (
#812
0#
#813
1#
b000000000 (
#814
0#
#815
1#
1'
b000000001 (
#816
0#
#817
1#
b000000010 (
#818
0#
#819
1#
0'
b000000011 (
#820
0#
#821
1#
b000000100 (
#822
0#
#823
1#
b000000101 (
#824
0#
#825
1#
b000000110 (
#826
0#
#827
1#
b000000111 (
#828
0#
#829
1#
b000000000 (
#830
0#
#831
1#
1'
b000000001 (
#832
0#
#833
1#
b000000010 (
#834
0#
#835
1#
0'
b000000011 (
#836
0#
#837
1#
b000000100 (
#838
0#
#839
1#
b000000101 (
#840
0#
#841
1#
b000000110 (
#842
0#
#843
1#
b000000111 (
#844
0#
#845
1#
b000000000 (
#846
0#
#847
1#
1'
b000000001 (
#848
0#
#849
1#
b000000010 (
#850
0#
#851
1#
0'
b000000011 (
#852
0#
#853
1#
b000000100 (
#854
0#
#855
1#
b000000101 (
#856
0#
#857
1#
b000000110 (
#858
0#
#859
1#
b000000111 (
#860
0#
#861
1#
b000000000 (
#862
0#
#863
1#
1'
b000000001 (
#864
0#
#865
1#
b000000010 (
#866
0#
#867
1#
0'
b000000011 (
#868
0#
#869
1#
b000000100 (
#870
0#
#871
1#
b000000101 (
#872
0#
#873
1#
b000000110 (
#874
0#
#875
1#
b000000111 (
#876
0#
#877
1#
b000000000 (
#878
0#
#879
1#
1'
b000000001 (
#880
0#
#881
1#
b000000010 (
#882
0#
#883
1#
0'
b000000011 (
#884
0#
#885
1#
b000000100 (
#886
0#
#887
1#
b000000101 (
#888
0#
#889
1#
b000000110 (
#890
0#
#891
1#
b000000111 (
#892
0#
#893
1#
b000000000 (
#894
0#
#895
1#
1'
b000000001 (
#896
0#
#897
1#
b000000010 (
#898
0#
#899
1#
0'
b000000011 (
#900
0#
#901
1#
b000000100 (
#902
0#
#903
1#
b000000101 (
#904
0#
#905
1#
b000000110 (
#906
0#
#907
1#
b000000111 (
#908
0#
#909
1#
b000000000 (
#910
0#
#911
1#
1'
b000000001 (
#912
0#
#913
1#
b000000010 (
#914
0#
#915
1#
0'
b000000011 (
#916
0#
#917
1#
b000000100 (
#918
0#
#919
1#
b000000101 (
#920
0#
#921
1#
b000000110 (
#922
0#
#923
1#
b000000111 (
#924
0#
#925
1#
b000000000 (
#926
0#
#927
1#
1'
b000000001 (
#928
0#
#929
1#
b000000010 (
#930
0#
#931
1#
0'
b000000011 (
#932
0#
#933
1#
b000000100 (
#934
0#
#935
1#
b000000101 (
#936
0#
#937
1#
b000000110 (
#938
0#
#939
1#
b000000111 (
#940
0#
#941
1#
b000000000 (
#942
0#
#943
1#
1'
b000000001 (
#944
0#
#945
1#
b000000010 (
#946
0#
#947
1#
0'
b000000011 (
#948
0#
#949
1#
b000000100 (
#950
0#
#951
1#
b000000101 (
#952
0#
#953
1#
b000000110 (
#954
0#
#955
1#
b000000111 (
#956
0#
#957
1#
b000000000 (
#958
0#
#959
1#
1'
b000000001 (
#960
0#
#961
1#
b000000010 (
#962
0#
#963
1#
0'
b000000011 (
#964
0#
#965
1#
b000000100 (
#966
0#
#967
1#
b000000101 (
#968
0#
#969
1#
b000000110 (
#970
0#
#971
1#
b000000111 (
#972
0#
#973
1#
b000000000 (
#974
0#
#975
1#
1'
b000000001 (
#976
0#
#977
1#
b000000010 (
#978
0#
#979
1#
0'
b000000011 (
#980
0#
#981
1#
b000000100 (
#982
0#
#983
1#
b000000101 (
#984
0#
#985
1#
b000000110 (
#986
0#
#987
1#
b000000111 (
#988
0#
#989
1#
b000000000 (
#990
0#
#991
1#
1'
b000000001 (
#992
0#
#993
1#
b000000010 (
#994
0#
#995
1#
0'
b000000011 (
#996
0#
#997
1#
b000000100 (
#998
0#
#999
1#
b000000101 (
#1000
0#
#1001
1#
b000000110 (
#1002
0#
#1003
1#
b000000111 (
#1004
0#
#1005
1#
b000000000 (
#1006
0#
0$
b11000000 &
b000000110 )
#1007
1#
#1008
0#
1$
#1009
1#
1'
b000000001 (
#1010
0#
#1011
1#
b000000010 (
#1012
0#
#1013
1#
b000000011 (
#1014
0#
#1015
1#
b000000100 (
#1016
0#
#1017
1#
b000000101 (
#1018
0#
#1019
1#
b000000110 (
#1020
0#
#1021
1#
0'
b000000111 (
#1022
0#
#1023
1#
b000000000 (
#1024
0#
#1025
1#
1'
b000000001 (
#1026
0#
#1027
1#
b000000010 (
#1028
0#
#1029
1#
b000000011 (
#1030
0#
#1031
1#
b000000100 (
#1032
0#
#1033
1#
b000000101 (
#1034
0#
#1035
1#
b000000110 (
#1036
0#
#1037
1#
0'
b000000111 (
#1038
0#
#1039
1#
b000000000 (
#1040
0#
#1041
1#
1'
b000000001 (
#1042
0#
#1043
1#
b000000010 (
#1044
0#
#1045
1#
b000000011 (
#1046
0#
#1047
1#
b000000100 (
#1048
0#
#1049
1#
b000000101 (
#1050
0#
#1051
1#
b000000110 (
#1052
0#
#1053
1#
0'
b000000111 (
#1054
0#
#1055
1#
b000000000 (
#1056
0#
#1057
1#
1'
b000000001 (
#1058
0#
#1059
1#
b000000010 (
#1060
0#
#1061
1#
b000000011 (
#1062
0#
#1063
1#
b000000100 (
#1064
0#
#1065
1#
b000000101 (
#1066
0#
#1067
1#
b000000110 (
#1068
0#
#1069
1#
0'
b000000111 (
#1070
0#
#1071
1#
b000000000 (
#1072
0#
#1073
1#
1'
b000000001 (
#1074
0#
#1075
1#
b000000010 (
#1076
0#
#1077
1#
b000000011 (
#1078
0#
#1079
1#
b000000100 (
#1080
0#
#1081
1#
b000000101 (
#1082
0#
#1083
1#
b000000110 (
#1084
0#
#1085
1#
0'
b000000111 (
#1086
0#
#1087
1#
b000000000 (
#1088
0#
#1089
1#
1'
b000000001 (
#1090
0#
#1091
1#
b000000010 (
#1092
0#
#1093
1#
b000000011 (
#1094
0#
#1095
1#
b000000100 (
#1096
0#
#1097
1#
b000000101 (
#1098
0#
#1099
1#
b000000110 (
#1100
0#
#1101
1#
0'
b000000111 (
#1102
0#
#1103
1#
b000000000 (
#1104
0#
#1105
1#
1'
b000000001 (
#1106
0#
#1107
1#
b000000010 (
#1108
0#
#1109
1#
b000000011 (
#1110
0#
#1111
1#
b000000100 (
#1112
0#
#1113
1#
b000000101 (
#1114
0#
#1115
1#
b000000110 (
#1116
0#
#1117
1#
0'
b000000111 (
#1118
0#
#1119
1#
b000000000 (
#1120
0#
#1121
1#
1'
b000000001 (
#1122
0#
#1123
1#
b000000010 (
#1124
0#
#1125
1#
b000000011 (
#1126
0#
#1127
1#
b000000100 (
#1128
0#
#1129
1#
b000000101 (
#1130
0#
#1131
1#
b000000110 (
#1132
0#
#1133
1#
0'
b000000111 (
#1134
0#
#1135
1#
b000000000 (
#1136
0#
#1137
1#
1'
b000000001 (
#1138
0#
#1139
1#
b000000010 (
#1140
0#
#1141
1#
b000000011 (
#1142
0#
#1143
1#
b000000100 (
#1144
0#
#1145
1#
b000000101 (
#1146
0#
#1147
1#
b000000110 (
#1148
0#
#1149
1#
0'
b000000111 (
#1150
0#
#1151
1#
b000000000 (
#1152
0#
#1153
1#
1'
b000000001 (
#1154
0#
#1155
1#
b000000010 (
#1156
0#
#1157
1#
b000000011 (
#1158
0#
#1159
1#
b000000100 (
#1160
0#
#1161
1#
b000000101 (
#1162
0#
#1163
1#
b000000110 (
#1164
0#
#1165
1#
0'
b000000111 (
#1166
0#
#1167
1#
b000000000 (
#1168
0#
#1169
1#
1'
b000000001 (
#1170
0#
#1171
1#
b000000010 (
#1172
0#
#1173
1#
b000000011 (
#1174
0#
#1175
1#
b000000100 (
#1176
0#
#1177
1#
b000000101 (
#1178
0#
#1179
1#
b000000110 (
#1180
0#
#1181
1#
0'
b000000111 (
#1182
0#
#1183
1#
b000000000 (
#1184
0#
#1185
1#
1'
b000000001 (
#1186
0#
#1187
1#
b000000010 (
#1188
0#
#1189
1#
b000000011 (
#1190
0#
#1191
1#
b000000100 (
#1192
0#
#1193
1#
b000000101 (
#1194
0#
#1195
1#
b000000110 (
#1196
0#
#1197
1#
0'
b000000111 (
#1198
0#
#1199
1#
b000000000 (
#1200
0#
#1201
1#
1'
b000000001 (
#1202
0#
#1203
1#
b000000010 (
#1204
0#
#1205
1#
b000000011 (
#1206
0#
#1207
1#
b000000100 (
#1208
0#
#1209
1#
b000000101 (
#1210
0#
#1211
1#
b000000110 (
#1212
0#
#1213
1#
0'
b000000111 (
#1214
0#
#1215
1#
b000000000 (
#1216
0#
#1217
1#
1'
b000000001 (
#1218
0#
#1219
1#
b000000010 (
#1220
0#
#1221
1#
b000000011 (
#1222
0#
#1223
1#
b000000100 (
#1224
0#
#1225
1#
b000000101 (
#1226
0#
#1227
1#
b000000110 (
#1228
0#
#1229
1#
0'
b000000111 (
#1230
0#
#1231
1#
b000000000 (
#1232
0#
#1233
1#
1'
b000000001 (
#1234
0#
#1235
1#
b000000010 (
#1236
0#
#1237
1#
b000000011 (
#1238
0#
#1239
1#
b000000100 (
#1240
0#
#1241
1#
b000000101 (
#1242
0#
#1243
1#
b000000110 (
#1244
0#
#1245
1#
0'
b000000111 (
#1246
0#
#1247
1#
b000000000 (
#1248
0#
#1249
1#
1'
b000000001 (
#1250
0#
#1251
1#
b000000010 (
#1252
0#
#1253
1#
b000000011 (
#1254
0#
#1255
1#
b000000100 (
#1256
0#
#1257
1#
b000000101 (
#1258
0#
#1259
1#
b000000110 (
#1260
0#
#1261
1#
0'
b000000111 (
#1262
0#
#1263
1#
b000000000 (
#1264
0#
#1265
1#
1'
b000000001 (
#1266
0#
#1267
1#
b000000010 (
#1268
0#
#1269
1#
b000000011 (
#1270
0#
#1271
1#
b000000100 (
#1272
0#
#1273
1#
b000000101 (
#1274
0#
#1275
1#
b000000110 (
#1276
0#
#1277
1#
0'
b000000111 (
#1278
0#
#1279
1#
b000000000 (
#1280
0#
#1281
1#
1'
b000000001 (
#1282
0#
#1283
1#
b000000010 (
#1284
0#
#1285
1#
b000000011 (
#1286
0#
#1287
1#
b000000100 (
#1288
0#
#1289
1#
b000000101 (
#1290
0#
#1291
1#
b000000110 (
#1292
0#
#1293
1#
0'
b000000111 (
#1294
0#
#1295
1#
b000000000 (
#1296
0#
#1297
1#
1'
b000000001 (
#1298
0#
#1299
1#
b000000010 (
#1300
0#
#1301
1#
b000000011 (
#1302
0#
#1303
1#
b000000100 (
#1304
0#
#1305
1#
b000000101 (
#1306
0#
#1307
1#
b000000110 (
#1308
0#
#1309
1#
0'
b000000111 (
#1310
0#
#1311
1#
b000000000 (
#1312
0#
#1313
1#
1'
b000000001 (
#1314
0#
#1315
1#
b000000010 (
#1316
0#
#1317
1#
b000000011 (
#1318
0#
#1319
1#
b000000100 (
#1320
0#
#1321
1#
b000000101 (
#1322
0#
#1323
1#
b000000110 (
#1324
0#
#1325
1#
0'
b000000111 (
#1326
0#
#1327
1#
b000000000 (
#1328
0#
#1329
1#
1'
b000000001 (
#1330
0#
#1331
1#
b000000010 (
#1332
0#
#1333
1#
b000000011 (
#1334
0#
#1335
1#
b000000100 (
#1336
0#
#1337
1#
b000000101 (
#1338
0#
#1339
1#
b000000110 (
#1340
0#
#1341
1#
0'
b000000111 (
#1342
0#
#1343
1#
b000000000 (
#1344
0#
#1345
1#
1'
b000000001 (
#1346
0#
#1347
1#
b000000010 (
#1348
0#
#1349
1#
b000000011 (
#1350
0#
#1351
1#
b000000100 (
#1352
0#
#1353
1#
b000000101 (
#1354
0#
#1355
1#
b000000110 (
#1356
0#
#1357
1#
0'
b000000111 (
