configurable_clz_clo.v
module configurable_clz_clo #(
    parameter DATA_WIDTH = 32,                    // Width of input data
    parameter COUNT_WIDTH = $clog2(DATA_WIDTH+1)  // Width of count output
) (
    input wire [DATA_WIDTH-1:0] data_in,
    input wire count_ones,                       // 0 for count leading zeros, 1 for count leading ones
    output reg [COUNT_WIDTH-1:0] count_out,
    output reg all_zeros,                        // Indicates if data_in is all zeros
    output reg all_ones                          // Indicates if data_in is all ones
);

    integer i;

    always @(*) begin
        // Set default values
        count_out = COUNT_WIDTH'(DATA_WIDTH);
        all_zeros = (data_in == {DATA_WIDTH{1'b0}});
        all_ones = (data_in == {DATA_WIDTH{1'b1}});
        
        // For count leading zeros
        if (count_ones == 1'b0) begin
            for (i = DATA_WIDTH-1; i >= 0; i = i - 1) begin
                if (data_in[i] == 1'b1) begin
                    count_out = COUNT_WIDTH'(DATA_WIDTH - 1 - i);
                    break;
                end
            end
        end
        // For count leading ones
        else begin
            for (i = DATA_WIDTH-1; i >= 0; i = i - 1) begin
                if (data_in[i] == 1'b0) begin
                    count_out = COUNT_WIDTH'(DATA_WIDTH - 1 - i);
                    break;
                end
            end
        end
    end

endmodule

configurable_clz_clo_sim.vcd
$version Generated by VerilatedVcd $end
$timescale 1ps $end
 $scope module TOP $end
  $var wire 32 # data_in [31:0] $end
  $var wire 1 $ count_ones $end
  $var wire 6 % count_out [5:0] $end
  $var wire 1 & all_zeros $end
  $var wire 1 ' all_ones $end
  $scope module configurable_clz_clo $end
   $var wire 32 ) DATA_WIDTH [31:0] $end
   $var wire 32 * COUNT_WIDTH [31:0] $end
   $var wire 32 # data_in [31:0] $end
   $var wire 1 $ count_ones $end
   $var wire 6 % count_out [5:0] $end
   $var wire 1 & all_zeros $end
   $var wire 1 ' all_ones $end
   $var wire 32 ( i [31:0] $end
  $upscope $end
 $upscope $end
$enddefinitions $end


#0
b00000000000000000000000000000000 #
0$
b100000 %
1&
0'
b11111111111111111111111111111111 (
b00000000000000000000000000100000 )
b00000000000000000000000000000110 *
#1
1$
b000000 %
b00000000000000000000000000011111 (
#2
b11111111111111111111111111111111 #
0$
0&
1'
#3
1$
b100000 %
b11111111111111111111111111111111 (
#4
b10000000000000000000000000000000 #
0$
b000000 %
0'
b00000000000000000000000000011111 (
#5
1$
b000001 %
b00000000000000000000000000011110 (
#6
b00000000000000000000000000000001 #
0$
b011111 %
b00000000000000000000000000000000 (
#7
1$
b000000 %
b00000000000000000000000000011111 (
#8
b01111111111111111111111111111111 #
0$
b000001 %
b00000000000000000000000000011110 (
#9
1$
b000000 %
b00000000000000000000000000011111 (
#10
b11111111111111111111111111111110 #
0$
#11
1$
b011111 %
b00000000000000000000000000000000 (
#12
b00001111000011110000111100001111 #
0$
b000100 %
b00000000000000000000000000011011 (
#13
1$
b000000 %
b00000000000000000000000000011111 (
#14
b11110000111100001111000011110000 #
0$
#15
1$
b000100 %
b00000000000000000000000000011011 (
#16
b01010101010101010101010101010101 #
0$
b000001 %
b00000000000000000000000000011110 (
#17
1$
b000000 %
b00000000000000000000000000011111 (
#18
b10101010101010101010101010101010 #
0$
#19
1$
b000001 %
b00000000000000000000000000011110 (
#20
b00000000111111111111111111111111 #
0$
b001000 %
b00000000000000000000000000010111 (
#21
1$
b000000 %
b00000000000000000000000000011111 (
#22
b11111111000000000000000000000000 #
0$
#23
1$
b001000 %
b00000000000000000000000000010111 (
