dual_port_ram.v
module dual_port_ram #(
    parameter DATA_WIDTH = 8,
    parameter ADDR_WIDTH = 4,
    parameter DEPTH = (1 << ADDR_WIDTH)
)(
    input wire clk,
    // Port A
    input wire [ADDR_WIDTH-1:0] addr_a,
    input wire [DATA_WIDTH-1:0] data_a,
    input wire we_a,
    output reg [DATA_WIDTH-1:0] q_a,
    // Port B
    input wire [ADDR_WIDTH-1:0] addr_b,
    input wire [DATA_WIDTH-1:0] data_b,
    input wire we_b,
    output reg [DATA_WIDTH-1:0] q_b
);

    // Memory array
    reg [DATA_WIDTH-1:0] ram [0:DEPTH-1];

    // Port A
    always @(posedge clk) begin
        if (we_a) begin
            ram[addr_a] <= data_a;
        end
        q_a <= ram[addr_a];
    end

    // Port B
    always @(posedge clk) begin
        if (we_b) begin
            ram[addr_b] <= data_b;
        end
        q_b <= ram[addr_b];
    end

endmodule

dual_port_ram_sim.vcd
$version Generated by VerilatedVcd $end
$timescale 1ps $end
 $scope module TOP $end
  $var wire 1 3 clk $end
  $var wire 4 4 addr_a [3:0] $end
  $var wire 8 5 data_a [7:0] $end
  $var wire 1 6 we_a $end
  $var wire 8 7 q_a [7:0] $end
  $var wire 4 8 addr_b [3:0] $end
  $var wire 8 9 data_b [7:0] $end
  $var wire 1 : we_b $end
  $var wire 8 ; q_b [7:0] $end
  $scope module dual_port_ram $end
   $var wire 32 < DATA_WIDTH [31:0] $end
   $var wire 32 = ADDR_WIDTH [31:0] $end
   $var wire 32 > DEPTH [31:0] $end
   $var wire 1 3 clk $end
   $var wire 4 4 addr_a [3:0] $end
   $var wire 8 5 data_a [7:0] $end
   $var wire 1 6 we_a $end
   $var wire 8 7 q_a [7:0] $end
   $var wire 4 8 addr_b [3:0] $end
   $var wire 8 9 data_b [7:0] $end
   $var wire 1 : we_b $end
   $var wire 8 ; q_b [7:0] $end
   $var wire 8 # ram[0] [7:0] $end
   $var wire 8 $ ram[1] [7:0] $end
   $var wire 8 % ram[2] [7:0] $end
   $var wire 8 & ram[3] [7:0] $end
   $var wire 8 ' ram[4] [7:0] $end
   $var wire 8 ( ram[5] [7:0] $end
   $var wire 8 ) ram[6] [7:0] $end
   $var wire 8 * ram[7] [7:0] $end
   $var wire 8 + ram[8] [7:0] $end
   $var wire 8 , ram[9] [7:0] $end
   $var wire 8 - ram[10] [7:0] $end
   $var wire 8 . ram[11] [7:0] $end
   $var wire 8 / ram[12] [7:0] $end
   $var wire 8 0 ram[13] [7:0] $end
   $var wire 8 1 ram[14] [7:0] $end
   $var wire 8 2 ram[15] [7:0] $end
  $upscope $end
 $upscope $end
$enddefinitions $end


#0
b00000000 #
b00000000 $
b00000000 %
b00000000 &
b00000000 '
b00000000 (
b00000000 )
b00000000 *
b00000000 +
b00000000 ,
b00000000 -
b00000000 .
b00000000 /
b00000000 0
b00000000 1
b00000000 2
03
b0000 4
b00000000 5
06
b00000000 7
b0000 8
b00000000 9
0:
b00000000 ;
b00000000000000000000000000001000 <
b00000000000000000000000000000100 =
b00000000000000000000000000010000 >
#1
16
#2
13
#3
03
06
#4
13
#5
03
b0001 4
b00000011 5
16
b0001 8
#6
b00000011 $
13
#7
03
06
#8
13
b00000011 7
b00000011 ;
#9
03
b0010 4
b00000110 5
16
b0010 8
#10
b00000110 %
13
b00000000 7
b00000000 ;
#11
03
06
#12
13
b00000110 7
b00000110 ;
#13
03
b0011 4
b00001001 5
16
b0011 8
#14
b00001001 &
13
b00000000 7
b00000000 ;
#15
03
06
#16
13
b00001001 7
b00001001 ;
#17
03
b0100 4
b00001100 5
16
b0100 8
#18
b00001100 '
13
b00000000 7
b00000000 ;
#19
03
06
#20
13
b00001100 7
b00001100 ;
#21
03
b0101 4
b00001111 5
16
b0101 8
#22
b00001111 (
13
b00000000 7
b00000000 ;
#23
03
06
#24
13
b00001111 7
b00001111 ;
#25
03
b0110 4
b00010010 5
16
b0110 8
#26
b00010010 )
13
b00000000 7
b00000000 ;
#27
03
06
#28
13
b00010010 7
b00010010 ;
#29
03
b0111 4
b00010101 5
16
b0111 8
#30
b00010101 *
13
b00000000 7
b00000000 ;
#31
03
06
#32
13
b00010101 7
b00010101 ;
#33
03
b1000 4
b00011000 5
16
b1000 8
#34
b00011000 +
13
b00000000 7
b00000000 ;
#35
03
06
#36
13
b00011000 7
b00011000 ;
#37
03
b1001 4
b00011011 5
16
b1001 8
#38
b00011011 ,
13
b00000000 7
b00000000 ;
#39
03
06
#40
13
b00011011 7
b00011011 ;
#41
03
b1010 4
b00011110 5
16
b1010 8
#42
b00011110 -
13
b00000000 7
b00000000 ;
#43
03
06
#44
13
b00011110 7
b00011110 ;
#45
03
b1011 4
b00100001 5
16
b1011 8
#46
b00100001 .
13
b00000000 7
b00000000 ;
#47
03
06
#48
13
b00100001 7
b00100001 ;
#49
03
b1100 4
b00100100 5
16
b1100 8
#50
b00100100 /
13
b00000000 7
b00000000 ;
#51
03
06
#52
13
b00100100 7
b00100100 ;
#53
03
b1101 4
b00100111 5
16
b1101 8
#54
b00100111 0
13
b00000000 7
b00000000 ;
#55
03
06
#56
13
b00100111 7
b00100111 ;
#57
03
b1110 4
b00101010 5
16
b1110 8
#58
b00101010 1
13
b00000000 7
b00000000 ;
#59
03
06
#60
13
b00101010 7
b00101010 ;
#61
03
b1111 4
b00101101 5
16
b1111 8
#62
b00101101 2
13
b00000000 7
b00000000 ;
#63
03
06
#64
13
b00101101 7
b00101101 ;
#65
03
b0000 4
b00000000 5
16
b0000 8
#66
13
b00000000 7
b00000000 ;
#67
03
b0001 4
b00000101 5
#68
b00000101 $
13
b00000011 7
#69
03
b0010 4
b00001010 5
#70
b00001010 %
13
b00000110 7
#71
03
b0011 4
b00001111 5
#72
b00001111 &
13
b00001001 7
#73
03
b0100 4
b00010100 5
#74
b00010100 '
13
b00001100 7
#75
03
b0101 4
b00011001 5
#76
b00011001 (
13
b00001111 7
#77
03
b0110 4
b00011110 5
#78
b00011110 )
13
b00010010 7
#79
03
b0111 4
b00100011 5
#80
b00100011 *
13
b00010101 7
#81
03
b1000 4
b00101000 5
#82
b00101000 +
13
b00011000 7
#83
03
b1001 4
b00101101 5
#84
b00101101 ,
13
b00011011 7
#85
03
b1010 4
b00110010 5
#86
b00110010 -
13
b00011110 7
#87
03
b1011 4
b00110111 5
#88
b00110111 .
13
b00100001 7
#89
03
b1100 4
b00111100 5
#90
b00111100 /
13
b00100100 7
#91
03
b1101 4
b01000001 5
#92
b01000001 0
13
b00100111 7
#93
03
b1110 4
b01000110 5
#94
b01000110 1
13
b00101010 7
#95
03
b1111 4
b01001011 5
#96
b01001011 2
13
b00101101 7
#97
03
b0000 4
b10100000 5
b1111 8
b10110000 9
1:
#98
b10100000 #
b10110000 2
13
b00000000 7
b01001011 ;
#99
03
06
0:
#100
13
b10100000 7
b10110000 ;
#101
03
b0001 4
b10100001 5
16
b1110 8
b10110001 9
1:
#102
b10100001 $
b10110001 1
13
b00000101 7
b01000110 ;
#103
03
06
0:
#104
13
b10100001 7
b10110001 ;
#105
03
b0010 4
b10100010 5
16
b1101 8
b10110010 9
1:
#106
b10100010 %
b10110010 0
13
b00001010 7
b01000001 ;
#107
03
06
0:
#108
13
b10100010 7
b10110010 ;
#109
03
b0011 4
b10100011 5
16
b1100 8
b10110011 9
1:
#110
b10100011 &
b10110011 /
13
b00001111 7
b00111100 ;
#111
03
06
0:
#112
13
b10100011 7
b10110011 ;
#113
03
b0100 4
b10100100 5
16
b1011 8
b10110100 9
1:
#114
b10100100 '
b10110100 .
13
b00010100 7
b00110111 ;
#115
03
06
0:
#116
13
b10100100 7
b10110100 ;
#117
03
b0101 4
b10100101 5
16
b1010 8
b10110101 9
1:
#118
b10100101 (
b10110101 -
13
b00011001 7
b00110010 ;
#119
03
06
0:
#120
13
b10100101 7
b10110101 ;
#121
03
b0110 4
b10100110 5
16
b1001 8
b10110110 9
1:
#122
b10100110 )
b10110110 ,
13
b00011110 7
b00101101 ;
#123
03
06
0:
#124
13
b10100110 7
b10110110 ;
#125
03
b0111 4
b10100111 5
16
b1000 8
b10110111 9
1:
#126
b10100111 *
b10110111 +
13
b00100011 7
b00101000 ;
#127
03
06
0:
#128
13
b10100111 7
b10110111 ;
