libraries/filters/fir_filter.v
module fir_filter #(
    parameter DATA_WIDTH = 8,
    parameter COEFF_WIDTH = 8,
    parameter OUTPUT_WIDTH = DATA_WIDTH + COEFF_WIDTH + 3, // Extra bits to prevent overflow
    parameter TAP_COUNT = 4
)(
    input wire clk,
    input wire rst_n,
    input wire [DATA_WIDTH-1:0] data_in,
    input wire data_valid,
    output wire [OUTPUT_WIDTH-1:0] data_out,
    output reg data_out_valid
);

    // Define coefficient values (fixed for this example)
    // In a real design, these might be configurable via registers
    reg signed [COEFF_WIDTH-1:0] coeffs [0:TAP_COUNT-1];
    
    // Delay line for input samples
    reg signed [DATA_WIDTH-1:0] delay_line [0:TAP_COUNT-1];
    
    // Output register
    reg signed [OUTPUT_WIDTH-1:0] result;
    assign data_out = result;
    
    // Wire for MAC calculation
    wire signed [OUTPUT_WIDTH-1:0] mac_result;
    
    // Initialize coefficients
    integer i;
    initial begin
        // Simple low-pass filter coefficients as an example
        coeffs[0] = 1;
        coeffs[1] = 2;
        coeffs[2] = 2;
        coeffs[3] = 1;
    end
    
    // Combinational MAC calculation
    assign mac_result = (delay_line[0] * coeffs[0]) + 
                       (delay_line[1] * coeffs[1]) + 
                       (delay_line[2] * coeffs[2]) + 
                       (delay_line[3] * coeffs[3]);
    
    // Shift register and output logic
    always @(posedge clk or negedge rst_n) begin
        if (!rst_n) begin
            for (i = 0; i < TAP_COUNT; i = i + 1) begin
                delay_line[i] <= 0;
            end
            result <= 0;
            data_out_valid <= 0;
        end
        else begin
            if (data_valid) begin
                // Shift delay line
                for (i = TAP_COUNT-1; i > 0; i = i - 1) begin
                    delay_line[i] <= delay_line[i-1];
                end
                delay_line[0] <= data_in;
                
                // Store MAC result
                result <= mac_result;
                
                data_out_valid <= 1;
            end
            else begin
                data_out_valid <= 0;
            end
        end
    end

endmodule

fir_filter_sim.vcd
$version Generated by VerilatedVcd $end
$timescale 1ps $end
 $scope module TOP $end
  $var wire 1 . clk $end
  $var wire 1 / rst_n $end
  $var wire 8 0 data_in [7:0] $end
  $var wire 1 1 data_valid $end
  $var wire 19 2 data_out [18:0] $end
  $var wire 1 3 data_out_valid $end
  $scope module fir_filter $end
   $var wire 32 4 DATA_WIDTH [31:0] $end
   $var wire 32 4 COEFF_WIDTH [31:0] $end
   $var wire 32 5 OUTPUT_WIDTH [31:0] $end
   $var wire 32 6 TAP_COUNT [31:0] $end
   $var wire 1 . clk $end
   $var wire 1 / rst_n $end
   $var wire 8 0 data_in [7:0] $end
   $var wire 1 1 data_valid $end
   $var wire 19 2 data_out [18:0] $end
   $var wire 1 3 data_out_valid $end
   $var wire 8 # coeffs[0] [7:0] $end
   $var wire 8 $ coeffs[1] [7:0] $end
   $var wire 8 % coeffs[2] [7:0] $end
   $var wire 8 & coeffs[3] [7:0] $end
   $var wire 8 ' delay_line[0] [7:0] $end
   $var wire 8 ( delay_line[1] [7:0] $end
   $var wire 8 ) delay_line[2] [7:0] $end
   $var wire 8 * delay_line[3] [7:0] $end
   $var wire 19 + result [18:0] $end
   $var wire 19 , mac_result [18:0] $end
   $var wire 32 - i [31:0] $end
  $upscope $end
 $upscope $end
$enddefinitions $end


#0
b00000001 #
b00000010 $
b00000010 %
b00000001 &
b00000000 '
b00000000 (
b00000000 )
b00000000 *
b0000000000000000000 +
b0000000000000000000 ,
b00000000000000000000000000000000 -
0.
0/
b00000000 0
01
b0000000000000000000 2
03
b00000000000000000000000000001000 4
b00000000000000000000000000010011 5
b00000000000000000000000000000100 6
#1
b00000000000000000000000000000100 -
1.
#2
0.
1/
11
#3
b00000000000000000000000000000000 -
1.
13
#4
0.
#5
1.
#6
0.
b00000001 0
#7
b00000001 '
b0000000000000000001 ,
1.
#8
0.
#9
b00000001 (
b0000000000000000001 +
b0000000000000000011 ,
1.
b0000000000000000001 2
#10
0.
b00000010 0
#11
b00000010 '
b00000001 )
b0000000000000000011 +
b0000000000000000110 ,
1.
b0000000000000000011 2
#12
0.
b00000011 0
#13
b00000011 '
b00000010 (
b00000001 *
b0000000000000000110 +
b0000000000000001010 ,
1.
b0000000000000000110 2
#14
0.
#15
b00000011 (
b00000010 )
b0000000000000001010 +
b0000000000000001110 ,
1.
b0000000000000001010 2
#16
0.
b00000101 0
#17
b00000101 '
b00000011 )
b00000010 *
b0000000000000001110 +
b0000000000000010011 ,
1.
b0000000000000001110 2
#18
0.
#19
b00000101 (
b00000011 *
b0000000000000010011 +
b0000000000000011000 ,
1.
b0000000000000010011 2
#20
0.
b00000110 0
#21
b00000110 '
b00000101 )
b0000000000000011000 +
b0000000000000011101 ,
1.
b0000000000000011000 2
#22
0.
b00000111 0
#23
b00000111 '
b00000110 (
b00000101 *
b0000000000000011101 +
b0000000000000100010 ,
1.
b0000000000000011101 2
#24
0.
#25
b00000111 (
b00000110 )
b0000000000000100010 +
b0000000000000100110 ,
1.
b0000000000000100010 2
#26
0.
b00001000 0
#27
b00001000 '
b00000111 )
b00000110 *
b0000000000000100110 +
b0000000000000101010 ,
1.
b0000000000000100110 2
#28
0.
b00001001 0
#29
b00001001 '
b00001000 (
b00000111 *
b0000000000000101010 +
b0000000000000101110 ,
1.
b0000000000000101010 2
#30
0.
b00001010 0
#31
b00001010 '
b00001001 (
b00001000 )
b0000000000000101110 +
b0000000000000110011 ,
1.
b0000000000000101110 2
#32
0.
b00001011 0
#33
b00001011 '
b00001010 (
b00001001 )
b00001000 *
b0000000000000110011 +
b0000000000000111001 ,
1.
b0000000000000110011 2
#34
0.
#35
b00001011 (
b00001010 )
b00001001 *
b0000000000000111001 +
b0000000000000111110 ,
1.
b0000000000000111001 2
#36
0.
b00001100 0
#37
b00001100 '
b00001011 )
b00001010 *
b0000000000000111110 +
b0000000000001000010 ,
1.
b0000000000000111110 2
#38
0.
#39
b00001100 (
b00001011 *
b0000000000001000010 +
b0000000000001000101 ,
1.
b0000000000001000010 2
#40
0.
b00001101 0
#41
b00001101 '
b00001100 )
b0000000000001000101 +
b0000000000001001000 ,
1.
b0000000000001000101 2
#42
0.
b00001110 0
#43
b00001110 '
b00001101 (
b00001100 *
b0000000000001001000 +
b0000000000001001100 ,
1.
b0000000000001001000 2
#44
0.
b00001111 0
#45
b00001111 '
b00001110 (
b00001101 )
b0000000000001001100 +
b0000000000001010001 ,
1.
b0000000000001001100 2
#46
0.
#47
b00001111 (
b00001110 )
b00001101 *
b0000000000001010001 +
b0000000000001010110 ,
1.
b0000000000001010001 2
#48
0.
b00010000 0
#49
b00010000 '
b00001111 )
b00001110 *
b0000000000001010110 +
b0000000000001011010 ,
1.
b0000000000001010110 2
#50
0.
#51
b00010000 (
b00001111 *
b0000000000001011010 +
b0000000000001011101 ,
1.
b0000000000001011010 2
#52
0.
b00010001 0
#53
b00010001 '
b00010000 )
b0000000000001011101 +
b0000000000001100000 ,
1.
b0000000000001011101 2
#54
0.
b00010010 0
#55
b00010010 '
b00010001 (
b00010000 *
b0000000000001100000 +
b0000000000001100100 ,
1.
b0000000000001100000 2
#56
0.
b00010011 0
#57
b00010011 '
b00010010 (
b00010001 )
b0000000000001100100 +
b0000000000001101001 ,
1.
b0000000000001100100 2
#58
0.
#59
b00010011 (
b00010010 )
b00010001 *
b0000000000001101001 +
b0000000000001101110 ,
1.
b0000000000001101001 2
#60
0.
#61
b00010011 )
b00010010 *
b0000000000001101110 +
b0000000000001110001 ,
1.
b0000000000001101110 2
#62
0.
b00010100 0
#63
b00010100 '
b00010011 *
b0000000000001110001 +
b0000000000001110011 ,
1.
b0000000000001110001 2
#64
0.
#65
b00010100 (
b0000000000001110011 +
b0000000000001110101 ,
1.
b0000000000001110011 2
#66
0.
b00010101 0
#67
b00010101 '
b00010100 )
b0000000000001110101 +
b0000000000001111000 ,
1.
b0000000000001110101 2
#68
0.
b00010110 0
#69
b00010110 '
b00010101 (
b00010100 *
b0000000000001111000 +
b0000000000001111100 ,
1.
b0000000000001111000 2
#70
0.
#71
b00010110 (
b00010101 )
b0000000000001111100 +
b0000000000010000000 ,
1.
b0000000000001111100 2
#72
0.
#73
b00010110 )
b00010101 *
b0000000000010000000 +
b0000000000010000011 ,
1.
b0000000000010000000 2
#74
0.
b00010111 0
#75
b00010111 '
b00010110 *
b0000000000010000011 +
b0000000000010000101 ,
1.
b0000000000010000011 2
#76
0.
#77
b00010111 (
b0000000000010000101 +
b0000000000010000111 ,
1.
b0000000000010000101 2
#78
0.
#79
b00010111 )
b0000000000010000111 +
b0000000000010001001 ,
1.
b0000000000010000111 2
#80
0.
b00011000 0
#81
b00011000 '
b00010111 *
b0000000000010001001 +
b0000000000010001011 ,
1.
b0000000000010001001 2
#82
0.
b00011001 0
#83
b00011001 '
b00011000 (
b0000000000010001011 +
b0000000000010001110 ,
1.
b0000000000010001011 2
#84
0.
#85
b00011001 (
b00011000 )
b0000000000010001110 +
b0000000000010010010 ,
1.
b0000000000010001110 2
#86
0.
#87
b00011001 )
b00011000 *
b0000000000010010010 +
b0000000000010010101 ,
1.
b0000000000010010010 2
#88
0.
#89
b00011001 *
b0000000000010010101 +
b0000000000010010110 ,
1.
b0000000000010010101 2
#90
0.
#91
b0000000000010010110 +
1.
b0000000000010010110 2
#92
0.
b00011010 0
#93
b00011010 '
b0000000000010010111 ,
1.
#94
0.
#95
b00011010 (
b0000000000010010111 +
b0000000000010011001 ,
1.
b0000000000010010111 2
#96
0.
#97
b00011010 )
b0000000000010011001 +
b0000000000010011011 ,
1.
b0000000000010011001 2
#98
0.
#99
b00011010 *
b0000000000010011011 +
b0000000000010011100 ,
1.
b0000000000010011011 2
#100
0.
#101
b0000000000010011100 +
1.
b0000000000010011100 2
#102
0.
b00011011 0
#103
b00011011 '
b0000000000010011101 ,
1.
#104
0.
b00011010 0
#105
b00011010 '
b00011011 (
b0000000000010011101 +
b0000000000010011110 ,
1.
b0000000000010011101 2
#106
0.
b00011011 0
#107
b00011011 '
b00011010 (
b00011011 )
b0000000000010011110 +
b0000000000010011111 ,
1.
b0000000000010011110 2
#108
0.
#109
b00011011 (
b00011010 )
b00011011 *
b0000000000010011111 +
b0000000000010100000 ,
1.
b0000000000010011111 2
#110
0.
#111
b00011011 )
b00011010 *
b0000000000010100000 +
b0000000000010100001 ,
1.
b0000000000010100000 2
#112
0.
#113
b00011011 *
b0000000000010100001 +
b0000000000010100010 ,
1.
b0000000000010100001 2
#114
0.
#115
b0000000000010100010 +
1.
b0000000000010100010 2
#116
0.
#117
1.
#118
0.
b00011100 0
#119
b00011100 '
b0000000000010100011 ,
1.
#120
0.
#121
b00011100 (
b0000000000010100011 +
b0000000000010100101 ,
1.
b0000000000010100011 2
#122
0.
#123
b00011100 )
b0000000000010100101 +
b0000000000010100111 ,
1.
b0000000000010100101 2
#124
0.
b00011011 0
#125
b00011011 '
b00011100 *
b0000000000010100111 +
1.
b0000000000010100111 2
#126
0.
#127
b00011011 (
b0000000000010100101 ,
1.
#128
0.
#129
b00011011 )
b0000000000010100101 +
b0000000000010100011 ,
1.
b0000000000010100101 2
#130
0.
#131
b00011011 *
b0000000000010100011 +
b0000000000010100010 ,
1.
b0000000000010100011 2
#132
0.
#133
b0000000000010100010 +
1.
b0000000000010100010 2
#134
0.
#135
1.
#136
0.
#137
1.
#138
0.
b00011010 0
#139
b00011010 '
b0000000000010100001 ,
1.
#140
0.
#141
b00011010 (
b0000000000010100001 +
b0000000000010011111 ,
1.
b0000000000010100001 2
#142
0.
#143
b00011010 )
b0000000000010011111 +
b0000000000010011101 ,
1.
b0000000000010011111 2
#144
0.
#145
b00011010 *
b0000000000010011101 +
b0000000000010011100 ,
1.
b0000000000010011101 2
#146
0.
#147
b0000000000010011100 +
1.
b0000000000010011100 2
#148
0.
#149
1.
#150
0.
b00011001 0
#151
b00011001 '
b0000000000010011011 ,
1.
#152
0.
#153
b00011001 (
b0000000000010011011 +
b0000000000010011001 ,
1.
b0000000000010011011 2
#154
0.
b00011000 0
#155
b00011000 '
b00011001 )
b0000000000010011001 +
b0000000000010010110 ,
1.
b0000000000010011001 2
#156
0.
#157
b00011000 (
b00011001 *
b0000000000010010110 +
b0000000000010010011 ,
1.
b0000000000010010110 2
#158
0.
#159
b00011000 )
b0000000000010010011 +
b0000000000010010001 ,
1.
b0000000000010010011 2
#160
0.
#161
b00011000 *
b0000000000010010001 +
b0000000000010010000 ,
1.
b0000000000010010001 2
#162
0.
b00010111 0
#163
b00010111 '
b0000000000010010000 +
b0000000000010001111 ,
1.
b0000000000010010000 2
#164
0.
#165
b00010111 (
b0000000000010001111 +
b0000000000010001101 ,
1.
b0000000000010001111 2
#166
0.
b00010110 0
#167
b00010110 '
b00010111 )
b0000000000010001101 +
b0000000000010001010 ,
1.
b0000000000010001101 2
#168
0.
#169
b00010110 (
b00010111 *
b0000000000010001010 +
b0000000000010000111 ,
1.
b0000000000010001010 2
#170
0.
#171
b00010110 )
b0000000000010000111 +
b0000000000010000101 ,
1.
b0000000000010000111 2
#172
0.
#173
b00010110 *
b0000000000010000101 +
b0000000000010000100 ,
1.
b0000000000010000101 2
#174
0.
b00010101 0
#175
b00010101 '
b0000000000010000100 +
b0000000000010000011 ,
1.
b0000000000010000100 2
#176
0.
b00010100 0
#177
b00010100 '
b00010101 (
b0000000000010000011 +
b0000000000010000000 ,
1.
b0000000000010000011 2
#178
0.
#179
b00010100 (
b00010101 )
b0000000000010000000 +
b0000000000001111100 ,
1.
b0000000000010000000 2
#180
0.
b00010011 0
#181
b00010011 '
b00010100 )
b00010101 *
b0000000000001111100 +
b0000000000001111000 ,
1.
b0000000000001111100 2
#182
0.
#183
b00010011 (
b00010100 *
b0000000000001111000 +
b0000000000001110101 ,
1.
b0000000000001111000 2
#184
0.
#185
b00010011 )
b0000000000001110101 +
b0000000000001110011 ,
1.
b0000000000001110101 2
#186
0.
b00010010 0
#187
b00010010 '
b00010011 *
b0000000000001110011 +
b0000000000001110001 ,
1.
b0000000000001110011 2
#188
0.
#189
b00010010 (
b0000000000001110001 +
b0000000000001101111 ,
1.
b0000000000001110001 2
#190
0.
b00010001 0
#191
b00010001 '
b00010010 )
b0000000000001101111 +
b0000000000001101100 ,
1.
b0000000000001101111 2
#192
0.
#193
b00010001 (
b00010010 *
b0000000000001101100 +
b0000000000001101001 ,
1.
b0000000000001101100 2
#194
0.
b00010000 0
#195
b00010000 '
b00010001 )
b0000000000001101001 +
b0000000000001100110 ,
1.
b0000000000001101001 2
#196
0.
#197
b00010000 (
b00010001 *
b0000000000001100110 +
b0000000000001100011 ,
1.
b0000000000001100110 2
#198
0.
#199
b00010000 )
b0000000000001100011 +
b0000000000001100001 ,
1.
b0000000000001100011 2
#200
0.
b00001111 0
#201
b00001111 '
b00010000 *
b0000000000001100001 +
b0000000000001011111 ,
1.
b0000000000001100001 2
#202
0.
01
#203
1.
03
