gray_counter.v
module gray_counter #(
    parameter WIDTH = 4
)(
    input wire clk,
    input wire rst_n,
    input wire enable,
    output reg [WIDTH-1:0] gray_out,
    output wire [WIDTH-1:0] binary_out
);

    // Internal binary counter
    reg [WIDTH-1:0] binary_count;
    
    // Convert binary count to Gray code
    assign binary_out = binary_count;
    
    always @(posedge clk or negedge rst_n) begin
        if (!rst_n) begin
            binary_count <= {WIDTH{1'b0}};
            gray_out <= {WIDTH{1'b0}};
        end else if (enable) begin
            // Update binary counter
            binary_count <= binary_count + 1'b1;
            
            // Calculate Gray code for the NEXT binary value
            // Gray code = binary XOR (binary >> 1)
            gray_out <= (binary_count + 1'b1) ^ ((binary_count + 1'b1) >> 1);
        end
    end

endmodule

gray_counter_sim.vcd
$version Generated by VerilatedVcd $end
$timescale 1ps $end
 $scope module TOP $end
  $var wire 1 # clk $end
  $var wire 1 $ rst_n $end
  $var wire 1 % enable $end
  $var wire 4 & gray_out [3:0] $end
  $var wire 4 ' binary_out [3:0] $end
  $scope module gray_counter $end
   $var wire 32 ) WIDTH [31:0] $end
   $var wire 1 # clk $end
   $var wire 1 $ rst_n $end
   $var wire 1 % enable $end
   $var wire 4 & gray_out [3:0] $end
   $var wire 4 ' binary_out [3:0] $end
   $var wire 4 ( binary_count [3:0] $end
  $upscope $end
 $upscope $end
$enddefinitions $end


#0
0#
0$
0%
b0000 &
b0000 '
b0000 (
b00000000000000000000000000000100 )
#1
1#
#2
0#
1$
1%
#3
1#
b0001 &
b0001 '
b0001 (
#4
0#
#5
1#
b0011 &
b0010 '
b0010 (
#6
0#
#7
1#
b0010 &
b0011 '
b0011 (
#8
0#
#9
1#
b0110 &
b0100 '
b0100 (
#10
0#
#11
1#
b0111 &
b0101 '
b0101 (
#12
0#
#13
1#
b0101 &
b0110 '
b0110 (
#14
0#
#15
1#
b0100 &
b0111 '
b0111 (
#16
0#
#17
1#
b1100 &
b1000 '
b1000 (
#18
0#
#19
1#
b1101 &
b1001 '
b1001 (
#20
0#
#21
1#
b1111 &
b1010 '
b1010 (
#22
0#
#23
1#
b1110 &
b1011 '
b1011 (
#24
0#
#25
1#
b1010 &
b1100 '
b1100 (
#26
0#
#27
1#
b1011 &
b1101 '
b1101 (
#28
0#
#29
1#
b1001 &
b1110 '
b1110 (
#30
0#
#31
1#
b1000 &
b1111 '
b1111 (
#32
0#
#33
1#
b0000 &
b0000 '
b0000 (
