parameterized_barrel_rotator.v
module parameterized_barrel_rotator #(
    parameter DATA_WIDTH = 32,                   // Width of data
    parameter SHIFT_WIDTH = $clog2(DATA_WIDTH)   // Width of shift amount signal
) (
    input wire [DATA_WIDTH-1:0] data_in,
    input wire [SHIFT_WIDTH-1:0] rotate_amount,
    input wire direction,  // 0 for right rotation, 1 for left rotation
    output reg [DATA_WIDTH-1:0] data_out
);
    // Helpers for performing the rotation
    reg [DATA_WIDTH-1:0] temp_data;
    reg [2*DATA_WIDTH-1:0] extended_data;
    reg [SHIFT_WIDTH-1:0] effective_rotate;
    
    always @(*) begin
        // Create an extended data word to simplify rotation
        extended_data = {data_in, data_in};
        
        // Use the rotate amount directly
        effective_rotate = rotate_amount;
        
        if (direction == 1'b0) begin
            // Right rotation
            // For right rotation, data_out[N-1:0] = {data_in[rotate-1:0], data_in[N-1:rotate]}
            // Using the extended data, this becomes: extended_data[N+rotate-1:rotate]
            temp_data = extended_data[DATA_WIDTH+effective_rotate-1 -: DATA_WIDTH];
        end else begin
            // Left rotation
            // For left rotation, data_out[N-1:0] = {data_in[N-1-rotate:0], data_in[N-1:N-rotate]}
            // Using the extended data, this becomes: extended_data[N-1-rotate+N:N-rotate]
            // Simplifies to: extended_data[2*N-1-rotate:N-rotate]
            temp_data = extended_data[2*DATA_WIDTH-1-effective_rotate -: DATA_WIDTH];
        end
        
        data_out = temp_data;
    end

endmodule

parameterized_barrel_rotator_sim.vcd
$version Generated by VerilatedVcd $end
$timescale 1ps $end
 $scope module TOP $end
  $var wire 32 ' data_in [31:0] $end
  $var wire 5 ( rotate_amount [4:0] $end
  $var wire 1 ) direction $end
  $var wire 32 * data_out [31:0] $end
  $scope module parameterized_barrel_rotator $end
   $var wire 32 + DATA_WIDTH [31:0] $end
   $var wire 32 , SHIFT_WIDTH [31:0] $end
   $var wire 32 ' data_in [31:0] $end
   $var wire 5 ( rotate_amount [4:0] $end
   $var wire 1 ) direction $end
   $var wire 32 * data_out [31:0] $end
   $var wire 32 # temp_data [31:0] $end
   $var wire 64 $ extended_data [63:0] $end
   $var wire 5 & effective_rotate [4:0] $end
  $upscope $end
 $upscope $end
$enddefinitions $end


#0
b00000000000000000000000000000001 #
b0000000000000000000000000000000100000000000000000000000000000001 $
b00000 &
b00000000000000000000000000000001 '
b00000 (
0)
b00000000000000000000000000000001 *
b00000000000000000000000000100000 +
b00000000000000000000000000000101 ,
#1
1)
#2
b10000000000000000000000000000000 #
b00001 &
b00001 (
0)
b10000000000000000000000000000000 *
#3
b00000000000000000000000000000010 #
1)
b00000000000000000000000000000010 *
#4
b00010000000000000000000000000000 #
b00100 &
b00100 (
0)
b00010000000000000000000000000000 *
#5
b00000000000000000000000000010000 #
1)
b00000000000000000000000000010000 *
#6
b00000010000000000000000000000000 #
b00111 &
b00111 (
0)
b00000010000000000000000000000000 *
#7
b00000000000000000000000010000000 #
1)
b00000000000000000000000010000000 *
#8
b00000001000000000000000000000000 #
b01000 &
b01000 (
0)
b00000001000000000000000000000000 *
#9
b00000000000000000000000100000000 #
1)
b00000000000000000000000100000000 *
#10
b00000000000000100000000000000000 #
b01111 &
b01111 (
0)
b00000000000000100000000000000000 *
#11
b00000000000000001000000000000000 #
1)
b00000000000000001000000000000000 *
#12
b00000000000000010000000000000000 #
b10000 &
b10000 (
0)
b00000000000000010000000000000000 *
#13
1)
#14
b00000000000000000000001000000000 #
b10111 &
b10111 (
0)
b00000000000000000000001000000000 *
#15
b00000000100000000000000000000000 #
1)
b00000000100000000000000000000000 *
#16
b00000000000000000000000100000000 #
b11000 &
b11000 (
0)
b00000000000000000000000100000000 *
#17
b00000001000000000000000000000000 #
1)
b00000001000000000000000000000000 *
#18
b00000000000000000000000000000010 #
b11111 &
b11111 (
0)
b00000000000000000000000000000010 *
#19
b10000000000000000000000000000000 #
1)
b10000000000000000000000000000000 *
#20
b1000000000000000000000000000000010000000000000000000000000000000 $
b00000 &
b10000000000000000000000000000000 '
b00000 (
0)
#21
1)
#22
b01000000000000000000000000000000 #
b00001 &
b00001 (
0)
b01000000000000000000000000000000 *
#23
b00000000000000000000000000000001 #
1)
b00000000000000000000000000000001 *
#24
b00001000000000000000000000000000 #
b00100 &
b00100 (
0)
b00001000000000000000000000000000 *
#25
b00000000000000000000000000001000 #
1)
b00000000000000000000000000001000 *
#26
b00000001000000000000000000000000 #
b00111 &
b00111 (
0)
b00000001000000000000000000000000 *
#27
b00000000000000000000000001000000 #
1)
b00000000000000000000000001000000 *
#28
b00000000100000000000000000000000 #
b01000 &
b01000 (
0)
b00000000100000000000000000000000 *
#29
b00000000000000000000000010000000 #
1)
b00000000000000000000000010000000 *
#30
b00000000000000010000000000000000 #
b01111 &
b01111 (
0)
b00000000000000010000000000000000 *
#31
b00000000000000000100000000000000 #
1)
b00000000000000000100000000000000 *
#32
b00000000000000001000000000000000 #
b10000 &
b10000 (
0)
b00000000000000001000000000000000 *
#33
1)
#34
b00000000000000000000000100000000 #
b10111 &
b10111 (
0)
b00000000000000000000000100000000 *
#35
b00000000010000000000000000000000 #
1)
b00000000010000000000000000000000 *
#36
b00000000000000000000000010000000 #
b11000 &
b11000 (
0)
b00000000000000000000000010000000 *
#37
b00000000100000000000000000000000 #
1)
b00000000100000000000000000000000 *
#38
b00000000000000000000000000000001 #
b11111 &
b11111 (
0)
b00000000000000000000000000000001 *
#39
b01000000000000000000000000000000 #
1)
b01000000000000000000000000000000 *
#40
b01010101010101010101010101010101 #
b0101010101010101010101010101010101010101010101010101010101010101 $
b00000 &
b01010101010101010101010101010101 '
b00000 (
0)
b01010101010101010101010101010101 *
#41
1)
#42
b10101010101010101010101010101010 #
b00001 &
b00001 (
0)
b10101010101010101010101010101010 *
#43
1)
#44
b01010101010101010101010101010101 #
b00100 &
b00100 (
0)
b01010101010101010101010101010101 *
#45
1)
#46
b10101010101010101010101010101010 #
b00111 &
b00111 (
0)
b10101010101010101010101010101010 *
#47
1)
#48
b01010101010101010101010101010101 #
b01000 &
b01000 (
0)
b01010101010101010101010101010101 *
#49
1)
#50
b10101010101010101010101010101010 #
b01111 &
b01111 (
0)
b10101010101010101010101010101010 *
#51
1)
#52
b01010101010101010101010101010101 #
b10000 &
b10000 (
0)
b01010101010101010101010101010101 *
#53
1)
#54
b10101010101010101010101010101010 #
b10111 &
b10111 (
0)
b10101010101010101010101010101010 *
#55
1)
#56
b01010101010101010101010101010101 #
b11000 &
b11000 (
0)
b01010101010101010101010101010101 *
#57
1)
#58
b10101010101010101010101010101010 #
b11111 &
b11111 (
0)
b10101010101010101010101010101010 *
#59
1)
#60
b1010101010101010101010101010101010101010101010101010101010101010 $
b00000 &
b10101010101010101010101010101010 '
b00000 (
0)
#61
1)
#62
b01010101010101010101010101010101 #
b00001 &
b00001 (
0)
b01010101010101010101010101010101 *
#63
1)
#64
b10101010101010101010101010101010 #
b00100 &
b00100 (
0)
b10101010101010101010101010101010 *
#65
1)
#66
b01010101010101010101010101010101 #
b00111 &
b00111 (
0)
b01010101010101010101010101010101 *
#67
1)
#68
b10101010101010101010101010101010 #
b01000 &
b01000 (
0)
b10101010101010101010101010101010 *
#69
1)
#70
b01010101010101010101010101010101 #
b01111 &
b01111 (
0)
b01010101010101010101010101010101 *
#71
1)
#72
b10101010101010101010101010101010 #
b10000 &
b10000 (
0)
b10101010101010101010101010101010 *
#73
1)
#74
b01010101010101010101010101010101 #
b10111 &
b10111 (
0)
b01010101010101010101010101010101 *
#75
1)
#76
b10101010101010101010101010101010 #
b11000 &
b11000 (
0)
b10101010101010101010101010101010 *
#77
1)
#78
b01010101010101010101010101010101 #
b11111 &
b11111 (
0)
b01010101010101010101010101010101 *
#79
1)
#80
b11111111111111111111111111111111 #
b1111111111111111111111111111111111111111111111111111111111111111 $
b00000 &
b11111111111111111111111111111111 '
b00000 (
0)
b11111111111111111111111111111111 *
#81
1)
#82
b00001 &
b00001 (
0)
#83
1)
#84
b00100 &
b00100 (
0)
#85
1)
#86
b00111 &
b00111 (
0)
#87
1)
#88
b01000 &
b01000 (
0)
#89
1)
#90
b01111 &
b01111 (
0)
#91
1)
#92
b10000 &
b10000 (
0)
#93
1)
#94
b10111 &
b10111 (
0)
#95
1)
#96
b11000 &
b11000 (
0)
#97
1)
#98
b11111 &
b11111 (
0)
#99
1)
#100
b00010010001101000101011001111000 #
b0001001000110100010101100111100000010010001101000101011001111000 $
b00000 &
b00010010001101000101011001111000 '
b00000 (
0)
b00010010001101000101011001111000 *
#101
1)
#102
b00001001000110100010101100111100 #
b00001 &
b00001 (
0)
b00001001000110100010101100111100 *
#103
b00100100011010001010110011110000 #
1)
b00100100011010001010110011110000 *
#104
b10000001001000110100010101100111 #
b00100 &
b00100 (
0)
b10000001001000110100010101100111 *
#105
b00100011010001010110011110000001 #
1)
b00100011010001010110011110000001 *
#106
b11110000001001000110100010101100 #
b00111 &
b00111 (
0)
b11110000001001000110100010101100 *
#107
b00011010001010110011110000001001 #
1)
b00011010001010110011110000001001 *
#108
b01111000000100100011010001010110 #
b01000 &
b01000 (
0)
b01111000000100100011010001010110 *
#109
b00110100010101100111100000010010 #
1)
b00110100010101100111100000010010 *
#110
b10101100111100000010010001101000 #
b01111 &
b01111 (
0)
b10101100111100000010010001101000 *
#111
b00101011001111000000100100011010 #
1)
b00101011001111000000100100011010 *
#112
b01010110011110000001001000110100 #
b10000 &
b10000 (
0)
b01010110011110000001001000110100 *
#113
1)
#114
b01101000101011001111000000100100 #
b10111 &
b10111 (
0)
b01101000101011001111000000100100 *
#115
b00111100000010010001101000101011 #
1)
b00111100000010010001101000101011 *
#116
b00110100010101100111100000010010 #
b11000 &
b11000 (
0)
b00110100010101100111100000010010 *
#117
b01111000000100100011010001010110 #
1)
b01111000000100100011010001010110 *
#118
b00100100011010001010110011110000 #
b11111 &
b11111 (
0)
b00100100011010001010110011110000 *
#119
b00001001000110100010101100111100 #
1)
b00001001000110100010101100111100 *
#120
b00000000000000001111111111111111 #
b0000000000000000111111111111111100000000000000001111111111111111 $
b00000 &
b00000000000000001111111111111111 '
b00000 (
0)
b00000000000000001111111111111111 *
#121
1)
#122
b10000000000000000111111111111111 #
b00001 &
b00001 (
0)
b10000000000000000111111111111111 *
#123
b00000000000000011111111111111110 #
1)
b00000000000000011111111111111110 *
#124
b11110000000000000000111111111111 #
b00100 &
b00100 (
0)
b11110000000000000000111111111111 *
#125
b00000000000011111111111111110000 #
1)
b00000000000011111111111111110000 *
#126
b11111110000000000000000111111111 #
b00111 &
b00111 (
0)
b11111110000000000000000111111111 *
#127
b00000000011111111111111110000000 #
1)
b00000000011111111111111110000000 *
#128
b11111111000000000000000011111111 #
b01000 &
b01000 (
0)
b11111111000000000000000011111111 *
#129
b00000000111111111111111100000000 #
1)
b00000000111111111111111100000000 *
#130
b11111111111111100000000000000001 #
b01111 &
b01111 (
0)
b11111111111111100000000000000001 *
#131
b01111111111111111000000000000000 #
1)
b01111111111111111000000000000000 *
#132
b11111111111111110000000000000000 #
b10000 &
b10000 (
0)
b11111111111111110000000000000000 *
#133
1)
#134
b00000001111111111111111000000000 #
b10111 &
b10111 (
0)
b00000001111111111111111000000000 *
#135
b11111111100000000000000001111111 #
1)
b11111111100000000000000001111111 *
#136
b00000000111111111111111100000000 #
b11000 &
b11000 (
0)
b00000000111111111111111100000000 *
#137
b11111111000000000000000011111111 #
1)
b11111111000000000000000011111111 *
#138
b00000000000000011111111111111110 #
b11111 &
b11111 (
0)
b00000000000000011111111111111110 *
#139
b10000000000000000111111111111111 #
1)
b10000000000000000111111111111111 *
#140
b11111111111111110000000000000000 #
b1111111111111111000000000000000011111111111111110000000000000000 $
b00000 &
b11111111111111110000000000000000 '
b00000 (
0)
b11111111111111110000000000000000 *
#141
1)
#142
b01111111111111111000000000000000 #
b00001 &
b00001 (
0)
b01111111111111111000000000000000 *
#143
b11111111111111100000000000000001 #
1)
b11111111111111100000000000000001 *
#144
b00001111111111111111000000000000 #
b00100 &
b00100 (
0)
b00001111111111111111000000000000 *
#145
b11111111111100000000000000001111 #
1)
b11111111111100000000000000001111 *
#146
b00000001111111111111111000000000 #
b00111 &
b00111 (
0)
b00000001111111111111111000000000 *
#147
b11111111100000000000000001111111 #
1)
b11111111100000000000000001111111 *
#148
b00000000111111111111111100000000 #
b01000 &
b01000 (
0)
b00000000111111111111111100000000 *
#149
b11111111000000000000000011111111 #
1)
b11111111000000000000000011111111 *
#150
b00000000000000011111111111111110 #
b01111 &
b01111 (
0)
b00000000000000011111111111111110 *
#151
b10000000000000000111111111111111 #
1)
b10000000000000000111111111111111 *
#152
b00000000000000001111111111111111 #
b10000 &
b10000 (
0)
b00000000000000001111111111111111 *
#153
1)
#154
b11111110000000000000000111111111 #
b10111 &
b10111 (
0)
b11111110000000000000000111111111 *
#155
b00000000011111111111111110000000 #
1)
b00000000011111111111111110000000 *
#156
b11111111000000000000000011111111 #
b11000 &
b11000 (
0)
b11111111000000000000000011111111 *
#157
b00000000111111111111111100000000 #
1)
b00000000111111111111111100000000 *
#158
b11111111111111100000000000000001 #
b11111 &
b11111 (
0)
b11111111111111100000000000000001 *
#159
b01111111111111111000000000000000 #
1)
b01111111111111111000000000000000 *
