parameterized_freq_divider.v
module parameterized_freq_divider #(
    parameter COUNTER_WIDTH = 16,                  // Width of counter
    parameter DEFAULT_DIVIDE_VALUE = 2,            // Default division factor
    parameter DEFAULT_DUTY_CYCLE = 50              // Default duty cycle percentage (0-100)
) (
    input wire clk_in,                             // Input clock
    input wire rst_n,                              // Active low reset
    input wire enable,                             // Enable signal
    input wire [COUNTER_WIDTH-1:0] divide_value,   // Division factor (must be ≥ 2)
    input wire [6:0] duty_cycle,                   // Duty cycle percentage (0-100)
    output reg clk_out                             // Output clock
);

    // Internal counter
    reg [COUNTER_WIDTH-1:0] counter;
    
    // High time calculation based on duty cycle
    wire [COUNTER_WIDTH-1:0] high_time; // Same width as counter
    
    // Calculate high_time based on duty cycle percentage
    // Use multiplication and division to get accurate duty cycle
    assign high_time = (divide_value * duty_cycle + 50) / 100; // +50 for proper rounding
    
    always @(posedge clk_in or negedge rst_n) begin
        if (!rst_n) begin
            counter <= {COUNTER_WIDTH{1'b0}};
            clk_out <= 1'b0;
        end else if (!enable) begin
            counter <= {COUNTER_WIDTH{1'b0}};
            clk_out <= 1'b0;
        end else begin
            // Use default value if divide_value is invalid (less than 2)
            if (divide_value < 2) begin
                if (counter >= DEFAULT_DIVIDE_VALUE - 1) begin
                    counter <= {COUNTER_WIDTH{1'b0}};
                end else begin
                    counter <= counter + 1'b1;
                end
                
                // Calculate high time for default
                if (counter < ((DEFAULT_DIVIDE_VALUE * DEFAULT_DUTY_CYCLE) + 50) / 100) begin
                    clk_out <= 1'b1;
                end else begin
                    clk_out <= 1'b0;
                end
            end else begin
                // Normal operation with specified divide_value
                if (counter >= divide_value - 1) begin
                    counter <= {COUNTER_WIDTH{1'b0}};
                end else begin
                    counter <= counter + 1'b1;
                end
                
                // Set output based on duty cycle
                if (duty_cycle == 0) begin
                    // Special case for 0% duty cycle
                    clk_out <= 1'b0;
                end else if (duty_cycle >= 100) begin
                    // Special case for 100% duty cycle
                    clk_out <= 1'b1;
                end else begin
                    // Normal operation with calculated duty cycle
                    if (counter < high_time) begin
                        clk_out <= 1'b1;  // High portion of cycle
                    end else begin
                        clk_out <= 1'b0;  // Low portion of cycle
                    end
                end
            end
        end
    end

endmodule

parameterized_freq_divider_sim.vcd
$version Generated by VerilatedVcd $end
$timescale 1ps $end
 $scope module TOP $end
  $var wire 1 # clk_in $end
  $var wire 1 $ rst_n $end
  $var wire 1 % enable $end
  $var wire 16 & divide_value [15:0] $end
  $var wire 7 ' duty_cycle [6:0] $end
  $var wire 1 ( clk_out $end
  $scope module parameterized_freq_divider $end
   $var wire 32 + COUNTER_WIDTH [31:0] $end
   $var wire 32 , DEFAULT_DIVIDE_VALUE [31:0] $end
   $var wire 32 - DEFAULT_DUTY_CYCLE [31:0] $end
   $var wire 1 # clk_in $end
   $var wire 1 $ rst_n $end
   $var wire 1 % enable $end
   $var wire 16 & divide_value [15:0] $end
   $var wire 7 ' duty_cycle [6:0] $end
   $var wire 1 ( clk_out $end
   $var wire 16 ) counter [15:0] $end
   $var wire 16 * high_time [15:0] $end
  $upscope $end
 $upscope $end
$enddefinitions $end


#0
0#
0$
0%
b0000000000000010 &
b0110010 '
0(
b0000000000000000 )
b0000000000000001 *
b00000000000000000000000000010000 +
b00000000000000000000000000000010 ,
b00000000000000000000000000110010 -
#1
1#
#2
0#
1$
1%
#3
1#
1(
b0000000000000001 )
#4
0#
#5
1#
0(
b0000000000000000 )
#6
0#
#7
1#
1(
b0000000000000001 )
#8
0#
#9
1#
0(
b0000000000000000 )
#10
0#
#11
1#
1(
b0000000000000001 )
#12
0#
#13
1#
0(
b0000000000000000 )
#14
0#
#15
1#
1(
b0000000000000001 )
#16
0#
#17
1#
0(
b0000000000000000 )
#18
0#
#19
1#
1(
b0000000000000001 )
#20
0#
#21
1#
0(
b0000000000000000 )
#22
0#
#23
1#
1(
b0000000000000001 )
#24
0#
#25
1#
0(
b0000000000000000 )
#26
0#
#27
1#
1(
b0000000000000001 )
#28
0#
#29
1#
0(
b0000000000000000 )
#30
0#
#31
1#
1(
b0000000000000001 )
#32
0#
#33
1#
0(
b0000000000000000 )
#34
0#
#35
1#
1(
b0000000000000001 )
#36
0#
#37
1#
0(
b0000000000000000 )
#38
0#
#39
1#
1(
b0000000000000001 )
#40
0#
#41
1#
0(
b0000000000000000 )
#42
0#
#43
1#
1(
b0000000000000001 )
#44
0#
#45
1#
0(
b0000000000000000 )
#46
0#
#47
1#
1(
b0000000000000001 )
#48
0#
#49
1#
0(
b0000000000000000 )
#50
0#
#51
1#
1(
b0000000000000001 )
#52
0#
#53
1#
0(
b0000000000000000 )
#54
0#
#55
1#
1(
b0000000000000001 )
#56
0#
#57
1#
0(
b0000000000000000 )
#58
0#
#59
1#
1(
b0000000000000001 )
#60
0#
#61
1#
0(
b0000000000000000 )
#62
0#
#63
1#
1(
b0000000000000001 )
#64
0#
#65
1#
0(
b0000000000000000 )
#66
0#
#67
1#
1(
b0000000000000001 )
#68
0#
#69
1#
0(
b0000000000000000 )
#70
0#
#71
1#
1(
b0000000000000001 )
#72
0#
#73
1#
0(
b0000000000000000 )
#74
0#
#75
1#
1(
b0000000000000001 )
#76
0#
#77
1#
0(
b0000000000000000 )
#78
0#
#79
1#
1(
b0000000000000001 )
#80
0#
#81
1#
0(
b0000000000000000 )
#82
0#
#83
1#
1(
b0000000000000001 )
#84
0#
#85
1#
0(
b0000000000000000 )
#86
0#
#87
1#
1(
b0000000000000001 )
#88
0#
#89
1#
0(
b0000000000000000 )
#90
0#
#91
1#
1(
b0000000000000001 )
#92
0#
#93
1#
0(
b0000000000000000 )
#94
0#
#95
1#
1(
b0000000000000001 )
#96
0#
#97
1#
0(
b0000000000000000 )
#98
0#
#99
1#
1(
b0000000000000001 )
#100
0#
#101
1#
0(
b0000000000000000 )
#102
0#
#103
1#
1(
b0000000000000001 )
#104
0#
#105
1#
0(
b0000000000000000 )
#106
0#
#107
1#
1(
b0000000000000001 )
#108
0#
#109
1#
0(
b0000000000000000 )
#110
0#
#111
1#
1(
b0000000000000001 )
#112
0#
#113
1#
0(
b0000000000000000 )
#114
0#
#115
1#
1(
b0000000000000001 )
#116
0#
#117
1#
0(
b0000000000000000 )
#118
0#
#119
1#
1(
b0000000000000001 )
#120
0#
#121
1#
0(
b0000000000000000 )
#122
0#
#123
1#
1(
b0000000000000001 )
#124
0#
#125
1#
0(
b0000000000000000 )
#126
0#
#127
1#
1(
b0000000000000001 )
#128
0#
#129
1#
0(
b0000000000000000 )
#130
0#
#131
1#
1(
b0000000000000001 )
#132
0#
#133
1#
0(
b0000000000000000 )
#134
0#
#135
1#
1(
b0000000000000001 )
#136
0#
#137
1#
0(
b0000000000000000 )
#138
0#
#139
1#
1(
b0000000000000001 )
#140
0#
#141
1#
0(
b0000000000000000 )
#142
0#
#143
1#
1(
b0000000000000001 )
#144
0#
#145
1#
0(
b0000000000000000 )
#146
0#
#147
1#
1(
b0000000000000001 )
#148
0#
#149
1#
0(
b0000000000000000 )
#150
0#
#151
1#
1(
b0000000000000001 )
#152
0#
#153
1#
0(
b0000000000000000 )
#154
0#
#155
1#
1(
b0000000000000001 )
#156
0#
#157
1#
0(
b0000000000000000 )
#158
0#
#159
1#
1(
b0000000000000001 )
#160
0#
#161
1#
0(
b0000000000000000 )
#162
0#
#163
1#
1(
b0000000000000001 )
#164
0#
#165
1#
0(
b0000000000000000 )
#166
0#
#167
1#
1(
b0000000000000001 )
#168
0#
#169
1#
0(
b0000000000000000 )
#170
0#
#171
1#
1(
b0000000000000001 )
#172
0#
#173
1#
0(
b0000000000000000 )
#174
0#
#175
1#
1(
b0000000000000001 )
#176
0#
#177
1#
0(
b0000000000000000 )
#178
0#
#179
1#
1(
b0000000000000001 )
#180
0#
#181
1#
0(
b0000000000000000 )
#182
0#
#183
1#
1(
b0000000000000001 )
#184
0#
#185
1#
0(
b0000000000000000 )
#186
0#
#187
1#
1(
b0000000000000001 )
#188
0#
#189
1#
0(
b0000000000000000 )
#190
0#
#191
1#
1(
b0000000000000001 )
#192
0#
#193
1#
0(
b0000000000000000 )
#194
0#
#195
1#
1(
b0000000000000001 )
#196
0#
#197
1#
0(
b0000000000000000 )
#198
0#
#199
1#
1(
b0000000000000001 )
#200
0#
#201
1#
0(
b0000000000000000 )
#202
0#
#203
1#
1(
b0000000000000001 )
#204
0#
#205
1#
0(
b0000000000000000 )
#206
0#
#207
1#
1(
b0000000000000001 )
#208
0#
#209
1#
0(
b0000000000000000 )
#210
0#
#211
1#
1(
b0000000000000001 )
#212
0#
#213
1#
0(
b0000000000000000 )
#214
0#
#215
1#
1(
b0000000000000001 )
#216
0#
#217
1#
0(
b0000000000000000 )
#218
0#
#219
1#
1(
b0000000000000001 )
#220
0#
#221
1#
0(
b0000000000000000 )
#222
0#
#223
1#
1(
b0000000000000001 )
#224
0#
#225
1#
0(
b0000000000000000 )
#226
0#
#227
1#
1(
b0000000000000001 )
#228
0#
#229
1#
0(
b0000000000000000 )
#230
0#
#231
1#
1(
b0000000000000001 )
#232
0#
#233
1#
0(
b0000000000000000 )
#234
0#
#235
1#
1(
b0000000000000001 )
#236
0#
#237
1#
0(
b0000000000000000 )
#238
0#
#239
1#
1(
b0000000000000001 )
#240
0#
#241
1#
0(
b0000000000000000 )
#242
0#
#243
1#
1(
b0000000000000001 )
#244
0#
#245
1#
0(
b0000000000000000 )
#246
0#
#247
1#
1(
b0000000000000001 )
#248
0#
#249
1#
0(
b0000000000000000 )
#250
0#
#251
1#
1(
b0000000000000001 )
#252
0#
#253
1#
0(
b0000000000000000 )
#254
0#
#255
1#
1(
b0000000000000001 )
#256
0#
#257
1#
0(
b0000000000000000 )
#258
0#
#259
1#
1(
b0000000000000001 )
#260
0#
#261
1#
0(
b0000000000000000 )
#262
0#
#263
1#
1(
b0000000000000001 )
#264
0#
#265
1#
0(
b0000000000000000 )
#266
0#
#267
1#
1(
b0000000000000001 )
#268
0#
#269
1#
0(
b0000000000000000 )
#270
0#
#271
1#
1(
b0000000000000001 )
#272
0#
#273
1#
0(
b0000000000000000 )
#274
0#
#275
1#
1(
b0000000000000001 )
#276
0#
#277
1#
0(
b0000000000000000 )
#278
0#
#279
1#
1(
b0000000000000001 )
#280
0#
#281
1#
0(
b0000000000000000 )
#282
0#
#283
1#
1(
b0000000000000001 )
#284
0#
#285
1#
0(
b0000000000000000 )
#286
0#
#287
1#
1(
b0000000000000001 )
#288
0#
#289
1#
0(
b0000000000000000 )
#290
0#
#291
1#
1(
b0000000000000001 )
#292
0#
#293
1#
0(
b0000000000000000 )
#294
0#
#295
1#
1(
b0000000000000001 )
#296
0#
#297
1#
0(
b0000000000000000 )
#298
0#
#299
1#
1(
b0000000000000001 )
#300
0#
#301
1#
0(
b0000000000000000 )
#302
0#
#303
1#
1(
b0000000000000001 )
#304
0#
#305
1#
0(
b0000000000000000 )
#306
0#
#307
1#
1(
b0000000000000001 )
#308
0#
#309
1#
0(
b0000000000000000 )
#310
0#
#311
1#
1(
b0000000000000001 )
#312
0#
#313
1#
0(
b0000000000000000 )
#314
0#
#315
1#
1(
b0000000000000001 )
#316
0#
#317
1#
0(
b0000000000000000 )
#318
0#
#319
1#
1(
b0000000000000001 )
#320
0#
#321
1#
0(
b0000000000000000 )
#322
0#
#323
1#
1(
b0000000000000001 )
#324
0#
#325
1#
0(
b0000000000000000 )
#326
0#
#327
1#
1(
b0000000000000001 )
#328
0#
#329
1#
0(
b0000000000000000 )
#330
0#
#331
1#
1(
b0000000000000001 )
#332
0#
#333
1#
0(
b0000000000000000 )
#334
0#
#335
1#
1(
b0000000000000001 )
#336
0#
#337
1#
0(
b0000000000000000 )
#338
0#
#339
1#
1(
b0000000000000001 )
#340
0#
#341
1#
0(
b0000000000000000 )
#342
0#
#343
1#
1(
b0000000000000001 )
#344
0#
#345
1#
0(
b0000000000000000 )
#346
0#
#347
1#
1(
b0000000000000001 )
#348
0#
#349
1#
0(
b0000000000000000 )
#350
0#
#351
1#
1(
b0000000000000001 )
#352
0#
#353
1#
0(
b0000000000000000 )
#354
0#
#355
1#
1(
b0000000000000001 )
#356
0#
#357
1#
0(
b0000000000000000 )
#358
0#
#359
1#
1(
b0000000000000001 )
#360
0#
#361
1#
0(
b0000000000000000 )
#362
0#
#363
1#
1(
b0000000000000001 )
#364
0#
#365
1#
0(
b0000000000000000 )
#366
0#
#367
1#
1(
b0000000000000001 )
#368
0#
#369
1#
0(
b0000000000000000 )
#370
0#
#371
1#
1(
b0000000000000001 )
#372
0#
#373
1#
0(
b0000000000000000 )
#374
0#
#375
1#
1(
b0000000000000001 )
#376
0#
#377
1#
0(
b0000000000000000 )
#378
0#
#379
1#
1(
b0000000000000001 )
#380
0#
#381
1#
0(
b0000000000000000 )
#382
0#
#383
1#
1(
b0000000000000001 )
#384
0#
#385
1#
0(
b0000000000000000 )
#386
0#
#387
1#
1(
b0000000000000001 )
#388
0#
#389
1#
0(
b0000000000000000 )
#390
0#
#391
1#
1(
b0000000000000001 )
#392
0#
#393
1#
0(
b0000000000000000 )
#394
0#
#395
1#
1(
b0000000000000001 )
#396
0#
#397
1#
0(
b0000000000000000 )
#398
0#
#399
1#
1(
b0000000000000001 )
#400
0#
#401
1#
0(
b0000000000000000 )
#402
0#
#403
1#
1(
b0000000000000001 )
#404
0#
#405
1#
0(
b0000000000000000 )
#406
0#
#407
1#
1(
b0000000000000001 )
#408
0#
#409
1#
0(
b0000000000000000 )
#410
0#
#411
1#
1(
b0000000000000001 )
#412
0#
#413
1#
0(
b0000000000000000 )
#414
0#
#415
1#
1(
b0000000000000001 )
#416
0#
#417
1#
0(
b0000000000000000 )
#418
0#
#419
1#
1(
b0000000000000001 )
#420
0#
#421
1#
0(
b0000000000000000 )
#422
0#
#423
1#
1(
b0000000000000001 )
#424
0#
#425
1#
0(
b0000000000000000 )
#426
0#
#427
1#
1(
b0000000000000001 )
#428
0#
#429
1#
0(
b0000000000000000 )
#430
0#
#431
1#
1(
b0000000000000001 )
#432
0#
#433
1#
0(
b0000000000000000 )
#434
0#
#435
1#
1(
b0000000000000001 )
#436
0#
#437
1#
0(
b0000000000000000 )
#438
0#
#439
1#
1(
b0000000000000001 )
#440
0#
#441
1#
0(
b0000000000000000 )
#442
0#
#443
1#
1(
b0000000000000001 )
#444
0#
#445
1#
0(
b0000000000000000 )
#446
0#
#447
1#
1(
b0000000000000001 )
#448
0#
#449
1#
0(
b0000000000000000 )
#450
0#
#451
1#
1(
b0000000000000001 )
#452
0#
#453
1#
0(
b0000000000000000 )
#454
0#
#455
1#
1(
b0000000000000001 )
#456
0#
#457
1#
0(
b0000000000000000 )
#458
0#
#459
1#
1(
b0000000000000001 )
#460
0#
#461
1#
0(
b0000000000000000 )
#462
0#
#463
1#
1(
b0000000000000001 )
#464
0#
#465
1#
0(
b0000000000000000 )
#466
0#
#467
1#
1(
b0000000000000001 )
#468
0#
#469
1#
0(
b0000000000000000 )
#470
0#
#471
1#
1(
b0000000000000001 )
#472
0#
#473
1#
0(
b0000000000000000 )
#474
0#
#475
1#
1(
b0000000000000001 )
#476
0#
#477
1#
0(
b0000000000000000 )
#478
0#
#479
1#
1(
b0000000000000001 )
#480
0#
#481
1#
0(
b0000000000000000 )
#482
0#
#483
1#
1(
b0000000000000001 )
#484
0#
#485
1#
0(
b0000000000000000 )
#486
0#
#487
1#
1(
b0000000000000001 )
#488
0#
#489
1#
0(
b0000000000000000 )
#490
0#
#491
1#
1(
b0000000000000001 )
#492
0#
#493
1#
0(
b0000000000000000 )
#494
0#
#495
1#
1(
b0000000000000001 )
#496
0#
#497
1#
0(
b0000000000000000 )
#498
0#
#499
1#
1(
b0000000000000001 )
#500
0#
#501
1#
0(
b0000000000000000 )
#502
0#
#503
1#
1(
b0000000000000001 )
#504
0#
#505
1#
0(
b0000000000000000 )
#506
0#
#507
1#
1(
b0000000000000001 )
#508
0#
#509
1#
0(
b0000000000000000 )
#510
0#
#511
1#
1(
b0000000000000001 )
#512
0#
#513
1#
0(
b0000000000000000 )
#514
0#
#515
1#
1(
b0000000000000001 )
#516
0#
#517
1#
0(
b0000000000000000 )
#518
0#
#519
1#
1(
b0000000000000001 )
#520
0#
#521
1#
0(
b0000000000000000 )
#522
0#
#523
1#
1(
b0000000000000001 )
#524
0#
#525
1#
0(
b0000000000000000 )
#526
0#
#527
1#
1(
b0000000000000001 )
#528
0#
#529
1#
0(
b0000000000000000 )
#530
0#
#531
1#
1(
b0000000000000001 )
#532
0#
#533
1#
0(
b0000000000000000 )
#534
0#
#535
1#
1(
b0000000000000001 )
#536
0#
#537
1#
0(
b0000000000000000 )
#538
0#
#539
1#
1(
b0000000000000001 )
#540
0#
#541
1#
0(
b0000000000000000 )
#542
0#
#543
1#
1(
b0000000000000001 )
#544
0#
#545
1#
0(
b0000000000000000 )
#546
0#
#547
1#
1(
b0000000000000001 )
#548
0#
#549
1#
0(
b0000000000000000 )
#550
0#
#551
1#
1(
b0000000000000001 )
#552
0#
#553
1#
0(
b0000000000000000 )
#554
0#
#555
1#
1(
b0000000000000001 )
#556
0#
#557
1#
0(
b0000000000000000 )
#558
0#
#559
1#
1(
b0000000000000001 )
#560
0#
#561
1#
0(
b0000000000000000 )
#562
0#
#563
1#
1(
b0000000000000001 )
#564
0#
#565
1#
0(
b0000000000000000 )
#566
0#
#567
1#
1(
b0000000000000001 )
#568
0#
#569
1#
0(
b0000000000000000 )
#570
0#
#571
1#
1(
b0000000000000001 )
#572
0#
#573
1#
0(
b0000000000000000 )
#574
0#
#575
1#
1(
b0000000000000001 )
#576
0#
#577
1#
0(
b0000000000000000 )
#578
0#
#579
1#
1(
b0000000000000001 )
#580
0#
#581
1#
0(
b0000000000000000 )
#582
0#
#583
1#
1(
b0000000000000001 )
#584
0#
#585
1#
0(
b0000000000000000 )
#586
0#
#587
1#
1(
b0000000000000001 )
#588
0#
#589
1#
0(
b0000000000000000 )
#590
0#
#591
1#
1(
b0000000000000001 )
#592
0#
#593
1#
0(
b0000000000000000 )
#594
0#
#595
1#
1(
b0000000000000001 )
#596
0#
#597
1#
0(
b0000000000000000 )
#598
0#
#599
1#
1(
b0000000000000001 )
#600
0#
#601
1#
0(
b0000000000000000 )
#602
0#
#603
1#
1(
b0000000000000001 )
#604
0#
#605
1#
0(
b0000000000000000 )
#606
0#
#607
1#
1(
b0000000000000001 )
#608
0#
#609
1#
0(
b0000000000000000 )
#610
0#
#611
1#
1(
b0000000000000001 )
#612
0#
#613
1#
0(
b0000000000000000 )
#614
0#
#615
1#
1(
b0000000000000001 )
#616
0#
#617
1#
0(
b0000000000000000 )
#618
0#
#619
1#
1(
b0000000000000001 )
#620
0#
#621
1#
0(
b0000000000000000 )
#622
0#
#623
1#
1(
b0000000000000001 )
#624
0#
#625
1#
0(
b0000000000000000 )
#626
0#
#627
1#
1(
b0000000000000001 )
#628
0#
#629
1#
0(
b0000000000000000 )
#630
0#
#631
1#
1(
b0000000000000001 )
#632
0#
#633
1#
0(
b0000000000000000 )
#634
0#
#635
1#
1(
b0000000000000001 )
#636
0#
#637
1#
0(
b0000000000000000 )
#638
0#
#639
1#
1(
b0000000000000001 )
#640
0#
#641
1#
0(
b0000000000000000 )
#642
0#
#643
1#
1(
b0000000000000001 )
#644
0#
#645
1#
0(
b0000000000000000 )
#646
0#
#647
1#
1(
b0000000000000001 )
#648
0#
#649
1#
0(
b0000000000000000 )
#650
0#
#651
1#
1(
b0000000000000001 )
#652
0#
#653
1#
0(
b0000000000000000 )
#654
0#
#655
1#
1(
b0000000000000001 )
#656
0#
#657
1#
0(
b0000000000000000 )
#658
0#
#659
1#
1(
b0000000000000001 )
#660
0#
#661
1#
0(
b0000000000000000 )
#662
0#
#663
1#
1(
b0000000000000001 )
#664
0#
#665
1#
0(
b0000000000000000 )
#666
0#
#667
1#
1(
b0000000000000001 )
#668
0#
#669
1#
0(
b0000000000000000 )
#670
0#
#671
1#
1(
b0000000000000001 )
#672
0#
#673
1#
0(
b0000000000000000 )
#674
0#
#675
1#
1(
b0000000000000001 )
#676
0#
#677
1#
0(
b0000000000000000 )
#678
0#
#679
1#
1(
b0000000000000001 )
#680
0#
#681
1#
0(
b0000000000000000 )
#682
0#
#683
1#
1(
b0000000000000001 )
#684
0#
#685
1#
0(
b0000000000000000 )
#686
0#
#687
1#
1(
b0000000000000001 )
#688
0#
#689
1#
0(
b0000000000000000 )
#690
0#
#691
1#
1(
b0000000000000001 )
#692
0#
#693
1#
0(
b0000000000000000 )
#694
0#
#695
1#
1(
b0000000000000001 )
#696
0#
#697
1#
0(
b0000000000000000 )
#698
0#
#699
1#
1(
b0000000000000001 )
#700
0#
#701
1#
0(
b0000000000000000 )
#702
0#
#703
1#
1(
b0000000000000001 )
#704
0#
#705
1#
0(
b0000000000000000 )
#706
0#
#707
1#
1(
b0000000000000001 )
#708
0#
#709
1#
0(
b0000000000000000 )
#710
0#
#711
1#
1(
b0000000000000001 )
#712
0#
#713
1#
0(
b0000000000000000 )
#714
0#
#715
1#
1(
b0000000000000001 )
#716
0#
#717
1#
0(
b0000000000000000 )
#718
0#
#719
1#
1(
b0000000000000001 )
#720
0#
#721
1#
0(
b0000000000000000 )
#722
0#
#723
1#
1(
b0000000000000001 )
#724
0#
#725
1#
0(
b0000000000000000 )
#726
0#
#727
1#
1(
b0000000000000001 )
#728
0#
#729
1#
0(
b0000000000000000 )
#730
0#
#731
1#
1(
b0000000000000001 )
#732
0#
#733
1#
0(
b0000000000000000 )
#734
0#
#735
1#
1(
b0000000000000001 )
#736
0#
#737
1#
0(
b0000000000000000 )
#738
0#
#739
1#
1(
b0000000000000001 )
#740
0#
#741
1#
0(
b0000000000000000 )
#742
0#
#743
1#
1(
b0000000000000001 )
#744
0#
#745
1#
0(
b0000000000000000 )
#746
0#
#747
1#
1(
b0000000000000001 )
#748
0#
#749
1#
0(
b0000000000000000 )
#750
0#
#751
1#
1(
b0000000000000001 )
#752
0#
#753
1#
0(
b0000000000000000 )
#754
0#
#755
1#
1(
b0000000000000001 )
#756
0#
#757
1#
0(
b0000000000000000 )
#758
0#
#759
1#
1(
b0000000000000001 )
#760
0#
#761
1#
0(
b0000000000000000 )
#762
0#
#763
1#
1(
b0000000000000001 )
#764
0#
#765
1#
0(
b0000000000000000 )
#766
0#
#767
1#
1(
b0000000000000001 )
#768
0#
#769
1#
0(
b0000000000000000 )
#770
0#
#771
1#
1(
b0000000000000001 )
#772
0#
#773
1#
0(
b0000000000000000 )
#774
0#
#775
1#
1(
b0000000000000001 )
#776
0#
#777
1#
0(
b0000000000000000 )
#778
0#
#779
1#
1(
b0000000000000001 )
#780
0#
#781
1#
0(
b0000000000000000 )
#782
0#
#783
1#
1(
b0000000000000001 )
#784
0#
#785
1#
0(
b0000000000000000 )
#786
0#
#787
1#
1(
b0000000000000001 )
#788
0#
#789
1#
0(
b0000000000000000 )
#790
0#
#791
1#
1(
b0000000000000001 )
#792
0#
#793
1#
0(
b0000000000000000 )
#794
0#
#795
1#
1(
b0000000000000001 )
#796
0#
#797
1#
0(
b0000000000000000 )
#798
0#
#799
1#
1(
b0000000000000001 )
#800
0#
#801
1#
0(
b0000000000000000 )
#802
0#
#803
1#
1(
b0000000000000001 )
#804
0#
#805
1#
0(
b0000000000000000 )
#806
0#
#807
1#
1(
b0000000000000001 )
#808
0#
#809
1#
0(
b0000000000000000 )
#810
0#
#811
1#
1(
b0000000000000001 )
#812
0#
#813
1#
0(
b0000000000000000 )
#814
0#
#815
1#
1(
b0000000000000001 )
#816
0#
#817
1#
0(
b0000000000000000 )
#818
0#
#819
1#
1(
b0000000000000001 )
#820
0#
#821
1#
0(
b0000000000000000 )
#822
0#
#823
1#
1(
b0000000000000001 )
#824
0#
#825
1#
0(
b0000000000000000 )
#826
0#
#827
1#
1(
b0000000000000001 )
#828
0#
#829
1#
0(
b0000000000000000 )
#830
0#
#831
1#
1(
b0000000000000001 )
#832
0#
#833
1#
0(
b0000000000000000 )
#834
0#
#835
1#
1(
b0000000000000001 )
#836
0#
#837
1#
0(
b0000000000000000 )
#838
0#
#839
1#
1(
b0000000000000001 )
#840
0#
#841
1#
0(
b0000000000000000 )
#842
0#
#843
1#
1(
b0000000000000001 )
#844
0#
#845
1#
0(
b0000000000000000 )
#846
0#
#847
1#
1(
b0000000000000001 )
#848
0#
#849
1#
0(
b0000000000000000 )
#850
0#
#851
1#
1(
b0000000000000001 )
#852
0#
#853
1#
0(
b0000000000000000 )
#854
0#
#855
1#
1(
b0000000000000001 )
#856
0#
#857
1#
0(
b0000000000000000 )
#858
0#
#859
1#
1(
b0000000000000001 )
#860
0#
#861
1#
0(
b0000000000000000 )
#862
0#
#863
1#
1(
b0000000000000001 )
#864
0#
#865
1#
0(
b0000000000000000 )
#866
0#
#867
1#
1(
b0000000000000001 )
#868
0#
#869
1#
0(
b0000000000000000 )
#870
0#
#871
1#
1(
b0000000000000001 )
#872
0#
#873
1#
0(
b0000000000000000 )
#874
0#
#875
1#
1(
b0000000000000001 )
#876
0#
#877
1#
0(
b0000000000000000 )
#878
0#
#879
1#
1(
b0000000000000001 )
#880
0#
#881
1#
0(
b0000000000000000 )
#882
0#
#883
1#
1(
b0000000000000001 )
#884
0#
#885
1#
0(
b0000000000000000 )
#886
0#
#887
1#
1(
b0000000000000001 )
#888
0#
#889
1#
0(
b0000000000000000 )
#890
0#
#891
1#
1(
b0000000000000001 )
#892
0#
#893
1#
0(
b0000000000000000 )
#894
0#
#895
1#
1(
b0000000000000001 )
#896
0#
#897
1#
0(
b0000000000000000 )
#898
0#
#899
1#
1(
b0000000000000001 )
#900
0#
#901
1#
0(
b0000000000000000 )
#902
0#
#903
1#
1(
b0000000000000001 )
#904
0#
#905
1#
0(
b0000000000000000 )
#906
0#
#907
1#
1(
b0000000000000001 )
#908
0#
#909
1#
0(
b0000000000000000 )
#910
0#
#911
1#
1(
b0000000000000001 )
#912
0#
#913
1#
0(
b0000000000000000 )
#914
0#
#915
1#
1(
b0000000000000001 )
#916
0#
#917
1#
0(
b0000000000000000 )
#918
0#
#919
1#
1(
b0000000000000001 )
#920
0#
#921
1#
0(
b0000000000000000 )
#922
0#
#923
1#
1(
b0000000000000001 )
#924
0#
#925
1#
0(
b0000000000000000 )
#926
0#
#927
1#
1(
b0000000000000001 )
#928
0#
#929
1#
0(
b0000000000000000 )
#930
0#
#931
1#
1(
b0000000000000001 )
#932
0#
#933
1#
0(
b0000000000000000 )
#934
0#
#935
1#
1(
b0000000000000001 )
#936
0#
#937
1#
0(
b0000000000000000 )
#938
0#
#939
1#
1(
b0000000000000001 )
#940
0#
#941
1#
0(
b0000000000000000 )
#942
0#
#943
1#
1(
b0000000000000001 )
#944
0#
#945
1#
0(
b0000000000000000 )
#946
0#
#947
1#
1(
b0000000000000001 )
#948
0#
#949
1#
0(
b0000000000000000 )
#950
0#
#951
1#
1(
b0000000000000001 )
#952
0#
#953
1#
0(
b0000000000000000 )
#954
0#
#955
1#
1(
b0000000000000001 )
#956
0#
#957
1#
0(
b0000000000000000 )
#958
0#
#959
1#
1(
b0000000000000001 )
#960
0#
#961
1#
0(
b0000000000000000 )
#962
0#
#963
1#
1(
b0000000000000001 )
#964
0#
#965
1#
0(
b0000000000000000 )
#966
0#
#967
1#
1(
b0000000000000001 )
#968
0#
#969
1#
0(
b0000000000000000 )
#970
0#
#971
1#
1(
b0000000000000001 )
#972
0#
#973
1#
0(
b0000000000000000 )
#974
0#
#975
1#
1(
b0000000000000001 )
#976
0#
#977
1#
0(
b0000000000000000 )
#978
0#
#979
1#
1(
b0000000000000001 )
#980
0#
#981
1#
0(
b0000000000000000 )
#982
0#
#983
1#
1(
b0000000000000001 )
#984
0#
#985
1#
0(
b0000000000000000 )
#986
0#
#987
1#
1(
b0000000000000001 )
#988
0#
#989
1#
0(
b0000000000000000 )
#990
0#
#991
1#
1(
b0000000000000001 )
#992
0#
#993
1#
0(
b0000000000000000 )
#994
0#
#995
1#
1(
b0000000000000001 )
#996
0#
#997
1#
0(
b0000000000000000 )
#998
0#
#999
1#
1(
b0000000000000001 )
#1000
0#
#1001
1#
0(
b0000000000000000 )
#1002
0#
#1003
1#
1(
b0000000000000001 )
#1004
0#
#1005
1#
0(
b0000000000000000 )
#1006
0#
#1007
1#
1(
b0000000000000001 )
#1008
0#
#1009
1#
0(
b0000000000000000 )
#1010
0#
#1011
1#
1(
b0000000000000001 )
#1012
0#
#1013
1#
0(
b0000000000000000 )
#1014
0#
#1015
1#
1(
b0000000000000001 )
#1016
0#
#1017
1#
0(
b0000000000000000 )
#1018
0#
#1019
1#
1(
b0000000000000001 )
#1020
0#
#1021
1#
0(
b0000000000000000 )
#1022
0#
#1023
1#
1(
b0000000000000001 )
#1024
0#
#1025
1#
0(
b0000000000000000 )
#1026
0#
#1027
1#
1(
b0000000000000001 )
#1028
0#
#1029
1#
0(
b0000000000000000 )
#1030
0#
#1031
1#
1(
b0000000000000001 )
#1032
0#
#1033
1#
0(
b0000000000000000 )
#1034
0#
#1035
1#
1(
b0000000000000001 )
#1036
0#
#1037
1#
0(
b0000000000000000 )
#1038
0#
#1039
1#
1(
b0000000000000001 )
#1040
0#
#1041
1#
0(
b0000000000000000 )
#1042
0#
#1043
1#
1(
b0000000000000001 )
#1044
0#
#1045
1#
0(
b0000000000000000 )
#1046
0#
#1047
1#
1(
b0000000000000001 )
#1048
0#
#1049
1#
0(
b0000000000000000 )
#1050
0#
#1051
1#
1(
b0000000000000001 )
#1052
0#
#1053
1#
0(
b0000000000000000 )
#1054
0#
#1055
1#
1(
b0000000000000001 )
#1056
0#
#1057
1#
0(
b0000000000000000 )
#1058
0#
#1059
1#
1(
b0000000000000001 )
#1060
0#
#1061
1#
0(
b0000000000000000 )
