pwm_generator.v
module pwm_generator #(
    parameter COUNTER_WIDTH = 8,
    parameter DEFAULT_DUTY = 128
)(
    input wire clk,
    input wire rst_n,
    input wire enable,
    input wire [COUNTER_WIDTH-1:0] duty_cycle,
    input wire [COUNTER_WIDTH-1:0] period,
    output reg pwm_out
);

    // Counter register
    reg [COUNTER_WIDTH-1:0] counter;
    
    // Duty cycle register (allows for changing duty cycle without glitches)
    reg [COUNTER_WIDTH-1:0] duty_reg;
    
    // Period register
    reg [COUNTER_WIDTH-1:0] period_reg;
    
    // Update duty cycle and period at counter reset to avoid glitches
    always @(posedge clk or negedge rst_n) begin
        if (!rst_n) begin
            duty_reg <= DEFAULT_DUTY;
            period_reg <= {COUNTER_WIDTH{1'b1}}; // Default to max period
        end
        else if (counter == period_reg) begin
            duty_reg <= duty_cycle;
            period_reg <= period;
        end
    end
    
    // Counter logic
    always @(posedge clk or negedge rst_n) begin
        if (!rst_n) begin
            counter <= {COUNTER_WIDTH{1'b0}};
            pwm_out <= 1'b0;
        end
        else if (enable) begin
            // Reset counter when it reaches the period
            if (counter >= period_reg) begin
                counter <= {COUNTER_WIDTH{1'b0}};
            end
            else begin
                counter <= counter + 1'b1;
            end
            
            // Set output based on duty cycle comparison
            pwm_out <= (counter < duty_reg) ? 1'b1 : 1'b0;
        end
    end

endmodule

pwm_generator_sim.vcd
$version Generated by VerilatedVcd $end
$timescale 1ps $end
 $scope module TOP $end
  $var wire 1 & clk $end
  $var wire 1 ' rst_n $end
  $var wire 1 ( enable $end
  $var wire 8 ) duty_cycle [7:0] $end
  $var wire 8 * period [7:0] $end
  $var wire 1 + pwm_out $end
  $scope module pwm_generator $end
   $var wire 32 , COUNTER_WIDTH [31:0] $end
   $var wire 32 - DEFAULT_DUTY [31:0] $end
   $var wire 1 & clk $end
   $var wire 1 ' rst_n $end
   $var wire 1 ( enable $end
   $var wire 8 ) duty_cycle [7:0] $end
   $var wire 8 * period [7:0] $end
   $var wire 1 + pwm_out $end
   $var wire 8 # counter [7:0] $end
   $var wire 8 $ duty_reg [7:0] $end
   $var wire 8 % period_reg [7:0] $end
  $upscope $end
 $upscope $end
$enddefinitions $end


#0
b00000000 #
b00000000 $
b00000000 %
0&
0'
0(
b00000000 )
b00000000 *
0+
b00000000000000000000000000001000 ,
b00000000000000000000000010000000 -
#1
b10000000 $
b11111111 %
1&
#2
0&
1'
1(
b10000000 )
b11111111 *
#3
b00000001 #
1&
1+
#4
0&
#5
b00000010 #
1&
#6
0&
#7
b00000011 #
1&
#8
0&
#9
b00000100 #
1&
#10
0&
#11
b00000101 #
1&
#12
0&
#13
b00000110 #
1&
#14
0&
#15
b00000111 #
1&
#16
0&
#17
b00001000 #
1&
#18
0&
#19
b00001001 #
1&
#20
0&
#21
b00001010 #
1&
#22
0&
#23
b00001011 #
1&
#24
0&
#25
b00001100 #
1&
#26
0&
#27
b00001101 #
1&
#28
0&
#29
b00001110 #
1&
#30
0&
#31
b00001111 #
1&
#32
0&
#33
b00010000 #
1&
#34
0&
#35
b00010001 #
1&
#36
0&
#37
b00010010 #
1&
#38
0&
#39
b00010011 #
1&
#40
0&
#41
b00010100 #
1&
#42
0&
#43
b00010101 #
1&
#44
0&
#45
b00010110 #
1&
#46
0&
#47
b00010111 #
1&
#48
0&
#49
b00011000 #
1&
#50
0&
#51
b00011001 #
1&
#52
0&
#53
b00011010 #
1&
#54
0&
#55
b00011011 #
1&
#56
0&
#57
b00011100 #
1&
#58
0&
#59
b00011101 #
1&
#60
0&
#61
b00011110 #
1&
#62
0&
#63
b00011111 #
1&
#64
0&
#65
b00100000 #
1&
#66
0&
#67
b00100001 #
1&
#68
0&
#69
b00100010 #
1&
#70
0&
#71
b00100011 #
1&
#72
0&
#73
b00100100 #
1&
#74
0&
#75
b00100101 #
1&
#76
0&
#77
b00100110 #
1&
#78
0&
#79
b00100111 #
1&
#80
0&
#81
b00101000 #
1&
#82
0&
#83
b00101001 #
1&
#84
0&
#85
b00101010 #
1&
#86
0&
#87
b00101011 #
1&
#88
0&
#89
b00101100 #
1&
#90
0&
#91
b00101101 #
1&
#92
0&
#93
b00101110 #
1&
#94
0&
#95
b00101111 #
1&
#96
0&
#97
b00110000 #
1&
#98
0&
#99
b00110001 #
1&
#100
0&
#101
b00110010 #
1&
#102
0&
#103
b00110011 #
1&
#104
0&
#105
b00110100 #
1&
#106
0&
#107
b00110101 #
1&
#108
0&
#109
b00110110 #
1&
#110
0&
#111
b00110111 #
1&
#112
0&
#113
b00111000 #
1&
#114
0&
#115
b00111001 #
1&
#116
0&
#117
b00111010 #
1&
#118
0&
#119
b00111011 #
1&
#120
0&
#121
b00111100 #
1&
#122
0&
#123
b00111101 #
1&
#124
0&
#125
b00111110 #
1&
#126
0&
#127
b00111111 #
1&
#128
0&
#129
b01000000 #
1&
#130
0&
#131
b01000001 #
1&
#132
0&
#133
b01000010 #
1&
#134
0&
#135
b01000011 #
1&
#136
0&
#137
b01000100 #
1&
#138
0&
#139
b01000101 #
1&
#140
0&
#141
b01000110 #
1&
#142
0&
#143
b01000111 #
1&
#144
0&
#145
b01001000 #
1&
#146
0&
#147
b01001001 #
1&
#148
0&
#149
b01001010 #
1&
#150
0&
#151
b01001011 #
1&
#152
0&
#153
b01001100 #
1&
#154
0&
#155
b01001101 #
1&
#156
0&
#157
b01001110 #
1&
#158
0&
#159
b01001111 #
1&
#160
0&
#161
b01010000 #
1&
#162
0&
#163
b01010001 #
1&
#164
0&
#165
b01010010 #
1&
#166
0&
#167
b01010011 #
1&
#168
0&
#169
b01010100 #
1&
#170
0&
#171
b01010101 #
1&
#172
0&
#173
b01010110 #
1&
#174
0&
#175
b01010111 #
1&
#176
0&
#177
b01011000 #
1&
#178
0&
#179
b01011001 #
1&
#180
0&
#181
b01011010 #
1&
#182
0&
#183
b01011011 #
1&
#184
0&
#185
b01011100 #
1&
#186
0&
#187
b01011101 #
1&
#188
0&
#189
b01011110 #
1&
#190
0&
#191
b01011111 #
1&
#192
0&
#193
b01100000 #
1&
#194
0&
#195
b01100001 #
1&
#196
0&
#197
b01100010 #
1&
#198
0&
#199
b01100011 #
1&
#200
0&
#201
b01100100 #
1&
#202
0&
#203
b01100101 #
1&
#204
0&
#205
b01100110 #
1&
#206
0&
#207
b01100111 #
1&
#208
0&
#209
b01101000 #
1&
#210
0&
#211
b01101001 #
1&
#212
0&
#213
b01101010 #
1&
#214
0&
#215
b01101011 #
1&
#216
0&
#217
b01101100 #
1&
#218
0&
#219
b01101101 #
1&
#220
0&
#221
b01101110 #
1&
#222
0&
#223
b01101111 #
1&
#224
0&
#225
b01110000 #
1&
#226
0&
#227
b01110001 #
1&
#228
0&
#229
b01110010 #
1&
#230
0&
#231
b01110011 #
1&
#232
0&
#233
b01110100 #
1&
#234
0&
#235
b01110101 #
1&
#236
0&
#237
b01110110 #
1&
#238
0&
#239
b01110111 #
1&
#240
0&
#241
b01111000 #
1&
#242
0&
#243
b01111001 #
1&
#244
0&
#245
b01111010 #
1&
#246
0&
#247
b01111011 #
1&
#248
0&
#249
b01111100 #
1&
#250
0&
#251
b01111101 #
1&
#252
0&
#253
b01111110 #
1&
#254
0&
#255
b01111111 #
1&
#256
0&
#257
b10000000 #
1&
#258
0&
#259
b10000001 #
1&
0+
#260
0&
#261
b10000010 #
1&
#262
0&
#263
b10000011 #
1&
#264
0&
#265
b10000100 #
1&
#266
0&
#267
b10000101 #
1&
#268
0&
#269
b10000110 #
1&
#270
0&
#271
b10000111 #
1&
#272
0&
#273
b10001000 #
1&
#274
0&
#275
b10001001 #
1&
#276
0&
#277
b10001010 #
1&
#278
0&
#279
b10001011 #
1&
#280
0&
#281
b10001100 #
1&
#282
0&
#283
b10001101 #
1&
#284
0&
#285
b10001110 #
1&
#286
0&
#287
b10001111 #
1&
#288
0&
#289
b10010000 #
1&
#290
0&
#291
b10010001 #
1&
#292
0&
#293
b10010010 #
1&
#294
0&
#295
b10010011 #
1&
#296
0&
#297
b10010100 #
1&
#298
0&
#299
b10010101 #
1&
#300
0&
#301
b10010110 #
1&
#302
0&
#303
b10010111 #
1&
#304
0&
#305
b10011000 #
1&
#306
0&
#307
b10011001 #
1&
#308
0&
#309
b10011010 #
1&
#310
0&
#311
b10011011 #
1&
#312
0&
#313
b10011100 #
1&
#314
0&
#315
b10011101 #
1&
#316
0&
#317
b10011110 #
1&
#318
0&
#319
b10011111 #
1&
#320
0&
#321
b10100000 #
1&
#322
0&
#323
b10100001 #
1&
#324
0&
#325
b10100010 #
1&
#326
0&
#327
b10100011 #
1&
#328
0&
#329
b10100100 #
1&
#330
0&
#331
b10100101 #
1&
#332
0&
#333
b10100110 #
1&
#334
0&
#335
b10100111 #
1&
#336
0&
#337
b10101000 #
1&
#338
0&
#339
b10101001 #
1&
#340
0&
#341
b10101010 #
1&
#342
0&
#343
b10101011 #
1&
#344
0&
#345
b10101100 #
1&
#346
0&
#347
b10101101 #
1&
#348
0&
#349
b10101110 #
1&
#350
0&
#351
b10101111 #
1&
#352
0&
#353
b10110000 #
1&
#354
0&
#355
b10110001 #
1&
#356
0&
#357
b10110010 #
1&
#358
0&
#359
b10110011 #
1&
#360
0&
#361
b10110100 #
1&
#362
0&
#363
b10110101 #
1&
#364
0&
#365
b10110110 #
1&
#366
0&
#367
b10110111 #
1&
#368
0&
#369
b10111000 #
1&
#370
0&
#371
b10111001 #
1&
#372
0&
#373
b10111010 #
1&
#374
0&
#375
b10111011 #
1&
#376
0&
#377
b10111100 #
1&
#378
0&
#379
b10111101 #
1&
#380
0&
#381
b10111110 #
1&
#382
0&
#383
b10111111 #
1&
#384
0&
#385
b11000000 #
1&
#386
0&
#387
b11000001 #
1&
#388
0&
#389
b11000010 #
1&
#390
0&
#391
b11000011 #
1&
#392
0&
#393
b11000100 #
1&
#394
0&
#395
b11000101 #
1&
#396
0&
#397
b11000110 #
1&
#398
0&
#399
b11000111 #
1&
#400
0&
#401
b11001000 #
1&
#402
0&
#403
b11001001 #
1&
#404
0&
#405
b11001010 #
1&
#406
0&
#407
b11001011 #
1&
#408
0&
#409
b11001100 #
1&
#410
0&
#411
b11001101 #
1&
#412
0&
#413
b11001110 #
1&
#414
0&
#415
b11001111 #
1&
#416
0&
#417
b11010000 #
1&
#418
0&
#419
b11010001 #
1&
#420
0&
#421
b11010010 #
1&
#422
0&
#423
b11010011 #
1&
#424
0&
#425
b11010100 #
1&
#426
0&
#427
b11010101 #
1&
#428
0&
#429
b11010110 #
1&
#430
0&
#431
b11010111 #
1&
#432
0&
#433
b11011000 #
1&
#434
0&
#435
b11011001 #
1&
#436
0&
#437
b11011010 #
1&
#438
0&
#439
b11011011 #
1&
#440
0&
#441
b11011100 #
1&
#442
0&
#443
b11011101 #
1&
#444
0&
#445
b11011110 #
1&
#446
0&
#447
b11011111 #
1&
#448
0&
#449
b11100000 #
1&
#450
0&
#451
b11100001 #
1&
#452
0&
#453
b11100010 #
1&
#454
0&
#455
b11100011 #
1&
#456
0&
#457
b11100100 #
1&
#458
0&
#459
b11100101 #
1&
#460
0&
#461
b11100110 #
1&
#462
0&
#463
b11100111 #
1&
#464
0&
#465
b11101000 #
1&
#466
0&
#467
b11101001 #
1&
#468
0&
#469
b11101010 #
1&
#470
0&
#471
b11101011 #
1&
#472
0&
#473
b11101100 #
1&
#474
0&
#475
b11101101 #
1&
#476
0&
#477
b11101110 #
1&
#478
0&
#479
b11101111 #
1&
#480
0&
#481
b11110000 #
1&
#482
0&
#483
b11110001 #
1&
#484
0&
#485
b11110010 #
1&
#486
0&
#487
b11110011 #
1&
#488
0&
#489
b11110100 #
1&
#490
0&
#491
b11110101 #
1&
#492
0&
#493
b11110110 #
1&
#494
0&
#495
b11110111 #
1&
#496
0&
#497
b11111000 #
1&
#498
0&
#499
b11111001 #
1&
#500
0&
#501
b11111010 #
1&
#502
0&
#503
b11111011 #
1&
#504
0&
#505
b11111100 #
1&
#506
0&
#507
b11111101 #
1&
#508
0&
#509
b11111110 #
1&
#510
0&
#511
b11111111 #
1&
#512
0&
#513
b00000000 #
1&
#514
0&
#515
b00000001 #
1&
1+
#516
0&
#517
b00000010 #
1&
#518
0&
#519
b00000011 #
1&
#520
0&
#521
b00000100 #
1&
#522
0&
#523
b00000101 #
1&
#524
0&
#525
b00000110 #
1&
#526
0&
#527
b00000111 #
1&
#528
0&
#529
b00001000 #
1&
#530
0&
#531
b00001001 #
1&
#532
0&
#533
b00001010 #
1&
#534
0&
b00110010 )
b11001000 *
#535
b00001011 #
1&
#536
0&
#537
b00001100 #
1&
#538
0&
#539
b00001101 #
1&
#540
0&
#541
b00001110 #
1&
#542
0&
#543
b00001111 #
1&
#544
0&
#545
b00010000 #
1&
#546
0&
#547
b00010001 #
1&
#548
0&
#549
b00010010 #
1&
#550
0&
#551
b00010011 #
1&
#552
0&
#553
b00010100 #
1&
#554
0&
#555
b00010101 #
1&
#556
0&
#557
b00010110 #
1&
#558
0&
#559
b00010111 #
1&
#560
0&
#561
b00011000 #
1&
#562
0&
#563
b00011001 #
1&
#564
0&
#565
b00011010 #
1&
#566
0&
#567
b00011011 #
1&
#568
0&
#569
b00011100 #
1&
#570
0&
#571
b00011101 #
1&
#572
0&
#573
b00011110 #
1&
#574
0&
#575
b00011111 #
1&
#576
0&
#577
b00100000 #
1&
#578
0&
#579
b00100001 #
1&
#580
0&
#581
b00100010 #
1&
#582
0&
#583
b00100011 #
1&
#584
0&
#585
b00100100 #
1&
#586
0&
#587
b00100101 #
1&
#588
0&
#589
b00100110 #
1&
#590
0&
#591
b00100111 #
1&
#592
0&
#593
b00101000 #
1&
#594
0&
#595
b00101001 #
1&
#596
0&
#597
b00101010 #
1&
#598
0&
#599
b00101011 #
1&
#600
0&
#601
b00101100 #
1&
#602
0&
#603
b00101101 #
1&
#604
0&
#605
b00101110 #
1&
#606
0&
#607
b00101111 #
1&
#608
0&
#609
b00110000 #
1&
#610
0&
#611
b00110001 #
1&
#612
0&
#613
b00110010 #
1&
#614
0&
#615
b00110011 #
1&
#616
0&
#617
b00110100 #
1&
#618
0&
#619
b00110101 #
1&
#620
0&
#621
b00110110 #
1&
#622
0&
#623
b00110111 #
1&
#624
0&
#625
b00111000 #
1&
#626
0&
#627
b00111001 #
1&
#628
0&
#629
b00111010 #
1&
#630
0&
#631
b00111011 #
1&
#632
0&
#633
b00111100 #
1&
#634
0&
#635
b00111101 #
1&
#636
0&
#637
b00111110 #
1&
#638
0&
#639
b00111111 #
1&
#640
0&
#641
b01000000 #
1&
#642
0&
#643
b01000001 #
1&
#644
0&
#645
b01000010 #
1&
#646
0&
#647
b01000011 #
1&
#648
0&
#649
b01000100 #
1&
#650
0&
#651
b01000101 #
1&
#652
0&
#653
b01000110 #
1&
#654
0&
#655
b01000111 #
1&
#656
0&
#657
b01001000 #
1&
#658
0&
#659
b01001001 #
1&
#660
0&
#661
b01001010 #
1&
#662
0&
#663
b01001011 #
1&
#664
0&
#665
b01001100 #
1&
#666
0&
#667
b01001101 #
1&
#668
0&
#669
b01001110 #
1&
#670
0&
#671
b01001111 #
1&
#672
0&
#673
b01010000 #
1&
#674
0&
#675
b01010001 #
1&
#676
0&
#677
b01010010 #
1&
#678
0&
#679
b01010011 #
1&
#680
0&
#681
b01010100 #
1&
#682
0&
#683
b01010101 #
1&
#684
0&
#685
b01010110 #
1&
#686
0&
#687
b01010111 #
1&
#688
0&
#689
b01011000 #
1&
#690
0&
#691
b01011001 #
1&
#692
0&
#693
b01011010 #
1&
#694
0&
#695
b01011011 #
1&
#696
0&
#697
b01011100 #
1&
#698
0&
#699
b01011101 #
1&
#700
0&
#701
b01011110 #
1&
#702
0&
#703
b01011111 #
1&
#704
0&
#705
b01100000 #
1&
#706
0&
#707
b01100001 #
1&
#708
0&
#709
b01100010 #
1&
#710
0&
#711
b01100011 #
1&
#712
0&
#713
b01100100 #
1&
#714
0&
#715
b01100101 #
1&
#716
0&
#717
b01100110 #
1&
#718
0&
#719
b01100111 #
1&
#720
0&
#721
b01101000 #
1&
#722
0&
#723
b01101001 #
1&
#724
0&
#725
b01101010 #
1&
#726
0&
#727
b01101011 #
1&
#728
0&
#729
b01101100 #
1&
#730
0&
#731
b01101101 #
1&
#732
0&
#733
b01101110 #
1&
#734
0&
#735
b01101111 #
1&
#736
0&
#737
b01110000 #
1&
#738
0&
#739
b01110001 #
1&
#740
0&
#741
b01110010 #
1&
#742
0&
#743
b01110011 #
1&
#744
0&
#745
b01110100 #
1&
#746
0&
#747
b01110101 #
1&
#748
0&
#749
b01110110 #
1&
#750
0&
#751
b01110111 #
1&
#752
0&
#753
b01111000 #
1&
#754
0&
#755
b01111001 #
1&
#756
0&
#757
b01111010 #
1&
#758
0&
#759
b01111011 #
1&
#760
0&
#761
b01111100 #
1&
#762
0&
#763
b01111101 #
1&
#764
0&
#765
b01111110 #
1&
#766
0&
#767
b01111111 #
1&
#768
0&
#769
b10000000 #
1&
#770
0&
#771
b10000001 #
1&
0+
#772
0&
#773
b10000010 #
1&
#774
0&
#775
b10000011 #
1&
#776
0&
#777
b10000100 #
1&
#778
0&
#779
b10000101 #
1&
#780
0&
#781
b10000110 #
1&
#782
0&
#783
b10000111 #
1&
#784
0&
#785
b10001000 #
1&
#786
0&
#787
b10001001 #
1&
#788
0&
#789
b10001010 #
1&
#790
0&
#791
b10001011 #
1&
#792
0&
#793
b10001100 #
1&
#794
0&
#795
b10001101 #
1&
#796
0&
#797
b10001110 #
1&
#798
0&
#799
b10001111 #
1&
#800
0&
#801
b10010000 #
1&
#802
0&
#803
b10010001 #
1&
#804
0&
#805
b10010010 #
1&
#806
0&
#807
b10010011 #
1&
#808
0&
#809
b10010100 #
1&
#810
0&
#811
b10010101 #
1&
#812
0&
#813
b10010110 #
1&
#814
0&
#815
b10010111 #
1&
#816
0&
#817
b10011000 #
1&
#818
0&
#819
b10011001 #
1&
#820
0&
#821
b10011010 #
1&
#822
0&
#823
b10011011 #
1&
#824
0&
#825
b10011100 #
1&
#826
0&
#827
b10011101 #
1&
#828
0&
#829
b10011110 #
1&
#830
0&
#831
b10011111 #
1&
#832
0&
#833
b10100000 #
1&
#834
0&
#835
b10100001 #
1&
#836
0&
#837
b10100010 #
1&
#838
0&
#839
b10100011 #
1&
#840
0&
#841
b10100100 #
1&
#842
0&
#843
b10100101 #
1&
#844
0&
#845
b10100110 #
1&
#846
0&
#847
b10100111 #
1&
#848
0&
#849
b10101000 #
1&
#850
0&
#851
b10101001 #
1&
#852
0&
#853
b10101010 #
1&
#854
0&
#855
b10101011 #
1&
#856
0&
#857
b10101100 #
1&
#858
0&
#859
b10101101 #
1&
#860
0&
#861
b10101110 #
1&
#862
0&
#863
b10101111 #
1&
#864
0&
#865
b10110000 #
1&
#866
0&
#867
b10110001 #
1&
#868
0&
#869
b10110010 #
1&
#870
0&
#871
b10110011 #
1&
#872
0&
#873
b10110100 #
1&
#874
0&
#875
b10110101 #
1&
#876
0&
#877
b10110110 #
1&
#878
0&
#879
b10110111 #
1&
#880
0&
#881
b10111000 #
1&
#882
0&
#883
b10111001 #
1&
#884
0&
#885
b10111010 #
1&
#886
0&
#887
b10111011 #
1&
#888
0&
#889
b10111100 #
1&
#890
0&
#891
b10111101 #
1&
#892
0&
#893
b10111110 #
1&
#894
0&
#895
b10111111 #
1&
#896
0&
#897
b11000000 #
1&
#898
0&
#899
b11000001 #
1&
#900
0&
#901
b11000010 #
1&
#902
0&
#903
b11000011 #
1&
#904
0&
#905
b11000100 #
1&
#906
0&
#907
b11000101 #
1&
#908
0&
#909
b11000110 #
1&
#910
0&
#911
b11000111 #
1&
#912
0&
#913
b11001000 #
1&
#914
0&
#915
b11001001 #
1&
#916
0&
#917
b11001010 #
1&
#918
0&
#919
b11001011 #
1&
#920
0&
#921
b11001100 #
1&
#922
0&
#923
b11001101 #
1&
#924
0&
#925
b11001110 #
1&
#926
0&
#927
b11001111 #
1&
#928
0&
#929
b11010000 #
1&
#930
0&
#931
b11010001 #
1&
#932
0&
#933
b11010010 #
1&
#934
0&
#935
b11010011 #
1&
#936
0&
#937
b11010100 #
1&
#938
0&
#939
b11010101 #
1&
#940
0&
#941
b11010110 #
1&
#942
0&
#943
b11010111 #
1&
#944
0&
#945
b11011000 #
1&
#946
0&
#947
b11011001 #
1&
#948
0&
#949
b11011010 #
1&
#950
0&
#951
b11011011 #
1&
#952
0&
#953
b11011100 #
1&
#954
0&
#955
b11011101 #
1&
#956
0&
#957
b11011110 #
1&
#958
0&
#959
b11011111 #
1&
#960
0&
#961
b11100000 #
1&
#962
0&
#963
b11100001 #
1&
#964
0&
#965
b11100010 #
1&
#966
0&
#967
b11100011 #
1&
#968
0&
#969
b11100100 #
1&
#970
0&
#971
b11100101 #
1&
#972
0&
#973
b11100110 #
1&
#974
0&
#975
b11100111 #
1&
#976
0&
#977
b11101000 #
1&
#978
0&
#979
b11101001 #
1&
#980
0&
#981
b11101010 #
1&
#982
0&
#983
b11101011 #
1&
#984
0&
#985
b11101100 #
1&
#986
0&
#987
b11101101 #
1&
#988
0&
#989
b11101110 #
1&
#990
0&
#991
b11101111 #
1&
#992
0&
#993
b11110000 #
1&
#994
0&
#995
b11110001 #
1&
#996
0&
#997
b11110010 #
1&
#998
0&
#999
b11110011 #
1&
#1000
0&
#1001
b11110100 #
1&
#1002
0&
#1003
b11110101 #
1&
#1004
0&
#1005
b11110110 #
1&
#1006
0&
#1007
b11110111 #
1&
#1008
0&
#1009
b11111000 #
1&
#1010
0&
#1011
b11111001 #
1&
#1012
0&
#1013
b11111010 #
1&
#1014
0&
#1015
b11111011 #
1&
#1016
0&
#1017
b11111100 #
1&
#1018
0&
#1019
b11111101 #
1&
#1020
0&
#1021
b11111110 #
1&
#1022
0&
#1023
b11111111 #
1&
#1024
0&
#1025
b00000000 #
b00110010 $
b11001000 %
1&
#1026
0&
#1027
b00000001 #
1&
1+
#1028
0&
#1029
b00000010 #
1&
#1030
0&
#1031
b00000011 #
1&
#1032
0&
#1033
b00000100 #
1&
#1034
0&
#1035
b00000101 #
1&
#1036
0&
#1037
b00000110 #
1&
#1038
0&
#1039
b00000111 #
1&
#1040
0&
#1041
b00001000 #
1&
#1042
0&
#1043
b00001001 #
1&
#1044
0&
#1045
b00001010 #
1&
#1046
0&
#1047
b00001011 #
1&
#1048
0&
#1049
b00001100 #
1&
#1050
0&
#1051
b00001101 #
1&
#1052
0&
#1053
b00001110 #
1&
#1054
0&
#1055
b00001111 #
1&
#1056
0&
#1057
b00010000 #
1&
#1058
0&
#1059
b00010001 #
1&
#1060
0&
#1061
b00010010 #
1&
#1062
0&
#1063
b00010011 #
1&
#1064
0&
#1065
b00010100 #
1&
#1066
0&
#1067
b00010101 #
1&
#1068
0&
#1069
b00010110 #
1&
#1070
0&
#1071
b00010111 #
1&
#1072
0&
#1073
b00011000 #
1&
#1074
0&
#1075
b00011001 #
1&
#1076
0&
#1077
b00011010 #
1&
#1078
0&
#1079
b00011011 #
1&
#1080
0&
#1081
b00011100 #
1&
#1082
0&
#1083
b00011101 #
1&
#1084
0&
#1085
b00011110 #
1&
#1086
0&
#1087
b00011111 #
1&
#1088
0&
#1089
b00100000 #
1&
#1090
0&
#1091
b00100001 #
1&
#1092
0&
#1093
b00100010 #
1&
#1094
0&
#1095
b00100011 #
1&
#1096
0&
#1097
b00100100 #
1&
#1098
0&
#1099
b00100101 #
1&
#1100
0&
#1101
b00100110 #
1&
#1102
0&
#1103
b00100111 #
1&
#1104
0&
#1105
b00101000 #
1&
#1106
0&
#1107
b00101001 #
1&
#1108
0&
#1109
b00101010 #
1&
#1110
0&
#1111
b00101011 #
1&
#1112
0&
#1113
b00101100 #
1&
#1114
0&
#1115
b00101101 #
1&
#1116
0&
#1117
b00101110 #
1&
#1118
0&
#1119
b00101111 #
1&
#1120
0&
#1121
b00110000 #
1&
#1122
0&
#1123
b00110001 #
1&
#1124
0&
#1125
b00110010 #
1&
#1126
0&
#1127
b00110011 #
1&
0+
#1128
0&
#1129
b00110100 #
1&
#1130
0&
#1131
b00110101 #
1&
#1132
0&
#1133
b00110110 #
1&
#1134
0&
#1135
b00110111 #
1&
#1136
0&
#1137
b00111000 #
1&
#1138
0&
#1139
b00111001 #
1&
#1140
0&
#1141
b00111010 #
1&
#1142
0&
#1143
b00111011 #
1&
#1144
0&
#1145
b00111100 #
1&
#1146
0&
#1147
b00111101 #
1&
#1148
0&
#1149
b00111110 #
1&
#1150
0&
#1151
b00111111 #
1&
#1152
0&
#1153
b01000000 #
1&
#1154
0&
#1155
b01000001 #
1&
#1156
0&
#1157
b01000010 #
1&
#1158
0&
#1159
b01000011 #
1&
#1160
0&
#1161
b01000100 #
1&
#1162
0&
#1163
b01000101 #
1&
#1164
0&
#1165
b01000110 #
1&
#1166
0&
#1167
b01000111 #
1&
#1168
0&
#1169
b01001000 #
1&
#1170
0&
#1171
b01001001 #
1&
#1172
0&
#1173
b01001010 #
1&
#1174
0&
#1175
b01001011 #
1&
#1176
0&
#1177
b01001100 #
1&
#1178
0&
#1179
b01001101 #
1&
#1180
0&
#1181
b01001110 #
1&
#1182
0&
#1183
b01001111 #
1&
#1184
0&
#1185
b01010000 #
1&
#1186
0&
#1187
b01010001 #
1&
#1188
0&
#1189
b01010010 #
1&
#1190
0&
#1191
b01010011 #
1&
#1192
0&
#1193
b01010100 #
1&
#1194
0&
#1195
b01010101 #
1&
#1196
0&
#1197
b01010110 #
1&
#1198
0&
#1199
b01010111 #
1&
#1200
0&
#1201
b01011000 #
1&
#1202
0&
#1203
b01011001 #
1&
#1204
0&
#1205
b01011010 #
1&
#1206
0&
#1207
b01011011 #
1&
#1208
0&
#1209
b01011100 #
1&
#1210
0&
#1211
b01011101 #
1&
#1212
0&
#1213
b01011110 #
1&
#1214
0&
#1215
b01011111 #
1&
#1216
0&
#1217
b01100000 #
1&
#1218
0&
#1219
b01100001 #
1&
#1220
0&
#1221
b01100010 #
1&
#1222
0&
#1223
b01100011 #
1&
#1224
0&
#1225
b01100100 #
1&
#1226
0&
#1227
b01100101 #
1&
#1228
0&
#1229
b01100110 #
1&
#1230
0&
#1231
b01100111 #
1&
#1232
0&
#1233
b01101000 #
1&
#1234
0&
#1235
b01101001 #
1&
#1236
0&
#1237
b01101010 #
1&
#1238
0&
#1239
b01101011 #
1&
#1240
0&
#1241
b01101100 #
1&
#1242
0&
#1243
b01101101 #
1&
#1244
0&
#1245
b01101110 #
1&
#1246
0&
#1247
b01101111 #
1&
#1248
0&
#1249
b01110000 #
1&
#1250
0&
#1251
b01110001 #
1&
#1252
0&
#1253
b01110010 #
1&
#1254
0&
#1255
b01110011 #
1&
#1256
0&
#1257
b01110100 #
1&
#1258
0&
#1259
b01110101 #
1&
#1260
0&
#1261
b01110110 #
1&
#1262
0&
#1263
b01110111 #
1&
#1264
0&
#1265
b01111000 #
1&
#1266
0&
#1267
b01111001 #
1&
#1268
0&
#1269
b01111010 #
1&
#1270
0&
#1271
b01111011 #
1&
#1272
0&
#1273
b01111100 #
1&
#1274
0&
#1275
b01111101 #
1&
#1276
0&
#1277
b01111110 #
1&
#1278
0&
#1279
b01111111 #
1&
#1280
0&
#1281
b10000000 #
1&
#1282
0&
#1283
b10000001 #
1&
#1284
0&
#1285
b10000010 #
1&
#1286
0&
#1287
b10000011 #
1&
#1288
0&
#1289
b10000100 #
1&
#1290
0&
#1291
b10000101 #
1&
#1292
0&
#1293
b10000110 #
1&
#1294
0&
#1295
b10000111 #
1&
#1296
0&
#1297
b10001000 #
1&
#1298
0&
#1299
b10001001 #
1&
#1300
0&
#1301
b10001010 #
1&
#1302
0&
#1303
b10001011 #
1&
#1304
0&
#1305
b10001100 #
1&
#1306
0&
#1307
b10001101 #
1&
#1308
0&
#1309
b10001110 #
1&
#1310
0&
#1311
b10001111 #
1&
#1312
0&
#1313
b10010000 #
1&
#1314
0&
#1315
b10010001 #
1&
#1316
0&
#1317
b10010010 #
1&
#1318
0&
#1319
b10010011 #
1&
#1320
0&
#1321
b10010100 #
1&
#1322
0&
#1323
b10010101 #
1&
#1324
0&
#1325
b10010110 #
1&
#1326
0&
#1327
b10010111 #
1&
#1328
0&
#1329
b10011000 #
1&
#1330
0&
#1331
b10011001 #
1&
#1332
0&
#1333
b10011010 #
1&
#1334
0&
#1335
b10011011 #
1&
#1336
0&
#1337
b10011100 #
1&
#1338
0&
#1339
b10011101 #
1&
#1340
0&
#1341
b10011110 #
1&
#1342
0&
#1343
b10011111 #
1&
#1344
0&
#1345
b10100000 #
1&
#1346
0&
#1347
b10100001 #
1&
#1348
0&
#1349
b10100010 #
1&
#1350
0&
#1351
b10100011 #
1&
#1352
0&
#1353
b10100100 #
1&
#1354
0&
#1355
b10100101 #
1&
#1356
0&
#1357
b10100110 #
1&
#1358
0&
#1359
b10100111 #
1&
#1360
0&
#1361
b10101000 #
1&
#1362
0&
#1363
b10101001 #
1&
#1364
0&
#1365
b10101010 #
1&
#1366
0&
#1367
b10101011 #
1&
#1368
0&
#1369
b10101100 #
1&
#1370
0&
#1371
b10101101 #
1&
#1372
0&
#1373
b10101110 #
1&
#1374
0&
#1375
b10101111 #
1&
#1376
0&
#1377
b10110000 #
1&
#1378
0&
#1379
b10110001 #
1&
#1380
0&
#1381
b10110010 #
1&
#1382
0&
#1383
b10110011 #
1&
#1384
0&
#1385
b10110100 #
1&
#1386
0&
#1387
b10110101 #
1&
#1388
0&
#1389
b10110110 #
1&
#1390
0&
#1391
b10110111 #
1&
#1392
0&
#1393
b10111000 #
1&
#1394
0&
#1395
b10111001 #
1&
#1396
0&
#1397
b10111010 #
1&
#1398
0&
#1399
b10111011 #
1&
#1400
0&
#1401
b10111100 #
1&
#1402
0&
#1403
b10111101 #
1&
#1404
0&
